Workbook
Name CapitalFormula: '[1]Capital Reports'!$E$15:$BC$17
Name DOT: #REF!
Name FromYear: [1]MainSheet!$B$14
Name GrandTotals: '[1]Capital Reports'!$E$75:$BC$77
Name HeaderRow: [1]MainSheet!$B$1
Name Inf: #REF!
Name Inflation: [2]InflationSheet!$O$2:$BL$2
Name InflationFactor: [1]MainSheet!$B$13
Name INPUT: #REF!
Name Item: #REF!
Name ItemColumn: [1]MainSheet!$B$2
Name Linear_Asset: #REF!
Name LinearAssetColumn: [1]MainSheet!$B$6
Name Major_Maint_Duration__Years: #REF!
Name Major_Maint_Total_Expense: #REF!
Name Major_Maint_Year: #REF!
Name MajorMaintCostColumn: [1]MainSheet!$B$11
Name MajorMaintDurationColumn: [1]MainSheet!$B$12
Name MajorMaintYearColumn: [1]MainSheet!$B$10
Name NameTable: [1]MainSheet!$A$1:$B$15
Name Original_Cost: #REF!
Name Original_Installation_Year: #REF!
Name Original_Life: #REF!
Name OriginalCostColumn: [1]MainSheet!$B$4
Name OriginalLifeColumn: [1]MainSheet!$B$5
Name OriginalYearInstalledColumn: [1]MainSheet!$B$3
Name Replace_Cost: #REF!
Name Replace_Life: #REF!
Name Replace_Year: #REF!
Name ReplaceCostColumn: [1]MainSheet!$B$8
Name ReplaceLifeColumn: [1]MainSheet!$B$9
Name ReplaceYearColumn: [1]MainSheet!$B$7
Name Source_Book: #REF!
Name Source_Row: #REF!
Name Source_Sheet: #REF!
Name Title: #REF!
Name Total: #REF!
Name ToYear: [1]MainSheet!$B$15
Name Version: [1]MainSheet!$B$16
Name Years: #REF!

Sheet Instructions
B2: Capital Job Initiation (JI)
A3: Introduction
B4: The Job Initiation Form is a working document for managing and directing a capital project. It is the focal point at which information relating to the project is gathered for approval by Management and serves to remind all of the project scope. A clear understanding of the project ensures that the major needs are identified and incorporated into the planning of the project.
B5: The primary use of the document is to act as a base document against which approval to advance can be given, progress can be assessed, and changes can be made as needed.
B6: Parts of the JI Form might need to be amended as the project progresses.
A8: Process Flow
B9: Complete JI Form tab
B10: Complete Cash Flow tab
B11: Submit JI Form and Cash Flow to DU President/CEO for approval
B12: Acquisition or construction of new facilities shall be done in accordance with the Army and Management Committee’s approved capital plan, or modifications to the contracts. Prior to approving the acquisition or construction of a new asset, management shall be presented with an estimate of the full cost to purchase or construct the new asset. Upon determination of approval, management and/or the Management Committee will ensure resources are adequate to meet these needs.
B13: Upon approval, signed documents should be forwarded to Accounting at USA.
B14: Job #s will be created in NAV Job System and provided via email to requesting party.
B15: Copies of all signed contracts are provided to Accounting and filed in the job file (which will be incorporated into the CPR (Continuing Property Record)).
B16: A copy of all project plans and specifications are provided to accounting and kept in the job file.
B18: All change orders require approval by management.
B19: Updates/changes are provided to Accounting regularly.
B20: Notify Accounting when the project is scheduled to be completed and placed into service.
A22: JI Form - Help
B23: General Definitions
B25: JI Form - Job Initiation Form
B27: Capital Projects - Defined as investor owned or contributed plant (self constructed or subcontracted by bid award). Job tasks are defined to ensure proper classification upon completion of the project.
B29: General Help
B31: JI Form - The Job Initiation Form is integrated with links to help the end-user complete the form. Tips can be found within the JI Form by hovering the mouse pointer on the name of a field. Further information can be found by clicking directly on the name of a field.
B33: Only enter data into the highlighted cells and the drop-down selection cells. Highlighting will automatically disappear from each cell as data is entered into the cell. If all else fails, fill the form out by hand (the drop down values for each field are listed in the help description for each field), or seek assistance from Accounting.
B36: Help - JI Form - Field Assistance
B38: Job # This field will be completed by Accounting | C38: return to field
B40: Job Description (Short) This field will carry forward as the name or title of the job. Be as specific as you can, within space provided. Maximum of 50 characters. | C40: return to field
B42: Job Description (Long) Explain what the project is setting out to achieve. Be as specific as you can. Target: One paragraph. | C42: return to field
B44: Division Using the drop down menu, select the applicable Division (Corporate, Fort Wainwright, Fort Richardson or Fort Greely). Only one selection is permitted per JI Form. | C44: return to field
B46: Utility Using the drop down menu, select the applicable Utility (Corporate, Natural Gas, Water, Waste Water, Electric Distribution, Central Heating Plant). Only one selection is permitted per JI Form. | C46: return to field
B48: Requested by Using the drop down menu, select the applicable option (1. Original Contract, 2. Contract Mod, 3. COR MOD, 4. Other MOD, 5. Corporate, 6. An Individual). Only one selection is permitted per JI Form. Data in this field should correspond with those in the field titled, "Requested By Description". | C48: return to field
B50: Requested by Description Based on the selection in the "Requested By" field, enter the corresponding information: select the applicable option | C50: return to field
B51: 1. Original Contract - Enter Letter/# designator (i.e. HCU10)
B52: 2. Contract Mod - Enter Letter/# designator (i.e. HCU10)
B53: 3. COR MOD (Contracting Officer's Rep MOD) - Enter Letter/# designator
B54: 4. Other MOD - Enter Letter/# designator
B55: 5. Corporate - Enter Corporate Department or Title (i.e. IT, etc.)
B56: 6. An Individual - This should be the last choice! Enter the name of person
B57: Data in this field should correspond with those in the field titled, "Requested By".
B59: Project Manager Enter the name of the Project Manager/Requestor for this job. | C59: return to field
B61: Start Date Enter the start date of the project. This is the date that we will begin spending money (manpower, supplies, contracts, etc.). | C61: return to field
B63: Expected Completion Date Enter the expected end of construction date. (Date facility is expected to be "used & useful"and placed into service.) | C63: return to field
B65: Subclasses Enter one or more retirement units if known. | C65: return to field
B66: A listing of subclasses is located in the Subclasses tab.
B67: Data in this field should correspond with those in the field titled, "Subclass Cost Estimate".
B69: Subclass Cost Estimate Enter the cost estimate of each of the retirement units if known. The total of all subclass estimates should be the same as the full cost estimate for the Job. | C69: return to field
B70: Data in this field should correspond with those in the field titled, "Subclasses".
B72: Cost Estimate Enter the cost estimate of the entire job. The total of all subclass estimates should be the same as the full cost estimate for the Job. Updates should be provided to Accounting as better information becomes available. | C72: return to field
B74: Cash Flow Estimate Provide a current Cash Flow estimate within the Cash Flow tab, or attach to the completed JI Form for approval. Cash Flow should be broken out by year/quarter or year/month. Updates should be provided to Accounting as better information becomes available. | C74: return to field
B75: Cash Flow tab
B77: Description of Retirements List the associated capital items that will be removed from service (demolished, retired, scrapped, sold, etc.) due to the completion of this job. Please include description, age, size, quantity, manufacturer, location, etc. While this may not be known at the time a job is initiated, it will have to be done at some time during the life of the job! Close coordination with Accounting / GIS will be required. | C77: return to field
B79: Additional Comments List any additional comments, pictures, maps, etc. for reference in the Job file. | C79: return to field
B81: Your Name Enter your name | C81: return to field
B89: Capital Job Completion (JC)
A90: Introduction
B91: The Job Completion Form is a trigger document for alerting all to the acquisition of and begin the final capitalization of a capital project. It is the trigger point at which information relating to the finalization of the project is reviewed by Management and serves to update and capsulate all of the information for the Property Record. A clear understanding of what was acquired throughout the project ensures that the acquisitions are identified and incorporated into the final costs and recording of the fixed asset.
B92: The primary use of the document is to act as a base document against which approval to close can be given, final paperwork can be requested, and the job file can be prepared for final review prior to close.
A95: Process Flow
B96: Complete Job Completion Form tab
B98: Submit Job Completion Form to DU President/CEO for approval
B99: Acquisition or construction of new facilities shall be done in accordance with the Army and Management Committee’s approved capital plan, or modifications to the contracts. Prior to approving the acquisition or construction of a new asset, management shall be presented with an estimate of the full cost to purchase or construct the new asset. Upon determination of approval, management and/or the Management Committee will ensure resources are adequate to meet these needs.
B100: Upon approval, signed documents should be forwarded to Accounting at USA.
B101: Copies of all signed contracts, outstanding invoices, drawings, pictures, diagrams, etc. are provided to Accounting and filed in the job file (which will be incorporated into the CPR (Continuing Property Record)).
B102: A copy of all project plans and specifications are provided to accounting and kept in the job file.
B103: Job records will be reviewed for completeness and prepared to be reviewed by the Project Manager and Management.
B104: Updates/changes are provided to Accounting ASAP.
B106: Notify Accounting when the project is completed and placed into service.
A109: Job Completion Form - Help
B110: General Definitions
B112: JC Form - Job Completion Form
B114: Capital Projects - Defined as investor owned or contributed plant (self constructed or subcontracted by bid award). Job tasks are defined to ensure proper classification upon completion of the project.
B116: General Help
B118: JC Form - The Job Completion Form is integrated with links to help the end-user complete the form. Tips can be found within the JC Form by hovering the mouse pointer on the name of a field. Further information can be found by clicking directly on the name of a field.
B120: Only enter data into the highlighted cells and the drop-down selection cells. Highlighting will automatically disappear from each cell as data is entered into the cell. If all else fails, fill the form out by hand (the drop down values for each field are listed in the help description for each field), or seek assistance from Accounting.
B123: Help - JC Form - Field Assistance
B125: Job # Enter the Job # of the job that is due to be completed | C125: return to field
B127: Job Description (Short) This field will carry forward as the name or title of the job and capital asset. Be as specific as you can, within space provided. Maximum of 50 characters. | C127: return to field
B129: Job Description (Long) Explain what the project is setting out to achieve. Be as specific as you can. Target: One paragraph. | C129: return to field
B131: Division Using the drop down menu, select the applicable Division (Corporate, Fort Wainwright, Fort Richardson or Fort Greely). Only one selection is permitted per Form. | C131: return to field
B133: Utility Using the drop down menu, select the applicable Utility (Corporate, Natural Gas, Water, Waste Water, Electric Distribution, Central Heating Plant). Only one selection is permitted per Form. | C133: return to field
B135: Requested by Using the drop down menu, select the applicable option (1. Original Contract, 2. Contract Mod, 3. COR MOD, 4. Other MOD, 5. Corporate, 6. An Individual). Only one selection is permitted per JC Form. Data in this field should correspond with those in the field titled, "Requested By Description". | C135: return to field
B137: Requested by Description Based on the selection in the "Requested By" field, enter the corresponding information: select the applicable option | C137: return to field
B138: 1. Original Contract - Enter Letter/# designator (i.e. HCU10)
B139: 2. Contract Mod - Enter Letter/# designator (i.e. HCU10)
B140: 3. COR MOD (Contracting Officer's Rep MOD) - Enter Letter/# designator
B141: 4. Other MOD - Enter Letter/# designator
B142: 5. Corporate - Enter Corporate Department or Title (i.e. IT, etc.)
B143: 6. An Individual - This should be the last choice! Enter the name of person
B144: Data in this field should correspond with those in the field titled, "Requested By".
B146: Project Manager Enter the name of the Final Project Manager/Requestor for this job. | C146: return to field
B148: Start Date Enter the start date of the project. This is the date that we began spending money (manpower, supplies, contracts, etc.). | C148: return to field
B150: Final Completion Date Enter the actual or pending end of construction date. (Date facility is expected to be "used & useful" and placed into service.) | C150: return to field
B152: Short Description (Subclass) Enter brief description of acquisition for each subclass row selected. | C152: return to field
B153: Data in this field should correspond with those in the field titled, "Subclass".
B155: Qty (Subclass) Enter quantity of acquisition for each subclass row selected. | C155: return to field
B156: Data in this field should correspond with those in the field titled, "Subclass".
B158: Expected Life (years) If you feel the estimated useful GAAP life listed in the Subclass tab is not appropriate for this asset, please enter your best estimate for the useful life. | C158: return to field
B159: Data in this field should correspond with those in the field titled, "Subclass".
B161: Subclass Enter one or more retirement units if known. | C161: return to field
B162: A listing of subclasses is located in the Subclasses tab.
...

Sheet Job Initiation Form
G1: =IF(ISBLANK('form picklists'!G2)=TRUE,"",'form picklists'!G2&", "&'form picklists'!H2&", "&'form picklists'!I2)
G2: =IF(ISBLANK('form picklists'!G3)=TRUE,"",'form picklists'!G3&", "&'form picklists'!H3&", "&'form picklists'!I3) -> DHS 211 8, CHPP Plant, Boiler Plant Equip - 75 years
G3: =IF(ISBLANK('form picklists'!G4)=TRUE,"",'form picklists'!G4&", "&'form picklists'!H4&", "&'form picklists'!I4) -> DHS 212 8, CHPP Plant, Boiler Plant Equip - 50 years
G4: =IF(ISBLANK('form picklists'!G5)=TRUE,"",'form picklists'!G5&", "&'form picklists'!H5&", "&'form picklists'!I5) -> DHS 213 8, CHPP Plant, Boiler Plant Equipment - Other-35 yr
B5: Job #:____________ | G5: =IF(ISBLANK('form picklists'!G6)=TRUE,"",'form picklists'!G6&", "&'form picklists'!H6&", "&'form picklists'!I6) -> DHS 213 8.1, CHPP Plant, Boiler Plant Equipment - Other-10 yr
B6: Capital Job Initiation form | G6: =IF(ISBLANK('form picklists'!G7)=TRUE,"",'form picklists'!G7&", "&'form picklists'!H7&", "&'form picklists'!I7) -> DHS 213 8.2, CHPP Plant, Boiler Plant Equipment - Other-20 year
B7: Request for creation of new Job number | G7: =IF(ISBLANK('form picklists'!G8)=TRUE,"",'form picklists'!G8&", "&'form picklists'!H8&", "&'form picklists'!I8) -> DHS 214 8, CHPP Plant, Boiler - Deaeriator
A8: Today's Date: | B8: 40318 | G8: =IF(ISBLANK('form picklists'!G9)=TRUE,"",'form picklists'!G9&", "&'form picklists'!H9&", "&'form picklists'!I9) -> DHS 215 8, CHPP Plant, Boiler - Feedwater Heaters
G9: =IF(ISBLANK('form picklists'!G10)=TRUE,"",'form picklists'!G10&", "&'form picklists'!H10&", "&'form picklists'!I10) -> DHS 216 8, CHPP Plant, Boiler - Feedwater Pump
A10: Job Description (Short): | B10: Service to Building 3014 | G10: =IF(ISBLANK('form picklists'!G11)=TRUE,"",'form picklists'!G11&", "&'form picklists'!H11&", "&'form picklists'!I11) -> DHS 221 4, Distribution, Steam Meter Installations
G11: =IF(ISBLANK('form picklists'!G12)=TRUE,"",'form picklists'!G12&", "&'form picklists'!H12&", "&'form picklists'!I12) -> DHS 222 4, Distribution, Steam Meters
A12: Job Description (Long): | B12: RFP Number: FWA-10-024: Upgrading size of pipe from existing utilidor vault H4-1-1 to the mechanical room to handle additional volume of water for the new sprinklers. Also installing a meter. | G12: =IF(ISBLANK('form picklists'!G13)=TRUE,"",'form picklists'!G13&", "&'form picklists'!H13&", "&'form picklists'!I13) -> DHS 222 4.1, Distribution, Steam Meter AMRs
G13: =IF(ISBLANK('form picklists'!G14)=TRUE,"",'form picklists'!G14&", "&'form picklists'!H14&", "&'form picklists'!I14) -> DHS 231 4, Distribution, CHPP Utilidors-Direct Buried- Condensate Lines
A14: Division: | B14: 5 | D14: Utility: | E14: 2 | G14: =IF(ISBLANK('form picklists'!G15)=TRUE,"",'form picklists'!G15&", "&'form picklists'!H15&", "&'form picklists'!I15) -> DHS 231 4.1, Distribution, CHPP Utilidors - Condensate Lines
G15: =IF(ISBLANK('form picklists'!G16)=TRUE,"",'form picklists'!G16&", "&'form picklists'!H16&", "&'form picklists'!I16) -> DHS 231 4.2, Distribution, Direct Buried - Condensate Lines
A16: Requested by: | D16: Project Manager: | E16: Wily Splain | G16: =IF(ISBLANK('form picklists'!G17)=TRUE,"",'form picklists'!G17&", "&'form picklists'!H17&", "&'form picklists'!I17) -> DHS 232 4, Distribution, CHPP Utilidors-Direct Buried- Steam Lines
A17: Requested by Description: | B17: Wily Splain | G17: =IF(ISBLANK('form picklists'!G18)=TRUE,"",'form picklists'!G18&", "&'form picklists'!H18&", "&'form picklists'!I18) -> DHS 232 4.1, Distribution, CHPP Utilidors - Steam Lines
G18: =IF(ISBLANK('form picklists'!G19)=TRUE,"",'form picklists'!G19&", "&'form picklists'!H19&", "&'form picklists'!I19) -> DHS 232 4.2, Distribution, Direct Buried- Steam Lines
A19: Start Date: | B19: 40318 | D19: Est Completion Date: | E19: 40417 | G19: =IF(ISBLANK('form picklists'!G20)=TRUE,"",'form picklists'!G20&", "&'form picklists'!H20&", "&'form picklists'!I20) -> DHS 232 4.3, Distribution, Utilidors - Steam Traps
A20: Subclass: | E20: Subclass Cost Estimate | G20: =IF(ISBLANK('form picklists'!G21)=TRUE,"",'form picklists'!G21&", "&'form picklists'!H21&", "&'form picklists'!I21) -> DHS 235 8, CHPP Plant, Wells and Springs
E21: =15839-(E22+E23)+12075 -> 17776 | G21: =IF(ISBLANK('form picklists'!G22)=TRUE,"",'form picklists'!G22&", "&'form picklists'!H22&", "&'form picklists'!I22) -> DHS 242 8, CHPP Plant, Other-Fuel Holders, Producer
E22: 9838 | G22: =IF(ISBLANK('form picklists'!G23)=TRUE,"",'form picklists'!G23&", "&'form picklists'!H23&", "&'form picklists'!I23) -> DHS 261 8, CHPP Plant, Turbogenerator Unit
E23: 300 | G23: =IF(ISBLANK('form picklists'!G24)=TRUE,"",'form picklists'!G24&", "&'form picklists'!H24&", "&'form picklists'!I24) -> DHS 261 8.1, CHPP Plant, Steam Turbines
E24: 5257 | G24: =IF(ISBLANK('form picklists'!G25)=TRUE,"",'form picklists'!G25&", "&'form picklists'!H25&", "&'form picklists'!I25) -> DHS 261 8.2, CHPP Plant, Generators
G25: =IF(ISBLANK('form picklists'!G26)=TRUE,"",'form picklists'!G26&", "&'form picklists'!H26&", "&'form picklists'!I26) -> DHS 261 8.3, CHPP Plant, Black Start Generators
D26: Total Subclass Estimate | E26: =SUM(E21:E25) -> 33171 | G26: =IF(ISBLANK('form picklists'!G27)=TRUE,"",'form picklists'!G27&", "&'form picklists'!H27&", "&'form picklists'!I27) -> DHS 261 8.4, CHPP Plant, Governors 40YR
A27: Cost Estimate: | B27: 33171 | D27: Cost Est - Subclass Est | E27: =B27-E26 -> 0 | G27: =IF(ISBLANK('form picklists'!G28)=TRUE,"",'form picklists'!G28&", "&'form picklists'!H28&", "&'form picklists'!I28) -> DHS 261 8.5, CHPP Plant, Control Systems 20YR
G28: =IF(ISBLANK('form picklists'!G29)=TRUE,"",'form picklists'!G29&", "&'form picklists'!H29&", "&'form picklists'!I29) -> DHS 262 8, CHPP Plant, Engine Driven Generators
A29: Cash Flow Estimate: | G29: =IF(ISBLANK('form picklists'!G30)=TRUE,"",'form picklists'!G30&", "&'form picklists'!H30&", "&'form picklists'!I30) -> DHS 263 8, CHPP Plant, Accessory Electric Equipment
A30: Description of retirements: | C30: Replacing existing laterals w/ new | G30: =IF(ISBLANK('form picklists'!G31)=TRUE,"",'form picklists'!G31&", "&'form picklists'!H31&", "&'form picklists'!I31) -> DHS 263 8.1, CHPP Plant, Accessory Electric Equipment - 15YR
G31: =IF(ISBLANK('form picklists'!G32)=TRUE,"",'form picklists'!G32&", "&'form picklists'!H32&", "&'form picklists'!I32) -> DHS 263 8.2, CHPP Plant, Accessory Electric Equipment - 20YR
A32: Additional comments: | G32: =IF(ISBLANK('form picklists'!G33)=TRUE,"",'form picklists'!G33&", "&'form picklists'!H33&", "&'form picklists'!I33) -> DHS 263 8.3, CHPP Plant, Accessory Electric Equipment -SCADA 20YR
G33: =IF(ISBLANK('form picklists'!G34)=TRUE,"",'form picklists'!G34&", "&'form picklists'!H34&", "&'form picklists'!I34) -> DHS 264 8, CHPP Plant, Other Systems
A34: Your name: | B34: Wily Splain | G34: =IF(ISBLANK('form picklists'!G35)=TRUE,"",'form picklists'!G35&", "&'form picklists'!H35&", "&'form picklists'!I35) -> DHS 271 3, Water Treatment , Chemical Feed System
G35: =IF(ISBLANK('form picklists'!G36)=TRUE,"",'form picklists'!G36&", "&'form picklists'!H36&", "&'form picklists'!I36) -> DHS 272 3, Water Treatment , Condensate Polisher
A36: THIS FORM IS NOT VALID WITHOUT APPROVING SIGNATURE OF DU PRESIDENT/CEO | G36: =IF(ISBLANK('form picklists'!G37)=TRUE,"",'form picklists'!G37&", "&'form picklists'!H37&", "&'form picklists'!I37) -> DHS 273 3, Water Treatment , Condensate Pumps-Storage Tanks
A37: For use by DU President/CEO: | D37: For use by Accounting Office: | G37: =IF(ISBLANK('form picklists'!G38)=TRUE,"",'form picklists'!G38&", "&'form picklists'!H38&", "&'form picklists'!I38) -> DHS 274 3, Water Treatment , Manholes
A38: Approved by: | D38: Assigned Job #: | G38: =IF(ISBLANK('form picklists'!G39)=TRUE,"",'form picklists'!G39&", "&'form picklists'!H39&", "&'form picklists'!I39) -> DHS 281 9, Coal Handling, Bucket Elevators
A39: Approved on: | D39: Date Job Created: | G39: =IF(ISBLANK('form picklists'!G40)=TRUE,"",'form picklists'!G40&", "&'form picklists'!H40&", "&'form picklists'!I40) -> DHS 282 9, Coal Handling, Coal Conveyers
G40: =IF(ISBLANK('form picklists'!G41)=TRUE,"",'form picklists'!G41&", "&'form picklists'!H41&", "&'form picklists'!I41) -> DHS 283 9, Coal Handling, Coal Crushers
G41: =IF(ISBLANK('form picklists'!G42)=TRUE,"",'form picklists'!G42&", "&'form picklists'!H42&", "&'form picklists'!I42) -> DHS 283 9.1, Coal Handling, Coal System Dust Collectors
G42: =IF(ISBLANK('form picklists'!G43)=TRUE,"",'form picklists'!G43&", "&'form picklists'!H43&", "&'form picklists'!I43) -> DHS 284 9, Coal Handling, Coal Feeders
G43: =IF(ISBLANK('form picklists'!G44)=TRUE,"",'form picklists'!G44&", "&'form picklists'!H44&", "&'form picklists'!I44) -> DHS 285 9, Coal Handling, Screening System
G44: =IF(ISBLANK('form picklists'!G45)=TRUE,"",'form picklists'!G45&", "&'form picklists'!H45&", "&'form picklists'!I45) -> DHS 286 9, Coal Handling, Track Mobile
G45: =IF(ISBLANK('form picklists'!G46)=TRUE,"",'form picklists'!G46&", "&'form picklists'!H46&", "&'form picklists'!I46) -> DHS 287 9, Coal Handling, Other Equip
G46: =IF(ISBLANK('form picklists'!G47)=TRUE,"",'form picklists'!G47&", "&'form picklists'!H47&", "&'form picklists'!I47) -> DHS 291 11, Ash Handling , Ash Blowers
G47: =IF(ISBLANK('form picklists'!G48)=TRUE,"",'form picklists'!G48&", "&'form picklists'!H48&", "&'form picklists'!I48) -> DHS 292 11, Ash Handling , Ash Silo and Unloader
G48: =IF(ISBLANK('form picklists'!G49)=TRUE,"",'form picklists'!G49&", "&'form picklists'!H49&", "&'form picklists'!I49) -> DHS 293 11, Ash Handling , Ash System Bag House
G49: =IF(ISBLANK('form picklists'!G50)=TRUE,"",'form picklists'!G50&", "&'form picklists'!H50&", "&'form picklists'!I50) -> DHS 293 11.1, Ash Handling , Ash System Dust Collectors
G50: =IF(ISBLANK('form picklists'!G51)=TRUE,"",'form picklists'!G51&", "&'form picklists'!H51&", "&'form picklists'!I51) -> DHS 294 11, Ash Handling , Clinker Crushers
G51: =IF(ISBLANK('form picklists'!G52)=TRUE,"",'form picklists'!G52&", "&'form picklists'!H52&", "&'form picklists'!I52) -> DHS 301 1, Intangible, Organization
... G373: =IF(ISBLANK('form picklists'!G374)=TRUE,"",'form picklists'!G374&", "&'form picklists'!H374&", "&'form picklists'!I374)

Sheet CashFlow
A1: Cash Flow
A2: Job Description: | B2: =LEFT('Job Initiation Form'!B10,50) -> Service to Building 3014
A3: Job #: | B3: ='Job Initiation Form'!E38 -> 0
A4: DIV: | B4: =VLOOKUP('Job Initiation Form'!B14,'form picklists'!O3:P7,2) -> Fort Wainwright
A5: Utility: | B5: =VLOOKUP('Job Initiation Form'!E14,'form picklists'!Q3:R9,2) -> Central Heating Plant
A6: CPM?:
A7: Start Month: | B7: ='Job Initiation Form'!B19 -> 40318
A8: Duration (months): | B8: =DAYS360('Job Initiation Form'!B19,'Job Initiation Form'!E19,FALSE)/30 -> 3.2333333
B10: =YEAR(B7) -> 2010 | C10: =IF(B12=12,$B$10+1," ") | D10: =IF(C12=12,$B$10+1," ") | E10: =IF(D12=12,$B$10+1,IF(D12="Q4",A10+1," ")) | F10: =IF(E12=12,$B$10+1,IF(E12="Q4",B10+1," ")) | G10: =IF(F12=12,$B$10+1,IF(F12="Q4",C10+1," ")) | H10: =IF(G12=12,$B$10+1,IF(G12="Q4",D10+1," ")) | I10: =IF(H12=12,$B$10+1,IF(H12="Q4",E10+1," ")) | J10: =IF(I12=12,$B$10+1,IF(I12="Q4",F10+1," ")) -> 2011 | K10: =IF(J12=12,$B$10+1,IF(J12="Q4",G10+1," ")) | L10: =IF(K12=12,$B$10+1,IF(K12="Q4",H10+1," ")) | M10: =IF(L12=12,$B$10+1,IF(L12="Q4",I10+1," "))
B11: =LOOKUP(B$12,{0,1,2,3,4,5,6,7,8,9,10,11,12,13,"Q1","Q2","Q3","Q4"},{" ","Q1"," "," ","Q2"," "," ","Q3"," "," ","Q4"," "," ","Q1","Q1","Q2","Q3","Q4"}) | C11: =LOOKUP(C$12,{0,1,2,3,4,5,6,7,8,9,10,11,12,13,"Q1","Q2","Q3","Q4"},{" ","Q1"," "," ","Q2"," "," ","Q3"," "," ","Q4"," "," ","Q1","Q1","Q2","Q3","Q4"}) | D11: =LOOKUP(D$12,{0,1,2,3,4,5,6,7,8,9,10,11,12,13,"Q1","Q2","Q3","Q4"},{" ","Q1"," "," ","Q2"," "," ","Q3"," "," ","Q4"," "," ","Q1","Q1","Q2","Q3","Q4"}) -> Q3 | E11: =LOOKUP(E$12,{0,1,2,3,4,5,6,7,8,9,10,11,12,13,"Q1","Q2","Q3","Q4"},{" ","Q1"," "," ","Q2"," "," ","Q3"," "," ","Q4"," "," ","Q1","Q1","Q2","Q3","Q4"}) | F11: =LOOKUP(F$12,{0,1,2,3,4,5,6,7,8,9,10,11,12,13,"Q1","Q2","Q3","Q4"},{" ","Q1"," "," ","Q2"," "," ","Q3"," "," ","Q4"," "," ","Q1","Q1","Q2","Q3","Q4"}) | G11: =LOOKUP(G$12,{0,1,2,3,4,5,6,7,8,9,10,11,12,13,"Q1","Q2","Q3","Q4"},{" ","Q1"," "," ","Q2"," "," ","Q3"," "," ","Q4"," "," ","Q1","Q1","Q2","Q3","Q4"}) -> Q4 | H11: =LOOKUP(H$12,{0,1,2,3,4,5,6,7,8,9,10,11,12,13,"Q1","Q2","Q3","Q4"},{" ","Q1"," "," ","Q2"," "," ","Q3"," "," ","Q4"," "," ","Q1","Q1","Q2","Q3","Q4"}) | I11: =LOOKUP(I$12,{0,1,2,3,4,5,6,7,8,9,10,11,12,13,"Q1","Q2","Q3","Q4"},{" ","Q1"," "," ","Q2"," "," ","Q3"," "," ","Q4"," "," ","Q1","Q1","Q2","Q3","Q4"}) | ... M11: =LOOKUP(M$12,{0,1,2,3,4,5,6,7,8,9,10,11,12,13,"Q1","Q2","Q3","Q4"},{" ","Q1"," "," ","Q2"," "," ","Q3"," "," ","Q4"," "," ","Q1","Q1","Q2","Q3","Q4"}) -> Q4 | N11: Estimate
B12: =MONTH(B7) -> 5 | C12: =LOOKUP(B$12,{0,1,2,3,4,5,6,7,8,9,10,11,12,"Q1","Q2","Q3","Q4"},{"ERROR",2,3,4,5,6,7,8,9,10,11,12,"Q1","Q2","Q3","Q4","Q1"}) -> 6 | D12: =LOOKUP(C$12,{0,1,2,3,4,5,6,7,8,9,10,11,12,"Q1","Q2","Q3","Q4"},{"ERROR",2,3,4,5,6,7,8,9,10,11,12,"Q1","Q2","Q3","Q4","Q1"}) -> 7 | E12: =LOOKUP(D$12,{0,1,2,3,4,5,6,7,8,9,10,11,12,"Q1","Q2","Q3","Q4"},{"ERROR",2,3,4,5,6,7,8,9,10,11,12,"Q1","Q2","Q3","Q4","Q1"}) -> 8 | F12: =LOOKUP(E$12,{0,1,2,3,4,5,6,7,8,9,10,11,12,"Q1","Q2","Q3","Q4"},{"ERROR",2,3,4,5,6,7,8,9,10,11,12,"Q1","Q2","Q3","Q4","Q1"}) -> 9 | G12: =LOOKUP(F$12,{0,1,2,3,4,5,6,7,8,9,10,11,12,"Q1","Q2","Q3","Q4"},{"ERROR",2,3,4,5,6,7,8,9,10,11,12,"Q1","Q2","Q3","Q4","Q1"}) -> 10 | H12: =LOOKUP(G$12,{0,1,2,3,4,5,6,7,8,9,10,11,12,"Q1","Q2","Q3","Q4"},{"ERROR",2,3,4,5,6,7,8,9,10,11,12,"Q1","Q2","Q3","Q4","Q1"}) -> 11 | I12: =LOOKUP(H$12,{0,1,2,3,4,5,6,7,8,9,10,11,12,"Q1","Q2","Q3","Q4"},{"ERROR",2,3,4,5,6,7,8,9,10,11,12,"Q1","Q2","Q3","Q4","Q1"}) -> 12 | J12: =LOOKUP(I$12,{0,1,2,3,4,5,6,7,8,9,10,11,12,"Q1","Q2","Q3","Q4"},{"ERROR",2,3,4,5,6,7,8,9,10,11,12,"Q1","Q2","Q3","Q4","Q1"}) -> Q1 | ... M12: =LOOKUP(L$12,{0,1,2,3,4,5,6,7,8,9,10,11,12,"Q1","Q2","Q3","Q4"},{"ERROR",2,3,4,5,6,7,8,9,10,11,12,"Q1","Q2","Q3","Q4","Q1"}) -> Q4
B14: 0 | C14: 11057 | D14: 11057 | E14: 11057 | F14: 0 | G14: 0 | H14: 0 | I14: 0 | J14: 0 | K14: 0 | L14: 0 | M14: 0 | N14: =SUM(B14:M14) -> 33171
B17: =SUM(B13:B16) -> 0 | C17: =SUM(C13:C16) -> 11057 | D17: =SUM(D13:D16) -> 11057 | E17: =SUM(E13:E16) -> 11057 | F17: =SUM(F13:F16) -> 0 | G17: =SUM(G13:G16) -> 0 | H17: =SUM(H13:H16) -> 0 | I17: =SUM(I13:I16) -> 0 | ... N17: =SUM(N13:N16) -> 33171
C19: =C17+B17 -> 11057 | D19: =D17+C19 -> 22114 | E19: =E17+D19 -> 33171 | F19: =F17+E19 -> 33171 | G19: =G17+F19 -> 33171 | H19: =H17+G19 -> 33171 | I19: =I17+H19 -> 33171 | J19: =J17+I19 -> 33171 | K19: =K17+J19 -> 33171 | ... M19: =M17+L19 -> 33171
B22: =IF(M12=12,$B$10+1,IF(M12="Q4",J10+1," ")) -> 2012 | C22: =IF(B23=12,$B$10+1,IF(B23="Q4",K10+1," ")) | D22: =IF(C23=12,$B$10+1,IF(C23="Q4",L10+1," ")) | E22: =IF(D23=12,$B$10+1,IF(D23="Q4",M10+1," ")) | F22: =IF(E23=12,$B$10+1,IF(E23="Q4",B22+1," ")) -> 2013 | G22: =IF(F23=12,$B$10+1,IF(F23="Q4",C22+1," ")) | H22: =IF(G23=12,$B$10+1,IF(G23="Q4",D22+1," ")) | I22: =IF(H23=12,$B$10+1,IF(H23="Q4",E22+1," ")) | J22: =IF(I23=12,$B$10+1,IF(I23="Q4",F22+1," ")) -> 2014 | K22: =IF(J23=12,$B$10+1,IF(J23="Q4",G22+1," ")) | L22: =IF(K23=12,$B$10+1,IF(K23="Q4",H22+1," ")) | M22: =IF(L23=12,$B$10+1,IF(L23="Q4",I22+1," ")) | N22: Total Estimate
B23: =LOOKUP(B$24,{0,1,2,3,4,5,6,7,8,9,10,11,12,13,"Q1","Q2","Q3","Q4"},{" ","Q1"," "," ","Q2"," "," ","Q3"," "," ","Q4"," "," ","Q1","Q1","Q2","Q3","Q4"}) -> Q1 | C23: =LOOKUP(C$24,{0,1,2,3,4,5,6,7,8,9,10,11,12,13,"Q1","Q2","Q3","Q4"},{" ","Q1"," "," ","Q2"," "," ","Q3"," "," ","Q4"," "," ","Q1","Q1","Q2","Q3","Q4"}) -> Q2 | D23: =LOOKUP(D$24,{0,1,2,3,4,5,6,7,8,9,10,11,12,13,"Q1","Q2","Q3","Q4"},{" ","Q1"," "," ","Q2"," "," ","Q3"," "," ","Q4"," "," ","Q1","Q1","Q2","Q3","Q4"}) -> Q3 | E23: =LOOKUP(E$24,{0,1,2,3,4,5,6,7,8,9,10,11,12,13,"Q1","Q2","Q3","Q4"},{" ","Q1"," "," ","Q2"," "," ","Q3"," "," ","Q4"," "," ","Q1","Q1","Q2","Q3","Q4"}) -> Q4 | F23: =LOOKUP(F$24,{0,1,2,3,4,5,6,7,8,9,10,11,12,13,"Q1","Q2","Q3","Q4"},{" ","Q1"," "," ","Q2"," "," ","Q3"," "," ","Q4"," "," ","Q1","Q1","Q2","Q3","Q4"}) -> Q1 | G23: =LOOKUP(G$24,{0,1,2,3,4,5,6,7,8,9,10,11,12,13,"Q1","Q2","Q3","Q4"},{" ","Q1"," "," ","Q2"," "," ","Q3"," "," ","Q4"," "," ","Q1","Q1","Q2","Q3","Q4"}) -> Q2 | H23: =LOOKUP(H$24,{0,1,2,3,4,5,6,7,8,9,10,11,12,13,"Q1","Q2","Q3","Q4"},{" ","Q1"," "," ","Q2"," "," ","Q3"," "," ","Q4"," "," ","Q1","Q1","Q2","Q3","Q4"}) -> Q3 | I23: =LOOKUP(I$24,{0,1,2,3,4,5,6,7,8,9,10,11,12,13,"Q1","Q2","Q3","Q4"},{" ","Q1"," "," ","Q2"," "," ","Q3"," "," ","Q4"," "," ","Q1","Q1","Q2","Q3","Q4"}) -> Q4 | ... M23: =LOOKUP(M$24,{0,1,2,3,4,5,6,7,8,9,10,11,12,13,"Q1","Q2","Q3","Q4"},{" ","Q1"," "," ","Q2"," "," ","Q3"," "," ","Q4"," "," ","Q1","Q1","Q2","Q3","Q4"}) -> Q4
B24: =LOOKUP(M$12,{0,1,2,3,4,5,6,7,8,9,10,11,12,"Q1","Q2","Q3","Q4"},{"ERROR",2,3,4,5,6,7,8,9,10,11,12,"Q1","Q2","Q3","Q4","Q1"}) -> Q1 | C24: =LOOKUP(B$24,{0,1,2,3,4,5,6,7,8,9,10,11,12,"Q1","Q2","Q3","Q4"},{"ERROR",2,3,4,5,6,7,8,9,10,11,12,"Q1","Q2","Q3","Q4","Q1"}) -> Q2 | D24: =LOOKUP(C$24,{0,1,2,3,4,5,6,7,8,9,10,11,12,"Q1","Q2","Q3","Q4"},{"ERROR",2,3,4,5,6,7,8,9,10,11,12,"Q1","Q2","Q3","Q4","Q1"}) -> Q3 | E24: =LOOKUP(D$24,{0,1,2,3,4,5,6,7,8,9,10,11,12,"Q1","Q2","Q3","Q4"},{"ERROR",2,3,4,5,6,7,8,9,10,11,12,"Q1","Q2","Q3","Q4","Q1"}) -> Q4 | F24: =LOOKUP(E$24,{0,1,2,3,4,5,6,7,8,9,10,11,12,"Q1","Q2","Q3","Q4"},{"ERROR",2,3,4,5,6,7,8,9,10,11,12,"Q1","Q2","Q3","Q4","Q1"}) -> Q1 | G24: =LOOKUP(F$24,{0,1,2,3,4,5,6,7,8,9,10,11,12,"Q1","Q2","Q3","Q4"},{"ERROR",2,3,4,5,6,7,8,9,10,11,12,"Q1","Q2","Q3","Q4","Q1"}) -> Q2 | H24: =LOOKUP(G$24,{0,1,2,3,4,5,6,7,8,9,10,11,12,"Q1","Q2","Q3","Q4"},{"ERROR",2,3,4,5,6,7,8,9,10,11,12,"Q1","Q2","Q3","Q4","Q1"}) -> Q3 | I24: =LOOKUP(H$24,{0,1,2,3,4,5,6,7,8,9,10,11,12,"Q1","Q2","Q3","Q4"},{"ERROR",2,3,4,5,6,7,8,9,10,11,12,"Q1","Q2","Q3","Q4","Q1"}) -> Q4 | J24: =LOOKUP(I$24,{0,1,2,3,4,5,6,7,8,9,10,11,12,"Q1","Q2","Q3","Q4"},{"ERROR",2,3,4,5,6,7,8,9,10,11,12,"Q1","Q2","Q3","Q4","Q1"}) -> Q1 | ... M24: =LOOKUP(L$24,{0,1,2,3,4,5,6,7,8,9,10,11,12,"Q1","Q2","Q3","Q4"},{"ERROR",2,3,4,5,6,7,8,9,10,11,12,"Q1","Q2","Q3","Q4","Q1"}) -> Q4
B26: 0 | C26: 0 | D26: 0 | E26: 0 | F26: 0 | G26: 0 | H26: 0 | I26: 0 | J26: 0 | K26: 0 | L26: 0 | M26: 0 | N26: =SUM(B26:M26,N14) -> 33171
B29: =SUM(B25:B28) -> 0 | C29: =SUM(C25:C28) -> 0 | D29: =SUM(D25:D28) -> 0 | E29: =SUM(E25:E28) -> 0 | F29: =SUM(F25:F28) -> 0 | G29: =SUM(G25:G28) -> 0 | H29: =SUM(H25:H28) -> 0 | I29: =SUM(I25:I28) -> 0 | ... N29: =SUM(N25:N28) -> 33171
B31: =B29+N17 -> 33171 | C31: =C29+B31 -> 33171 | D31: =D29+C31 -> 33171 | E31: =E29+D31 -> 33171 | F31: =F29+E31 -> 33171 | G31: =G29+F31 -> 33171 | H31: =H29+G31 -> 33171 | I31: =I29+H31 -> 33171 | J31: =J29+I31 -> 33171 | ... M31: =M29+L31 -> 33171
A33: The header dates on this worksheet will automatically populate based on the start date of the job noted on the Job Initiation Form

Sheet Job Revision Form
B6: Capital Job Revision form
B7: Request for revision of existing Job
A8: Today's Date:
A9: Job #:
A10: Job Description (Short):
A12: Describe Change (Long):
A14: Division: | B14: 1 | D14: Utility: | E14: 1
A16: Requested by: | D16: Project Manager:
A17: Requested by Description:
A19: Start Date: | D19: Est Completion Date:
A21: Subclass: | D21: Subclass Cost Estimate
D26: Total Subclass Estimate | E26: =SUM(E21:E25) -> 0
A27: Cost Estimate: | D27: Cost Est - Subclass Est
A29: Cash Flow Estimate:
A30: Description of retirements:
A32: Additional comments:
A34: Your name:
A36: THIS FORM IS NOT VALID WITHOUT APPROVING SIGNATURE OF DU PRESIDENT/CEO
A37: For use by DU President/CEO: | D37: For use by Accounting Office:
A38: Approved by: | D38: Updated Job #:
A39: Approved on: | D39: Date Job Changed:

Sheet Subclasses
A1: NAV Code | B1: Cost Center | C1: Description | D1: NARUC Codes | E1: GAAP Life | F1: Fed Tax MACRS Life | G1: Bonus Depr
A2: DHS 211 8 | B2: CHPP Plant | C2: Boiler Plant Equip - 75 years | D2: n/a | E2: 70 & 75 | F2: 15 | G2: Y
A3: DHS 212 8 | B3: CHPP Plant | C3: Boiler Plant Equip - 50 years | D3: n/a | E3: 50 | F3: 15 | G3: Y
A4: DHS 213 8 | B4: CHPP Plant | C4: Boiler Plant Equipment - Other-35 yr | D4: n/a | E4: 35 | F4: 15 | G4: Y
A5: DHS 213 8.1 | B5: CHPP Plant | C5: Boiler Plant Equipment - Other-10 yr | D5: n/a | E5: 10 | F5: 15 | G5: Y
A6: DHS 213 8.2 | B6: CHPP Plant | C6: Boiler Plant Equipment - Other-20 year | D6: n/a | E6: 20 | F6: 15 | G6: Y
A7: DHS 214 8 | B7: CHPP Plant | C7: Boiler - Deaeriator | D7: n/a | E7: 35 | F7: 15 | G7: Y
A8: DHS 215 8 | B8: CHPP Plant | C8: Boiler - Feedwater Heaters | D8: n/a | E8: 35 | F8: 15 | G8: Y
A9: DHS 216 8 | B9: CHPP Plant | C9: Boiler - Feedwater Pump | D9: n/a | E9: 35 | F9: 15 | G9: Y
A10: DHS 221 4 | B10: Distribution | C10: Steam Meter Installations | D10: n/a | E10: 50 | F10: 15 | G10: Y
A11: DHS 222 4 | B11: Distribution | C11: Steam Meters | D11: n/a | E11: 20 & 25 | F11: 15 | G11: Y
A12: DHS 222 4.1 | B12: Distribution | C12: Steam Meter AMRs | D12: n/a | E12: 20 | F12: 15 | G12: Y
A13: DHS 231 4 | B13: Distribution | C13: CHPP Utilidors-Direct Buried- Condensate Lines | D13: n/a | E13: 40 | F13: 15 | G13: Y
A14: DHS 231 4.1 | B14: Distribution | C14: CHPP Utilidors - Condensate Lines | D14: n/a | E14: 40 | F14: 15 | G14: Y
A15: DHS 231 4.2 | B15: Distribution | C15: Direct Buried - Condensate Lines | D15: n/a | E15: 40 | F15: 15 | G15: Y
A16: DHS 232 4 | B16: Distribution | C16: CHPP Utilidors-Direct Buried- Steam Lines | D16: n/a | E16: 60 | F16: 15 | G16: Y
A17: DHS 232 4.1 | B17: Distribution | C17: CHPP Utilidors - Steam Lines | D17: n/a | E17: 60 | F17: 15 | G17: Y
A18: DHS 232 4.2 | B18: Distribution | C18: Direct Buried- Steam Lines | D18: n/a | E18: 60 | F18: 15 | G18: Y
A19: DHS 232 4.3 | B19: Distribution | C19: Utilidors - Steam Traps | D19: n/a | E19: 20 & 25 | F19: 15 | G19: Y
A20: DHS 235 8 | B20: CHPP Plant | C20: Wells and Springs | D20: n/a | E20: 45 | F20: 15 | G20: Y
A21: DHS 242 8 | B21: CHPP Plant | C21: Other-Fuel Holders, Producer | D21: n/a | E21: 55 | F21: 15 | G21: Y
A22: DHS 261 8 | B22: CHPP Plant | C22: Turbogenerator Unit | D22: n/a | E22: 75 | F22: 15 | G22: Y
A23: DHS 261 8.1 | B23: CHPP Plant | C23: Steam Turbines | D23: n/a | E23: 75 | F23: 15 | G23: Y
A24: DHS 261 8.2 | B24: CHPP Plant | C24: Generators | D24: n/a | E24: 75 | F24: 15 | G24: Y
A25: DHS 261 8.3 | B25: CHPP Plant | C25: Black Start Generators | D25: n/a | E25: 75 | F25: 15 | G25: Y
A26: DHS 261 8.4 | B26: CHPP Plant | C26: Governors 40YR | D26: n/a | E26: 40 | F26: 15 | G26: Y
A27: DHS 261 8.5 | B27: CHPP Plant | C27: Control Systems 20YR | D27: n/a | E27: 20 | F27: 15 | G27: Y
A28: DHS 262 8 | B28: CHPP Plant | C28: Engine Driven Generators | D28: n/a | E28: 75 | F28: 15 | G28: Y
A29: DHS 263 8 | B29: CHPP Plant | C29: Accessory Electric Equipment | D29: n/a | E29: 40 | F29: 15 | G29: Y
A30: DHS 263 8.1 | B30: CHPP Plant | C30: Accessory Electric Equipment - 15YR | D30: n/a | E30: 15 | F30: 5 | G30: Y
A31: DHS 263 8.2 | B31: CHPP Plant | C31: Accessory Electric Equipment - 20YR | D31: n/a | E31: 20 | F31: 15 | G31: Y
A32: DHS 263 8.3 | B32: CHPP Plant | C32: Accessory Electric Equipment -SCADA 20YR | D32: n/a | E32: 20 | F32: 15 | G32: Y
A33: DHS 264 8 | B33: CHPP Plant | C33: Other Systems | D33: n/a | E33: 35 & 40 | F33: 15 | G33: Y
A34: DHS 271 3 | B34: Water Treatment | C34: Chemical Feed System | D34: n/a | E34: 35 | F34: 15 | G34: Y
A35: DHS 272 3 | B35: Water Treatment | C35: Condensate Polisher | D35: n/a | E35: 35 | F35: 15 | G35: Y
A36: DHS 273 3 | B36: Water Treatment | C36: Condensate Pumps-Storage Tanks | D36: n/a | E36: 35 | F36: 15 | G36: Y
A37: DHS 274 3 | B37: Water Treatment | C37: Manholes | D37: n/a | E37: 35 | F37: 15 | G37: Y
A38: DHS 281 9 | B38: Coal Handling | C38: Bucket Elevators | D38: n/a | E38: 40 | F38: 15 | G38: Y
A39: DHS 282 9 | B39: Coal Handling | C39: Coal Conveyers | D39: n/a | E39: 40 | F39: 15 | G39: Y
A40: DHS 283 9 | B40: Coal Handling | C40: Coal Crushers | D40: n/a | E40: 40 | F40: 15 | G40: Y
A41: DHS 283 9.1 | B41: Coal Handling | C41: Coal System Dust Collectors | D41: n/a | E41: 40 | F41: 15 | G41: Y
A42: DHS 284 9 | B42: Coal Handling | C42: Coal Feeders | D42: n/a | E42: 40 | F42: 15 | G42: Y
A43: DHS 285 9 | B43: Coal Handling | C43: Screening System | D43: n/a | E43: 40 | F43: 15 | G43: Y
A44: DHS 286 9 | B44: Coal Handling | C44: Track Mobile | D44: n/a | E44: 75 | F44: 15 | G44: Y
A45: DHS 287 9 | B45: Coal Handling | C45: Other Equip | D45: n/a | E45: 40 | F45: 15 | G45: Y
... A79: DHS 361 5 | B79: General Plant | C79: Power Operated Equipment 10 YR | D79: n/a | E79: 10 | F79: 7 | G79: Y
A80: EDS 301 1 | B80: Intangible | C80: Organization | D80: 301 | E80: 50 | F80: 50 | G80: N
A81: EDS 303 1 | B81: Intangible | C81: Miscellaneous Intangible Plant | D81: 303 | E81: 25 | F81: 7 | G81: N
A82: EDS 310 10 | B82: Production Plant/Steam Prod | C82: Land and Land Rights | D82: 310 | E82: 0 | F82: 0 | G82: N
A83: EDS 311 10 | B83: Production Plant/Steam Prod | C83: Structures Improvement | D83: 311 | E83: 50 | F83: 39 | G83: N
A84: EDS 312 10 | B84: Production Plant/Steam Prod | C84: Boiler Plant Equip | D84: 312 | E84: 75 | F84: 15 | G84: Y
A85: EDS 313 10 | B85: Production Plant/Steam Prod | C85: Eng, Engin Driven Generators | D85: 313 | E85: 75 | F85: 15 | G85: Y
A86: EDS 314 10 | B86: Production Plant/Steam Prod | C86: Turbogenerator Units | D86: 314 | E86: 75 | F86: 15 | G86: Y
A87: EDS 315 10 | B87: Production Plant/Steam Prod | C87: Accessory Electric Equipment | D87: 315 | F87: 15 | G87: Y
A88: EDS 316 10 | B88: Production Plant/Steam Prod | C88: Misc Power Plant Equip | D88: 316 | F88: 15 | G88: Y
A89: EDS 341 10 | B89: Production Plant/Other Production | C89: Structures and Improvement | D89: 341 | E89: 50 | F89: 39 | G89: N
A90: EDS 342 10 | B90: Production Plant/Other Production | C90: Fuel Holders, Producer | D90: 342 | E90: 55 | F90: 15 | G90: Y
A91: EDS 344 10 | B91: Production Plant/Other Production | C91: Generators | D91: 344 | E91: 50 | F91: 15 | G91: Y
A92: EDS 345 10 | B92: Production Plant/Other Production | C92: Accessory Electric Equipment | D92: 345 | E92: 25 | F92: 15 | G92: Y
A93: EDS 345 14 | B93: Production Plant/Other Production | C93: Accessory Electric Equip-SCADA | D93: 345 | E93: 20 | F93: 15 | G93: Y
A94: EDS 346 10 | B94: Production Plant/Other Production | C94: Misc Power Plant Equip | D94: 345 | F94: 15 | G94: Y
A95: EDS 350 3 | B95: Transmission | C95: Land and Land Rights | D95: 350 | E95: 0 | F95: 0 | G95: N
A96: EDS 352 3 | B96: Transmission | C96: Structures & Improvements | D96: 352 | F96: 39 | G96: N
A97: EDS 353 3 | B97: Transmission | C97: Station Equipment | D97: 353 | F97: 15 | G97: Y
A98: EDS 354 3 | B98: Transmission | C98: Towers and Fixtures | D98: 354 | F98: 15 | G98: Y
A99: EDS 355 3 | B99: Transmission | C99: Poles and Fixtures | D99: 355 | F99: 15 | G99: Y
A100: EDS 356 3 | B100: Transmission | C100: Overhead Conductors & Devices | D100: 356 | F100: 15 | G100: Y
A101: EDS 357 3 | B101: Transmission | C101: Underground Conduit | D101: 357 | F101: 15 | G101: Y
A102: EDS 358 3 | B102: Transmission | C102: Underground Conductors & Devices | D102: 358 | F102: 15 | G102: Y
A103: EDS 359 3 | B103: Transmission | C103: Road and Trails | D103: 359 | F103: 15 | G103: Y
A104: EDS 360 4 | B104: Distribution | C104: Land and Land Rights | D104: 360 | E104: 0 | F104: 0 | G104: N
A105: EDS 361 4 | B105: Distribution | C105: Structures and Improvements 75YR | D105: 361 | E105: 75 | F105: 39 | G105: N
A106: EDS 361 4.1 | B106: Distribution | C106: Structures and Improvements 50YR | D106: 361 | E106: 50 | F106: 7 | G106: Y
A107: EDS 362 4 | B107: Distribution | C107: Station Equipment | D107: 362 | E107: 50 | F107: 15 | G107: Y
A108: EDS 362 4.1 | B108: Distribution | C108: Station Equip-SCADA | D108: 362 | E108: 20 | F108: 5 | G108: Y
A109: EDS 363 4 | B109: Distribution | C109: Storage Battery Equipment | D109: 363 | F109: 15 | G109: Y
A110: EDS 364 4 | B110: Distribution | C110: Poles, Towers, and Fixtures | D110: 364 | E110: 40 & 50 | F110: 15 | G110: Y
A111: EDS 365 4 | B111: Distribution | C111: Overhead Conductors and Devices | D111: 365 | E111: 35 & 50 | F111: 15 | G111: Y
A112: EDS 366 4 | B112: Distribution | C112: Underground Conduit | D112: 366 | E112: 85 & 105 | F112: 15 | G112: Y
A113: EDS 367 4 | B113: Distribution | C113: Underground Conductors and Devices | D113: 367 | E113: 50 | F113: 15 | G113: Y
A114: EDS 368 4 | B114: Distribution | C114: Line Transformers | D114: 368 | E114: 40 | F114: 15 | G114: Y
A115: EDS 369 4 | B115: Distribution | C115: Services | D115: 369 | E115: 40 | F115: 15 | G115: Y
A116: EDS 370 4 | B116: Distribution | C116: Meters | D116: 370 | E116: 20 | F116: 15 | G116: Y
A117: EDS 370 4.1 | B117: Distribution | C117: Meter AMRs | D117: 370 | E117: 20 | F117: 15 | G117: Y
A118: EDS 371 4 | B118: Distribution | C118: Installation on Customer's Premises | D118: 371 | E118: 50 | F118: 15 | G118: Y
A119: EDS 372 4 | B119: Distribution | C119: Leased Property on Customers Premises | D119: 372 | E119: 50 | F119: 15 | G119: Y
A120: EDS 373 4 | B120: Distribution | C120: Street Lighting and Signal Systems | D120: 373 | E120: 50 | F120: 15 | G120: Y
A121: EDS 389 5 | B121: General Plant | C121: Land and Land Rights | D121: 389 | E121: 0 | F121: 0 | G121: N
A122: EDS 390 5 | B122: General Plant | C122: Structures and Improvements | D122: 390 | E122: 50 | F122: 39 | G122: N
A123: EDS 391 5 | B123: General Plant | C123: Office Equipment | D123: 391 | E123: 5 | F123: 5 | G123: Y
A124: EDS 391 5.1 | B124: General Plant | C124: Office Furniture | D124: 391 | E124: 10 | F124: 7 | G124: Y
... A155: NGD 375 5 | B155: Distribution | C155: Structures and Improvements | D155: 375 | E155: 75 | F155: 39 | G155: N
A156: NGD 376 5 | B156: Distribution | C156: Mains | D156: 376 | E156: 25, 70 & 75 | F156: 15 | G156: Y
A157: NGD 377 5 | B157: Distribution | C157: Compressor Station Equipment | D157: 377 | E157: 40 | F157: 15 | G157: Y
A158: NGD 378 5 | B158: Distribution | C158: Measuring and Regulating Stn Equip General | D158: 378 | E158: 25 | F158: 15 | G158: Y
A159: NGD 378 5.1 | B159: Distribution | C159: SCADA System | D159: 378 | E159: 15 | F159: 5 | G159: Y
A160: NGD 379 5 | B160: Distribution | C160: Meas and Reg Stn Equip - Gate Chk Stations | D160: 379 | E160: 25 | F160: 15 | G160: Y
A161: NGD 380 5 | B161: Distribution | C161: Services | D161: 380 | E161: 50 | F161: 15 | G161: Y
A162: NGD 381 5 | B162: Distribution | C162: Meters | D162: 381 | E162: 35 | F162: 15 | G162: Y
A163: NGD 381 5.1 | B163: Distribution | C163: Meters 40YR | D163: 381 | E163: 40 | F163: 15 | G163: Y
...

Sheet Job Completion Form
B6: Job Completion form
B7: Notification of Job Completion
A8: Today's Date:
A9: Job #:
A10: Job Description (Short):
A12: Describe Job (Long):
A14: Division: | B14: 1 | D14: Utility: | E14: 1
A16: Requested by: | D16: Project Manager:
A17: Requested by Description:
A19: Start Date: | B19: 39448 | D19: Final Completion Date: | E19: 39448
A21: Short Description | B21: Subclass | C21: Qty | D21: Expected Life (yrs) | E21: Subclass Final Cost
D27: Total Subclass Cost | E27: =SUM(E22:E26) -> 0
A28: Final Cost: | D28: Cost - Subclass | E28: =B28-E27 -> 0
A30: Description of retirements:
A32: Additional comments:
A34: Your name:
A36: THIS FORM IS NOT VALID WITHOUT APPROVING SIGNATURE OF DU PRESIDENT/CEO
A37: For use by DU President/CEO: | D37: For use by Accounting Office:
A38: Approved by: | D38: Associated FA #:
A39: Approved on: | D39: Date Job Closed:

Sheet form picklists
A1: Division | C1: Utility | E1: Requested By | G1: NAV Code | H1: Cost Center | I1: Description | K1: Cash Flow? | M1: CPM? | O1: CFID | P1: Division | Q1: CFID2 | R1: Utility
A3: Corporate | C3: Central Heating Plant | E3: 1. Original Contract | G3: DHS 211 8 | H3: CHPP Plant | I3: Boiler Plant Equip - 75 years | K3: See Attached | M3: Yes | O3: 1 | P3: N/A | Q3: 1 | R3: N/A
A4: Fort Greely | C4: Corporate | E4: 2. Contract Mod | G4: DHS 212 8 | H4: CHPP Plant | I4: Boiler Plant Equip - 50 years | K4: N/A | M4: No | O4: 2 | P4: Corporate | Q4: 2 | R4: Central Heating Plant
A5: Fort Richardson | C5: Electric Distribution | E5: 3. COR MOD | G5: DHS 213 8 | H5: CHPP Plant | I5: Boiler Plant Equipment - Other-35 yr | O5: 3 | P5: Fort Greely | Q5: 3 | R5: Corporate
A6: Fort Wainwright | C6: Natural Gas | E6: 4. Other MOD | G6: DHS 213 8.1 | H6: CHPP Plant | I6: Boiler Plant Equipment - Other-10 yr | O6: 4 | P6: Fort Richardson | Q6: 4 | R6: Electric Distribution
C7: Waste Water | E7: 5. Corporate | G7: DHS 213 8.2 | H7: CHPP Plant | I7: Boiler Plant Equipment - Other-20 year | O7: 5 | P7: Fort Wainwright | Q7: 5 | R7: Natural Gas
C8: Water | E8: 6. An Individual | G8: DHS 214 8 | H8: CHPP Plant | I8: Boiler - Deaeriator | Q8: 6 | R8: Waste Water
G9: DHS 215 8 | H9: CHPP Plant | I9: Boiler - Feedwater Heaters | Q9: 7 | R9: Water
G10: DHS 216 8 | H10: CHPP Plant | I10: Boiler - Feedwater Pump
G11: DHS 221 4 | H11: Distribution | I11: Steam Meter Installations
G12: DHS 222 4 | H12: Distribution | I12: Steam Meters
G13: DHS 222 4.1 | H13: Distribution | I13: Steam Meter AMRs
G14: DHS 231 4 | H14: Distribution | I14: CHPP Utilidors-Direct Buried- Condensate Lines
G15: DHS 231 4.1 | H15: Distribution | I15: CHPP Utilidors - Condensate Lines
G16: DHS 231 4.2 | H16: Distribution | I16: Direct Buried - Condensate Lines
G17: DHS 232 4 | H17: Distribution | I17: CHPP Utilidors-Direct Buried- Steam Lines
G18: DHS 232 4.1 | H18: Distribution | I18: CHPP Utilidors - Steam Lines
G19: DHS 232 4.2 | H19: Distribution | I19: Direct Buried- Steam Lines
G20: DHS 232 4.3 | H20: Distribution | I20: Utilidors - Steam Traps
G21: DHS 235 8 | H21: CHPP Plant | I21: Wells and Springs
... G311: WWC 398 7.1 | H311: General Plant | I311: Other Tangible Equipment 5 YR
