Workbook
Name _EAR01: #REF!
Name _EAR02: #REF!
Name _EAR03: #REF!
Name _EAR04: #REF!
Name _EAR05: #REF!
Name _EAR06: #REF!
Name _EAR07: #REF!
Name _EAR08: #REF!
Name _EAR09: #REF!
Name _EAR10: #REF!
Name _LR01: #REF!
Name _LR02: #REF!
Name _LR03: #REF!
Name _LR04: #REF!
Name _LR05: #REF!
Name _LR06: #REF!
Name _LR07: #REF!
Name _LR08: #REF!
Name _LR09: #REF!
Name _LR10: #REF!
Name _OSR01: #REF!
Name _OSR02: #REF!
Name _OSR03: #REF!
Name _OSR04: #REF!
Name _OSR05: #REF!
Name _OSR06: #REF!
Name _OSR07: #REF!
Name _OSR08: #REF!
Name _OSR09: #REF!
Name _OSR10: #REF!
Name Area: #REF!
Name AvgFlow: #REF!
Name Basis: #REF!
Name Cell01: '[1]A2-Task'!$A$3
Name Cell02: '[1]A2-Task'!$A$4
Name Cell03: '[1]A2-Task'!$A$5
Name Cell04: '[1]A2-Task'!$A$6
Name Cell05: '[1]A2-Task'!$A$7
Name Cell06: '[1]A2-Task'!$A$8
Name Cell07: '[1]A2-Task'!$A$9
Name Cell08: '[1]A2-Task'!$A$10
Name Cell09: '[1]A2-Task'!$A$11
Name Cell10: '[1]A2-Task'!$A$12
Name CHANGES: #REF!
Name Clear: #REF!
Name Clear_0Summary: #REF!
Name Clear_5Staff: #REF!
Name Clear_EarnedValue: #REF!
Name Clear_Staff: '[1]A3-Staff'!#REF!
Name data: #REF!
Name DigFeed: #REF!
Name DigFlow: #REF!
Name digOut: #REF!
Name DigVol: #REF!
Name DigWarn: #REF!
Name EAR: #REF!
Name Exp_Revenue01: '[1]A5-Expense'!$C$149
Name Exp_Revenue02: '[1]A5-Expense'!$D$149
Name Exp_Revenue03: '[1]A5-Expense'!$E$149
Name Exp_Revenue04: '[1]A5-Expense'!$F$149

Sheet Richardson Elec Dist- R&R Proj
A1: Fort Richardson Electrical Distribution R&R Projects
A4: Project Number: Year 2
A5: Project Title: Upgrade Water System
A6: Year That Payment for Project Will Begin: Year 2 of the 50 Year Contract
A8: Project Description | B8: Year Implemented | C8: Year Payments Begin | D8: Quantity | E8: Unit of Measure | F8: Cost/UOM | G8: Base Constr Cost (no markups) | H8: Contingency | I8: Bonds, Insurance | J8: General Conditions | K8: G & A | L8: Profit | M8: Total Capital Cost | N8: Studies plus Predesign | O8: Design | P8: SDC | Q8: Fee on Professional Services | R8: Total Project Cost | T8: Engineering | U8: Construction | V8: GM
H9: 0.05 | I9: 0.02 | J9: 0.05 | K9: 0.122 | L9: 0.1 | N9: 0.077 | O9: 0.05 | P9: 0.03 | Q9: 0.1
A11: - | B11: =#REF! -> #REF! | C11: In Initial Replacements | G11: =SUMIF(#REF!,$B11,#REF!) -> #REF! | H11: =G11*$H$9 -> #REF! | I11: =SUM(G11:H11)*I$9 -> #REF! | J11: =SUM(G11:I11)*J$9 -> #REF! | K11: =SUM(G11:J11)*K$9 -> #REF! | L11: =SUM(G11:K11)*L$9 -> #REF! | M11: =SUM(G11:L11) -> #REF! | N11: =M11*N$9 -> #REF! | O11: =M11*O$9 -> #REF! | P11: =M11*P$9 -> #REF! | Q11: =SUM(N11:P11)*Q$9 -> #REF! | R11: =SUM(M11:Q11) -> #REF! | T11: =SUM(N11:Q11)*$S$69 -> #REF! | U11: =M11*$S$69 -> #REF! | V11: =(K11+L11+Q11)*S$69 -> #REF!
A12: - | B12: =B11+1 -> #REF! | C12: In Initial Replacements | G12: =SUMIF(#REF!,$B12,#REF!) -> #REF! | H12: =G12*$H$9 -> #REF! | I12: =SUM(G12:H12)*I$9 -> #REF! | J12: =SUM(G12:I12)*J$9 -> #REF! | K12: =SUM(G12:J12)*K$9 -> #REF! | L12: =SUM(G12:K12)*L$9 -> #REF! | M12: =SUM(G12:L12) -> #REF! | N12: =M12*N$9 -> #REF! | O12: =M12*O$9 -> #REF! | P12: =M12*P$9 -> #REF! | Q12: =SUM(N12:P12)*Q$9 -> #REF! | R12: =SUM(M12:Q12) -> #REF! | T12: =SUM(N12:Q12)*$S$69 -> #REF! | U12: =M12*$S$69 -> #REF! | V12: =(K12+L12+Q12)*S$69 -> #REF!
A13: - | B13: =B12+1 -> #REF! | C13: In Initial Replacements | G13: =SUMIF(#REF!,$B13,#REF!) -> #REF! | H13: =G13*$H$9 -> #REF! | I13: =SUM(G13:H13)*I$9 -> #REF! | J13: =SUM(G13:I13)*J$9 -> #REF! | K13: =SUM(G13:J13)*K$9 -> #REF! | L13: =SUM(G13:K13)*L$9 -> #REF! | M13: =SUM(G13:L13) -> #REF! | N13: =M13*N$9 -> #REF! | O13: =M13*O$9 -> #REF! | P13: =M13*P$9 -> #REF! | Q13: =SUM(N13:P13)*Q$9 -> #REF! | R13: =SUM(M13:Q13) -> #REF! | T13: =SUM(N13:Q13)*$S$69 -> #REF! | U13: =M13*$S$69 -> #REF! | V13: =(K13+L13+Q13)*S$69 -> #REF!
A14: - | B14: =B13+1 -> #REF! | C14: In Initial Replacements | G14: =SUMIF(#REF!,$B14,#REF!) -> #REF! | H14: =G14*$H$9 -> #REF! | I14: =SUM(G14:H14)*I$9 -> #REF! | J14: =SUM(G14:I14)*J$9 -> #REF! | K14: =SUM(G14:J14)*K$9 -> #REF! | L14: =SUM(G14:K14)*L$9 -> #REF! | M14: =SUM(G14:L14) -> #REF! | N14: =M14*N$9 -> #REF! | O14: =M14*O$9 -> #REF! | P14: =M14*P$9 -> #REF! | Q14: =SUM(N14:P14)*Q$9 -> #REF! | R14: =SUM(M14:Q14) -> #REF!
A15: - | B15: =B14+1 -> #REF! | C15: In Initial Replacements | G15: =SUMIF(#REF!,$B15,#REF!) -> #REF! | H15: =G15*$H$9 -> #REF! | I15: =SUM(G15:H15)*I$9 -> #REF! | J15: =SUM(G15:I15)*J$9 -> #REF! | K15: =SUM(G15:J15)*K$9 -> #REF! | L15: =SUM(G15:K15)*L$9 -> #REF! | M15: =SUM(G15:L15) -> #REF! | N15: =M15*N$9 -> #REF! | O15: =M15*O$9 -> #REF! | P15: =M15*P$9 -> #REF! | Q15: =SUM(N15:P15)*Q$9 -> #REF! | R15: =SUM(M15:Q15) -> #REF!
B16: =B15+1 -> #REF! | C16: =B16+1 -> #REF! | G16: =SUMIF(#REF!,$B16,#REF!) -> #REF! | H16: =G16*$H$9 -> #REF! | I16: =SUM(G16:H16)*I$9 -> #REF! | J16: =SUM(G16:I16)*J$9 -> #REF! | K16: =SUM(G16:J16)*K$9 -> #REF! | L16: =SUM(G16:K16)*L$9 -> #REF! | M16: =SUM(G16:L16) -> #REF! | N16: =M16*N$9 -> #REF! | O16: =M16*O$9 -> #REF! | P16: =M16*P$9 -> #REF! | Q16: =SUM(N16:P16)*Q$9 -> #REF! | R16: =SUM(M16:Q16) -> #REF!
B17: =B16+1 -> #REF! | C17: =B17+1 -> #REF! | G17: =SUMIF(#REF!,$B17,#REF!) -> #REF! | H17: =G17*$H$9 -> #REF! | I17: =SUM(G17:H17)*I$9 -> #REF! | J17: =SUM(G17:I17)*J$9 -> #REF! | K17: =SUM(G17:J17)*K$9 -> #REF! | L17: =SUM(G17:K17)*L$9 -> #REF! | M17: =SUM(G17:L17) -> #REF! | N17: =M17*N$9 -> #REF! | O17: =M17*O$9 -> #REF! | P17: =M17*P$9 -> #REF! | Q17: =SUM(N17:P17)*Q$9 -> #REF! | R17: =SUM(M17:Q17) -> #REF!
B18: =B17+1 -> #REF! | C18: =B18+1 -> #REF! | G18: =SUMIF(#REF!,$B18,#REF!) -> #REF! | H18: =G18*$H$9 -> #REF! | I18: =SUM(G18:H18)*I$9 -> #REF! | J18: =SUM(G18:I18)*J$9 -> #REF! | K18: =SUM(G18:J18)*K$9 -> #REF! | L18: =SUM(G18:K18)*L$9 -> #REF! | M18: =SUM(G18:L18) -> #REF! | N18: =M18*N$9 -> #REF! | O18: =M18*O$9 -> #REF! | P18: =M18*P$9 -> #REF! | Q18: =SUM(N18:P18)*Q$9 -> #REF! | R18: =SUM(M18:Q18) -> #REF!
B19: =B18+1 -> #REF! | C19: =B19+1 -> #REF! | G19: =SUMIF(#REF!,$B19,#REF!) -> #REF! | H19: =G19*$H$9 -> #REF! | I19: =SUM(G19:H19)*I$9 -> #REF! | J19: =SUM(G19:I19)*J$9 -> #REF! | K19: =SUM(G19:J19)*K$9 -> #REF! | L19: =SUM(G19:K19)*L$9 -> #REF! | M19: =SUM(G19:L19) -> #REF! | N19: =M19*N$9 -> #REF! | O19: =M19*O$9 -> #REF! | P19: =M19*P$9 -> #REF! | Q19: =SUM(N19:P19)*Q$9 -> #REF! | R19: =SUM(M19:Q19) -> #REF!
B20: =B19+1 -> #REF! | C20: =B20+1 -> #REF! | G20: =SUMIF(#REF!,$B20,#REF!) -> #REF! | H20: =G20*$H$9 -> #REF! | I20: =SUM(G20:H20)*I$9 -> #REF! | J20: =SUM(G20:I20)*J$9 -> #REF! | K20: =SUM(G20:J20)*K$9 -> #REF! | L20: =SUM(G20:K20)*L$9 -> #REF! | M20: =SUM(G20:L20) -> #REF! | N20: =M20*N$9 -> #REF! | O20: =M20*O$9 -> #REF! | P20: =M20*P$9 -> #REF! | Q20: =SUM(N20:P20)*Q$9 -> #REF! | R20: =SUM(M20:Q20) -> #REF!
B21: =B20+1 -> #REF! | C21: =B21+1 -> #REF! | G21: =SUMIF(#REF!,$B21,#REF!) -> #REF! | H21: =G21*$H$9 -> #REF! | I21: =SUM(G21:H21)*I$9 -> #REF! | J21: =SUM(G21:I21)*J$9 -> #REF! | K21: =SUM(G21:J21)*K$9 -> #REF! | L21: =SUM(G21:K21)*L$9 -> #REF! | M21: =SUM(G21:L21) -> #REF! | N21: =M21*N$9 -> #REF! | O21: =M21*O$9 -> #REF! | P21: =M21*P$9 -> #REF! | Q21: =SUM(N21:P21)*Q$9 -> #REF! | R21: =SUM(M21:Q21) -> #REF!
B22: =B21+1 -> #REF! | C22: =B22+1 -> #REF! | G22: =SUMIF(#REF!,$B22,#REF!) -> #REF! | H22: =G22*$H$9 -> #REF! | I22: =SUM(G22:H22)*I$9 -> #REF! | J22: =SUM(G22:I22)*J$9 -> #REF! | K22: =SUM(G22:J22)*K$9 -> #REF! | L22: =SUM(G22:K22)*L$9 -> #REF! | M22: =SUM(G22:L22) -> #REF! | N22: =M22*N$9 -> #REF! | O22: =M22*O$9 -> #REF! | P22: =M22*P$9 -> #REF! | Q22: =SUM(N22:P22)*Q$9 -> #REF! | R22: =SUM(M22:Q22) -> #REF!
B23: =B22+1 -> #REF! | C23: =B23+1 -> #REF! | G23: =SUMIF(#REF!,$B23,#REF!) -> #REF! | H23: =G23*$H$9 -> #REF! | I23: =SUM(G23:H23)*I$9 -> #REF! | J23: =SUM(G23:I23)*J$9 -> #REF! | K23: =SUM(G23:J23)*K$9 -> #REF! | L23: =SUM(G23:K23)*L$9 -> #REF! | M23: =SUM(G23:L23) -> #REF! | N23: =M23*N$9 -> #REF! | O23: =M23*O$9 -> #REF! | P23: =M23*P$9 -> #REF! | Q23: =SUM(N23:P23)*Q$9 -> #REF! | R23: =SUM(M23:Q23) -> #REF!
B24: =B23+1 -> #REF! | C24: =B24+1 -> #REF! | G24: =SUMIF(#REF!,$B24,#REF!) -> #REF! | H24: =G24*$H$9 -> #REF! | I24: =SUM(G24:H24)*I$9 -> #REF! | J24: =SUM(G24:I24)*J$9 -> #REF! | K24: =SUM(G24:J24)*K$9 -> #REF! | L24: =SUM(G24:K24)*L$9 -> #REF! | M24: =SUM(G24:L24) -> #REF! | N24: =M24*N$9 -> #REF! | O24: =M24*O$9 -> #REF! | P24: =M24*P$9 -> #REF! | Q24: =SUM(N24:P24)*Q$9 -> #REF! | R24: =SUM(M24:Q24) -> #REF!
B25: =B24+1 -> #REF! | C25: =B25+1 -> #REF! | G25: =SUMIF(#REF!,$B25,#REF!) -> #REF! | H25: =G25*$H$9 -> #REF! | I25: =SUM(G25:H25)*I$9 -> #REF! | J25: =SUM(G25:I25)*J$9 -> #REF! | K25: =SUM(G25:J25)*K$9 -> #REF! | L25: =SUM(G25:K25)*L$9 -> #REF! | M25: =SUM(G25:L25) -> #REF! | N25: =M25*N$9 -> #REF! | O25: =M25*O$9 -> #REF! | P25: =M25*P$9 -> #REF! | Q25: =SUM(N25:P25)*Q$9 -> #REF! | R25: =SUM(M25:Q25) -> #REF!
B26: =B25+1 -> #REF! | C26: =B26+1 -> #REF! | G26: =SUMIF(#REF!,$B26,#REF!) -> #REF! | H26: =G26*$H$9 -> #REF! | I26: =SUM(G26:H26)*I$9 -> #REF! | J26: =SUM(G26:I26)*J$9 -> #REF! | K26: =SUM(G26:J26)*K$9 -> #REF! | L26: =SUM(G26:K26)*L$9 -> #REF! | M26: =SUM(G26:L26) -> #REF! | N26: =M26*N$9 -> #REF! | O26: =M26*O$9 -> #REF! | P26: =M26*P$9 -> #REF! | Q26: =SUM(N26:P26)*Q$9 -> #REF! | R26: =SUM(M26:Q26) -> #REF!
B27: =B26+1 -> #REF! | C27: =B27+1 -> #REF! | G27: =SUMIF(#REF!,$B27,#REF!) -> #REF! | H27: =G27*$H$9 -> #REF! | I27: =SUM(G27:H27)*I$9 -> #REF! | J27: =SUM(G27:I27)*J$9 -> #REF! | K27: =SUM(G27:J27)*K$9 -> #REF! | L27: =SUM(G27:K27)*L$9 -> #REF! | M27: =SUM(G27:L27) -> #REF! | N27: =M27*N$9 -> #REF! | O27: =M27*O$9 -> #REF! | P27: =M27*P$9 -> #REF! | Q27: =SUM(N27:P27)*Q$9 -> #REF! | R27: =SUM(M27:Q27) -> #REF!
... B61: =B60+1 -> #REF! | C61: =B61+1 -> #REF! | G61: =SUMIF(#REF!,$B61,#REF!) -> #REF! | H61: =G61*$H$9 -> #REF! | I61: =SUM(G61:H61)*I$9 -> #REF! | J61: =SUM(G61:I61)*J$9 -> #REF! | K61: =SUM(G61:J61)*K$9 -> #REF! | L61: =SUM(G61:K61)*L$9 -> #REF! | M61: =SUM(G61:L61) -> #REF! | N61: =M61*N$9 -> #REF! | O61: =M61*O$9 -> #REF! | P61: =M61*P$9 -> #REF! | Q61: =SUM(N61:P61)*Q$9 -> #REF! | R61: =SUM(M61:Q61) -> #REF!
H62: =G62*$H$9 -> 0 | I62: =SUM(G62:H62)*I$9 -> 0 | J62: =SUM(G62:I62)*J$9 -> 0 | K62: =SUM(G62:J62)*K$9 -> 0 | L62: =SUM(G62:K62)*L$9 -> 0 | M62: =SUM(G62:L62) -> 0 | N62: =M62*N$9 -> 0 | O62: =M62*O$9 -> 0 | P62: =M62*P$9 -> 0 | Q62: =SUM(N62:P62)*Q$9 -> 0 | R62: =SUM(M62:Q62) -> 0 | T62: =SUM(N62:Q62)*$S$69 -> 0 | U62: =M62*$S$69 -> 0 | V62: =(K62+L62+Q62)*S$69 -> 0
A64: Summary Water Distribution | G64: =SUM(G11:G62) -> #REF! | H64: =SUM(H11:H62) -> #REF! | I64: =SUM(I11:I62) -> #REF! | J64: =SUM(J11:J62) -> #REF! | K64: =SUM(K11:K62) -> #REF! | L64: =SUM(L11:L62) -> #REF! | M64: =SUM(M11:M62) -> #REF! | N64: =SUM(N11:N62) -> #REF! | ... R64: =SUM(R11:R62) -> #REF!

Sheet Richardson NatG Dist- R&R Proj
A1: Fort Richardson Natural Gas Distribution R&R Projects
A4: Project Number: Year 2
A5: Project Title: Upgrade Water System
A6: Year That Payment for Project Will Begin: Year 2 of the 50 Year Contract
A8: Project Description | B8: Year Implemented | C8: Year Payments Begin | D8: Quantity | E8: Unit of Measure | F8: Cost/UOM | G8: Base Constr Cost (no markups) | H8: Contingency | I8: Bonds, Insurance | J8: General Conditions | K8: G & A | L8: Profit | M8: Total Capital Cost | N8: Studies plus Predesign | O8: Design | P8: SDC | Q8: Fee on Professional Services | R8: Total Project Cost | T8: Engineering | U8: Construction | V8: GM
H9: 0.05 | I9: 0.02 | J9: 0.05 | K9: 0.122 | L9: 0.1 | N9: 0.077 | O9: 0.05 | P9: 0.03 | Q9: 0.1
A11: - | B11: =#REF! -> #REF! | C11: In Initial Replacements | G11: =SUMIF(#REF!,$B11,#REF!) -> #REF! | H11: =G11*$H$9 -> #REF! | I11: =SUM(G11:H11)*I$9 -> #REF! | J11: =SUM(G11:I11)*J$9 -> #REF! | K11: =SUM(G11:J11)*K$9 -> #REF! | L11: =SUM(G11:K11)*L$9 -> #REF! | M11: =SUM(G11:L11) -> #REF! | N11: =M11*N$9 -> #REF! | O11: =M11*O$9 -> #REF! | P11: =M11*P$9 -> #REF! | Q11: =SUM(N11:P11)*Q$9 -> #REF! | R11: =SUM(M11:Q11) -> #REF! | T11: =SUM(N11:Q11)*$S$69 -> #REF! | U11: =M11*$S$69 -> #REF! | V11: =(K11+L11+Q11)*S$69 -> #REF!
A12: - | B12: =B11+1 -> #REF! | C12: In Initial Replacements | G12: =SUMIF(#REF!,$B12,#REF!) -> #REF! | H12: =G12*$H$9 -> #REF! | I12: =SUM(G12:H12)*I$9 -> #REF! | J12: =SUM(G12:I12)*J$9 -> #REF! | K12: =SUM(G12:J12)*K$9 -> #REF! | L12: =SUM(G12:K12)*L$9 -> #REF! | M12: =SUM(G12:L12) -> #REF! | N12: =M12*N$9 -> #REF! | O12: =M12*O$9 -> #REF! | P12: =M12*P$9 -> #REF! | Q12: =SUM(N12:P12)*Q$9 -> #REF! | R12: =SUM(M12:Q12) -> #REF! | T12: =SUM(N12:Q12)*$S$69 -> #REF! | U12: =M12*$S$69 -> #REF! | V12: =(K12+L12+Q12)*S$69 -> #REF!
A13: - | B13: =B12+1 -> #REF! | C13: In Initial Replacements | G13: =SUMIF(#REF!,$B13,#REF!) -> #REF! | H13: =G13*$H$9 -> #REF! | I13: =SUM(G13:H13)*I$9 -> #REF! | J13: =SUM(G13:I13)*J$9 -> #REF! | K13: =SUM(G13:J13)*K$9 -> #REF! | L13: =SUM(G13:K13)*L$9 -> #REF! | M13: =SUM(G13:L13) -> #REF! | N13: =M13*N$9 -> #REF! | O13: =M13*O$9 -> #REF! | P13: =M13*P$9 -> #REF! | Q13: =SUM(N13:P13)*Q$9 -> #REF! | R13: =SUM(M13:Q13) -> #REF! | T13: =SUM(N13:Q13)*$S$69 -> #REF! | U13: =M13*$S$69 -> #REF! | V13: =(K13+L13+Q13)*S$69 -> #REF!
A14: - | B14: =B13+1 -> #REF! | C14: In Initial Replacements | G14: =SUMIF(#REF!,$B14,#REF!) -> #REF! | H14: =G14*$H$9 -> #REF! | I14: =SUM(G14:H14)*I$9 -> #REF! | J14: =SUM(G14:I14)*J$9 -> #REF! | K14: =SUM(G14:J14)*K$9 -> #REF! | L14: =SUM(G14:K14)*L$9 -> #REF! | M14: =SUM(G14:L14) -> #REF! | N14: =M14*N$9 -> #REF! | O14: =M14*O$9 -> #REF! | P14: =M14*P$9 -> #REF! | Q14: =SUM(N14:P14)*Q$9 -> #REF! | R14: =SUM(M14:Q14) -> #REF!
A15: - | B15: =B14+1 -> #REF! | C15: In Initial Replacements | G15: =SUMIF(#REF!,$B15,#REF!) -> #REF! | H15: =G15*$H$9 -> #REF! | I15: =SUM(G15:H15)*I$9 -> #REF! | J15: =SUM(G15:I15)*J$9 -> #REF! | K15: =SUM(G15:J15)*K$9 -> #REF! | L15: =SUM(G15:K15)*L$9 -> #REF! | M15: =SUM(G15:L15) -> #REF! | N15: =M15*N$9 -> #REF! | O15: =M15*O$9 -> #REF! | P15: =M15*P$9 -> #REF! | Q15: =SUM(N15:P15)*Q$9 -> #REF! | R15: =SUM(M15:Q15) -> #REF!
B16: =B15+1 -> #REF! | C16: =B16+1 -> #REF! | G16: =SUMIF(#REF!,$B16,#REF!) -> #REF! | H16: =G16*$H$9 -> #REF! | I16: =SUM(G16:H16)*I$9 -> #REF! | J16: =SUM(G16:I16)*J$9 -> #REF! | K16: =SUM(G16:J16)*K$9 -> #REF! | L16: =SUM(G16:K16)*L$9 -> #REF! | M16: =SUM(G16:L16) -> #REF! | N16: =M16*N$9 -> #REF! | O16: =M16*O$9 -> #REF! | P16: =M16*P$9 -> #REF! | Q16: =SUM(N16:P16)*Q$9 -> #REF! | R16: =SUM(M16:Q16) -> #REF!
B17: =B16+1 -> #REF! | C17: =B17+1 -> #REF! | G17: =SUMIF(#REF!,$B17,#REF!) -> #REF! | H17: =G17*$H$9 -> #REF! | I17: =SUM(G17:H17)*I$9 -> #REF! | J17: =SUM(G17:I17)*J$9 -> #REF! | K17: =SUM(G17:J17)*K$9 -> #REF! | L17: =SUM(G17:K17)*L$9 -> #REF! | M17: =SUM(G17:L17) -> #REF! | N17: =M17*N$9 -> #REF! | O17: =M17*O$9 -> #REF! | P17: =M17*P$9 -> #REF! | Q17: =SUM(N17:P17)*Q$9 -> #REF! | R17: =SUM(M17:Q17) -> #REF!
B18: =B17+1 -> #REF! | C18: =B18+1 -> #REF! | G18: =SUMIF(#REF!,$B18,#REF!) -> #REF! | H18: =G18*$H$9 -> #REF! | I18: =SUM(G18:H18)*I$9 -> #REF! | J18: =SUM(G18:I18)*J$9 -> #REF! | K18: =SUM(G18:J18)*K$9 -> #REF! | L18: =SUM(G18:K18)*L$9 -> #REF! | M18: =SUM(G18:L18) -> #REF! | N18: =M18*N$9 -> #REF! | O18: =M18*O$9 -> #REF! | P18: =M18*P$9 -> #REF! | Q18: =SUM(N18:P18)*Q$9 -> #REF! | R18: =SUM(M18:Q18) -> #REF!
B19: =B18+1 -> #REF! | C19: =B19+1 -> #REF! | G19: =SUMIF(#REF!,$B19,#REF!) -> #REF! | H19: =G19*$H$9 -> #REF! | I19: =SUM(G19:H19)*I$9 -> #REF! | J19: =SUM(G19:I19)*J$9 -> #REF! | K19: =SUM(G19:J19)*K$9 -> #REF! | L19: =SUM(G19:K19)*L$9 -> #REF! | M19: =SUM(G19:L19) -> #REF! | N19: =M19*N$9 -> #REF! | O19: =M19*O$9 -> #REF! | P19: =M19*P$9 -> #REF! | Q19: =SUM(N19:P19)*Q$9 -> #REF! | R19: =SUM(M19:Q19) -> #REF!
B20: =B19+1 -> #REF! | C20: =B20+1 -> #REF! | G20: =SUMIF(#REF!,$B20,#REF!) -> #REF! | H20: =G20*$H$9 -> #REF! | I20: =SUM(G20:H20)*I$9 -> #REF! | J20: =SUM(G20:I20)*J$9 -> #REF! | K20: =SUM(G20:J20)*K$9 -> #REF! | L20: =SUM(G20:K20)*L$9 -> #REF! | M20: =SUM(G20:L20) -> #REF! | N20: =M20*N$9 -> #REF! | O20: =M20*O$9 -> #REF! | P20: =M20*P$9 -> #REF! | Q20: =SUM(N20:P20)*Q$9 -> #REF! | R20: =SUM(M20:Q20) -> #REF!
B21: =B20+1 -> #REF! | C21: =B21+1 -> #REF! | G21: =SUMIF(#REF!,$B21,#REF!) -> #REF! | H21: =G21*$H$9 -> #REF! | I21: =SUM(G21:H21)*I$9 -> #REF! | J21: =SUM(G21:I21)*J$9 -> #REF! | K21: =SUM(G21:J21)*K$9 -> #REF! | L21: =SUM(G21:K21)*L$9 -> #REF! | M21: =SUM(G21:L21) -> #REF! | N21: =M21*N$9 -> #REF! | O21: =M21*O$9 -> #REF! | P21: =M21*P$9 -> #REF! | Q21: =SUM(N21:P21)*Q$9 -> #REF! | R21: =SUM(M21:Q21) -> #REF!
B22: =B21+1 -> #REF! | C22: =B22+1 -> #REF! | G22: =SUMIF(#REF!,$B22,#REF!) -> #REF! | H22: =G22*$H$9 -> #REF! | I22: =SUM(G22:H22)*I$9 -> #REF! | J22: =SUM(G22:I22)*J$9 -> #REF! | K22: =SUM(G22:J22)*K$9 -> #REF! | L22: =SUM(G22:K22)*L$9 -> #REF! | M22: =SUM(G22:L22) -> #REF! | N22: =M22*N$9 -> #REF! | O22: =M22*O$9 -> #REF! | P22: =M22*P$9 -> #REF! | Q22: =SUM(N22:P22)*Q$9 -> #REF! | R22: =SUM(M22:Q22) -> #REF!
B23: =B22+1 -> #REF! | C23: =B23+1 -> #REF! | G23: =SUMIF(#REF!,$B23,#REF!) -> #REF! | H23: =G23*$H$9 -> #REF! | I23: =SUM(G23:H23)*I$9 -> #REF! | J23: =SUM(G23:I23)*J$9 -> #REF! | K23: =SUM(G23:J23)*K$9 -> #REF! | L23: =SUM(G23:K23)*L$9 -> #REF! | M23: =SUM(G23:L23) -> #REF! | N23: =M23*N$9 -> #REF! | O23: =M23*O$9 -> #REF! | P23: =M23*P$9 -> #REF! | Q23: =SUM(N23:P23)*Q$9 -> #REF! | R23: =SUM(M23:Q23) -> #REF!
B24: =B23+1 -> #REF! | C24: =B24+1 -> #REF! | G24: =SUMIF(#REF!,$B24,#REF!) -> #REF! | H24: =G24*$H$9 -> #REF! | I24: =SUM(G24:H24)*I$9 -> #REF! | J24: =SUM(G24:I24)*J$9 -> #REF! | K24: =SUM(G24:J24)*K$9 -> #REF! | L24: =SUM(G24:K24)*L$9 -> #REF! | M24: =SUM(G24:L24) -> #REF! | N24: =M24*N$9 -> #REF! | O24: =M24*O$9 -> #REF! | P24: =M24*P$9 -> #REF! | Q24: =SUM(N24:P24)*Q$9 -> #REF! | R24: =SUM(M24:Q24) -> #REF!
B25: =B24+1 -> #REF! | C25: =B25+1 -> #REF! | G25: =SUMIF(#REF!,$B25,#REF!) -> #REF! | H25: =G25*$H$9 -> #REF! | I25: =SUM(G25:H25)*I$9 -> #REF! | J25: =SUM(G25:I25)*J$9 -> #REF! | K25: =SUM(G25:J25)*K$9 -> #REF! | L25: =SUM(G25:K25)*L$9 -> #REF! | M25: =SUM(G25:L25) -> #REF! | N25: =M25*N$9 -> #REF! | O25: =M25*O$9 -> #REF! | P25: =M25*P$9 -> #REF! | Q25: =SUM(N25:P25)*Q$9 -> #REF! | R25: =SUM(M25:Q25) -> #REF!
B26: =B25+1 -> #REF! | C26: =B26+1 -> #REF! | G26: =SUMIF(#REF!,$B26,#REF!) -> #REF! | H26: =G26*$H$9 -> #REF! | I26: =SUM(G26:H26)*I$9 -> #REF! | J26: =SUM(G26:I26)*J$9 -> #REF! | K26: =SUM(G26:J26)*K$9 -> #REF! | L26: =SUM(G26:K26)*L$9 -> #REF! | M26: =SUM(G26:L26) -> #REF! | N26: =M26*N$9 -> #REF! | O26: =M26*O$9 -> #REF! | P26: =M26*P$9 -> #REF! | Q26: =SUM(N26:P26)*Q$9 -> #REF! | R26: =SUM(M26:Q26) -> #REF!
B27: =B26+1 -> #REF! | C27: =B27+1 -> #REF! | G27: =SUMIF(#REF!,$B27,#REF!) -> #REF! | H27: =G27*$H$9 -> #REF! | I27: =SUM(G27:H27)*I$9 -> #REF! | J27: =SUM(G27:I27)*J$9 -> #REF! | K27: =SUM(G27:J27)*K$9 -> #REF! | L27: =SUM(G27:K27)*L$9 -> #REF! | M27: =SUM(G27:L27) -> #REF! | N27: =M27*N$9 -> #REF! | O27: =M27*O$9 -> #REF! | P27: =M27*P$9 -> #REF! | Q27: =SUM(N27:P27)*Q$9 -> #REF! | R27: =SUM(M27:Q27) -> #REF!
... B61: =B60+1 -> #REF! | C61: =B61+1 -> #REF! | G61: =SUMIF(#REF!,$B61,#REF!) -> #REF! | H61: =G61*$H$9 -> #REF! | I61: =SUM(G61:H61)*I$9 -> #REF! | J61: =SUM(G61:I61)*J$9 -> #REF! | K61: =SUM(G61:J61)*K$9 -> #REF! | L61: =SUM(G61:K61)*L$9 -> #REF! | M61: =SUM(G61:L61) -> #REF! | N61: =M61*N$9 -> #REF! | O61: =M61*O$9 -> #REF! | P61: =M61*P$9 -> #REF! | Q61: =SUM(N61:P61)*Q$9 -> #REF! | R61: =SUM(M61:Q61) -> #REF!
H62: =G62*$H$9 -> 0 | I62: =SUM(G62:H62)*I$9 -> 0 | J62: =SUM(G62:I62)*J$9 -> 0 | K62: =SUM(G62:J62)*K$9 -> 0 | L62: =SUM(G62:K62)*L$9 -> 0 | M62: =SUM(G62:L62) -> 0 | N62: =M62*N$9 -> 0 | O62: =M62*O$9 -> 0 | P62: =M62*P$9 -> 0 | Q62: =SUM(N62:P62)*Q$9 -> 0 | R62: =SUM(M62:Q62) -> 0 | T62: =SUM(N62:Q62)*$S$69 -> 0 | U62: =M62*$S$69 -> 0 | V62: =(K62+L62+Q62)*S$69 -> 0
A64: Summary Water Distribution | G64: =SUM(G11:G62) -> #REF! | H64: =SUM(H11:H62) -> #REF! | I64: =SUM(I11:I62) -> #REF! | J64: =SUM(J11:J62) -> #REF! | K64: =SUM(K11:K62) -> #REF! | L64: =SUM(L11:L62) -> #REF! | M64: =SUM(M11:M62) -> #REF! | N64: =SUM(N11:N62) -> #REF! | ... R64: =SUM(R11:R62) -> #REF!

Sheet Richardson Water - R&R Proj
A1: Fort Richardson Water Distribution R&R Projects
A4: Project Number: Year 2
A5: Project Title: Upgrade Water System
A6: Year That Payment for Project Will Begin: Year 2 of the 50 Year Contract
A8: Project Description | B8: Year Implemented | C8: Year Payments Begin | D8: Quantity | E8: Unit of Measure | F8: Cost/UOM | G8: Base Constr Cost (no markups) | H8: Contingency | I8: Bonds, Insurance | J8: General Conditions | K8: G & A | L8: Profit | M8: Total Capital Cost | N8: Studies plus Predesign | O8: Design | P8: SDC | Q8: Fee on Professional Services | R8: Total Project Cost | T8: Engineering | U8: Construction | V8: GM
H9: 0.05 | I9: 0.02 | J9: 0.05 | K9: 0.122 | L9: 0.1 | N9: 0.077 | O9: 0.05 | P9: 0.03 | Q9: 0.1
A11: - | B11: =#REF! -> #REF! | C11: In Initial Replacements | G11: =SUMIF(#REF!,$B11,#REF!) -> #REF! | H11: =G11*$H$9 -> #REF! | I11: =SUM(G11:H11)*I$9 -> #REF! | J11: =SUM(G11:I11)*J$9 -> #REF! | K11: =SUM(G11:J11)*K$9 -> #REF! | L11: =SUM(G11:K11)*L$9 -> #REF! | M11: =SUM(G11:L11) -> #REF! | N11: =M11*N$9 -> #REF! | O11: =M11*O$9 -> #REF! | P11: =M11*P$9 -> #REF! | Q11: =SUM(N11:P11)*Q$9 -> #REF! | R11: =SUM(M11:Q11) -> #REF! | T11: =SUM(N11:Q11)*$S$69 -> #REF! | U11: =M11*$S$69 -> #REF! | V11: =(K11+L11+Q11)*S$69 -> #REF!
A12: - | B12: =B11+1 -> #REF! | C12: In Initial Replacements | G12: =SUMIF(#REF!,$B12,#REF!) -> #REF! | H12: =G12*$H$9 -> #REF! | I12: =SUM(G12:H12)*I$9 -> #REF! | J12: =SUM(G12:I12)*J$9 -> #REF! | K12: =SUM(G12:J12)*K$9 -> #REF! | L12: =SUM(G12:K12)*L$9 -> #REF! | M12: =SUM(G12:L12) -> #REF! | N12: =M12*N$9 -> #REF! | O12: =M12*O$9 -> #REF! | P12: =M12*P$9 -> #REF! | Q12: =SUM(N12:P12)*Q$9 -> #REF! | R12: =SUM(M12:Q12) -> #REF! | T12: =SUM(N12:Q12)*$S$69 -> #REF! | U12: =M12*$S$69 -> #REF! | V12: =(K12+L12+Q12)*S$69 -> #REF!
A13: - | B13: =B12+1 -> #REF! | C13: In Initial Replacements | G13: =SUMIF(#REF!,$B13,#REF!) -> #REF! | H13: =G13*$H$9 -> #REF! | I13: =SUM(G13:H13)*I$9 -> #REF! | J13: =SUM(G13:I13)*J$9 -> #REF! | K13: =SUM(G13:J13)*K$9 -> #REF! | L13: =SUM(G13:K13)*L$9 -> #REF! | M13: =SUM(G13:L13) -> #REF! | N13: =M13*N$9 -> #REF! | O13: =M13*O$9 -> #REF! | P13: =M13*P$9 -> #REF! | Q13: =SUM(N13:P13)*Q$9 -> #REF! | R13: =SUM(M13:Q13) -> #REF! | T13: =SUM(N13:Q13)*$S$69 -> #REF! | U13: =M13*$S$69 -> #REF! | V13: =(K13+L13+Q13)*S$69 -> #REF!
A14: - | B14: =B13+1 -> #REF! | C14: In Initial Replacements | G14: =SUMIF(#REF!,$B14,#REF!) -> #REF! | H14: =G14*$H$9 -> #REF! | I14: =SUM(G14:H14)*I$9 -> #REF! | J14: =SUM(G14:I14)*J$9 -> #REF! | K14: =SUM(G14:J14)*K$9 -> #REF! | L14: =SUM(G14:K14)*L$9 -> #REF! | M14: =SUM(G14:L14) -> #REF! | N14: =M14*N$9 -> #REF! | O14: =M14*O$9 -> #REF! | P14: =M14*P$9 -> #REF! | Q14: =SUM(N14:P14)*Q$9 -> #REF! | R14: =SUM(M14:Q14) -> #REF!
A15: - | B15: =B14+1 -> #REF! | C15: In Initial Replacements | G15: =SUMIF(#REF!,$B15,#REF!) -> #REF! | H15: =G15*$H$9 -> #REF! | I15: =SUM(G15:H15)*I$9 -> #REF! | J15: =SUM(G15:I15)*J$9 -> #REF! | K15: =SUM(G15:J15)*K$9 -> #REF! | L15: =SUM(G15:K15)*L$9 -> #REF! | M15: =SUM(G15:L15) -> #REF! | N15: =M15*N$9 -> #REF! | O15: =M15*O$9 -> #REF! | P15: =M15*P$9 -> #REF! | Q15: =SUM(N15:P15)*Q$9 -> #REF! | R15: =SUM(M15:Q15) -> #REF!
B16: =B15+1 -> #REF! | C16: =B16+1 -> #REF! | G16: =SUMIF(#REF!,$B16,#REF!) -> #REF! | H16: =G16*$H$9 -> #REF! | I16: =SUM(G16:H16)*I$9 -> #REF! | J16: =SUM(G16:I16)*J$9 -> #REF! | K16: =SUM(G16:J16)*K$9 -> #REF! | L16: =SUM(G16:K16)*L$9 -> #REF! | M16: =SUM(G16:L16) -> #REF! | N16: =M16*N$9 -> #REF! | O16: =M16*O$9 -> #REF! | P16: =M16*P$9 -> #REF! | Q16: =SUM(N16:P16)*Q$9 -> #REF! | R16: =SUM(M16:Q16) -> #REF!
B17: =B16+1 -> #REF! | C17: =B17+1 -> #REF! | G17: =SUMIF(#REF!,$B17,#REF!) -> #REF! | H17: =G17*$H$9 -> #REF! | I17: =SUM(G17:H17)*I$9 -> #REF! | J17: =SUM(G17:I17)*J$9 -> #REF! | K17: =SUM(G17:J17)*K$9 -> #REF! | L17: =SUM(G17:K17)*L$9 -> #REF! | M17: =SUM(G17:L17) -> #REF! | N17: =M17*N$9 -> #REF! | O17: =M17*O$9 -> #REF! | P17: =M17*P$9 -> #REF! | Q17: =SUM(N17:P17)*Q$9 -> #REF! | R17: =SUM(M17:Q17) -> #REF!
B18: =B17+1 -> #REF! | C18: =B18+1 -> #REF! | G18: =SUMIF(#REF!,$B18,#REF!) -> #REF! | H18: =G18*$H$9 -> #REF! | I18: =SUM(G18:H18)*I$9 -> #REF! | J18: =SUM(G18:I18)*J$9 -> #REF! | K18: =SUM(G18:J18)*K$9 -> #REF! | L18: =SUM(G18:K18)*L$9 -> #REF! | M18: =SUM(G18:L18) -> #REF! | N18: =M18*N$9 -> #REF! | O18: =M18*O$9 -> #REF! | P18: =M18*P$9 -> #REF! | Q18: =SUM(N18:P18)*Q$9 -> #REF! | R18: =SUM(M18:Q18) -> #REF!
B19: =B18+1 -> #REF! | C19: =B19+1 -> #REF! | G19: =SUMIF(#REF!,$B19,#REF!) -> #REF! | H19: =G19*$H$9 -> #REF! | I19: =SUM(G19:H19)*I$9 -> #REF! | J19: =SUM(G19:I19)*J$9 -> #REF! | K19: =SUM(G19:J19)*K$9 -> #REF! | L19: =SUM(G19:K19)*L$9 -> #REF! | M19: =SUM(G19:L19) -> #REF! | N19: =M19*N$9 -> #REF! | O19: =M19*O$9 -> #REF! | P19: =M19*P$9 -> #REF! | Q19: =SUM(N19:P19)*Q$9 -> #REF! | R19: =SUM(M19:Q19) -> #REF!
B20: =B19+1 -> #REF! | C20: =B20+1 -> #REF! | G20: =SUMIF(#REF!,$B20,#REF!) -> #REF! | H20: =G20*$H$9 -> #REF! | I20: =SUM(G20:H20)*I$9 -> #REF! | J20: =SUM(G20:I20)*J$9 -> #REF! | K20: =SUM(G20:J20)*K$9 -> #REF! | L20: =SUM(G20:K20)*L$9 -> #REF! | M20: =SUM(G20:L20) -> #REF! | N20: =M20*N$9 -> #REF! | O20: =M20*O$9 -> #REF! | P20: =M20*P$9 -> #REF! | Q20: =SUM(N20:P20)*Q$9 -> #REF! | R20: =SUM(M20:Q20) -> #REF!
B21: =B20+1 -> #REF! | C21: =B21+1 -> #REF! | G21: =SUMIF(#REF!,$B21,#REF!) -> #REF! | H21: =G21*$H$9 -> #REF! | I21: =SUM(G21:H21)*I$9 -> #REF! | J21: =SUM(G21:I21)*J$9 -> #REF! | K21: =SUM(G21:J21)*K$9 -> #REF! | L21: =SUM(G21:K21)*L$9 -> #REF! | M21: =SUM(G21:L21) -> #REF! | N21: =M21*N$9 -> #REF! | O21: =M21*O$9 -> #REF! | P21: =M21*P$9 -> #REF! | Q21: =SUM(N21:P21)*Q$9 -> #REF! | R21: =SUM(M21:Q21) -> #REF!
B22: =B21+1 -> #REF! | C22: =B22+1 -> #REF! | G22: =SUMIF(#REF!,$B22,#REF!) -> #REF! | H22: =G22*$H$9 -> #REF! | I22: =SUM(G22:H22)*I$9 -> #REF! | J22: =SUM(G22:I22)*J$9 -> #REF! | K22: =SUM(G22:J22)*K$9 -> #REF! | L22: =SUM(G22:K22)*L$9 -> #REF! | M22: =SUM(G22:L22) -> #REF! | N22: =M22*N$9 -> #REF! | O22: =M22*O$9 -> #REF! | P22: =M22*P$9 -> #REF! | Q22: =SUM(N22:P22)*Q$9 -> #REF! | R22: =SUM(M22:Q22) -> #REF!
B23: =B22+1 -> #REF! | C23: =B23+1 -> #REF! | G23: =SUMIF(#REF!,$B23,#REF!) -> #REF! | H23: =G23*$H$9 -> #REF! | I23: =SUM(G23:H23)*I$9 -> #REF! | J23: =SUM(G23:I23)*J$9 -> #REF! | K23: =SUM(G23:J23)*K$9 -> #REF! | L23: =SUM(G23:K23)*L$9 -> #REF! | M23: =SUM(G23:L23) -> #REF! | N23: =M23*N$9 -> #REF! | O23: =M23*O$9 -> #REF! | P23: =M23*P$9 -> #REF! | Q23: =SUM(N23:P23)*Q$9 -> #REF! | R23: =SUM(M23:Q23) -> #REF!
B24: =B23+1 -> #REF! | C24: =B24+1 -> #REF! | G24: =SUMIF(#REF!,$B24,#REF!) -> #REF! | H24: =G24*$H$9 -> #REF! | I24: =SUM(G24:H24)*I$9 -> #REF! | J24: =SUM(G24:I24)*J$9 -> #REF! | K24: =SUM(G24:J24)*K$9 -> #REF! | L24: =SUM(G24:K24)*L$9 -> #REF! | M24: =SUM(G24:L24) -> #REF! | N24: =M24*N$9 -> #REF! | O24: =M24*O$9 -> #REF! | P24: =M24*P$9 -> #REF! | Q24: =SUM(N24:P24)*Q$9 -> #REF! | R24: =SUM(M24:Q24) -> #REF!
B25: =B24+1 -> #REF! | C25: =B25+1 -> #REF! | G25: =SUMIF(#REF!,$B25,#REF!) -> #REF! | H25: =G25*$H$9 -> #REF! | I25: =SUM(G25:H25)*I$9 -> #REF! | J25: =SUM(G25:I25)*J$9 -> #REF! | K25: =SUM(G25:J25)*K$9 -> #REF! | L25: =SUM(G25:K25)*L$9 -> #REF! | M25: =SUM(G25:L25) -> #REF! | N25: =M25*N$9 -> #REF! | O25: =M25*O$9 -> #REF! | P25: =M25*P$9 -> #REF! | Q25: =SUM(N25:P25)*Q$9 -> #REF! | R25: =SUM(M25:Q25) -> #REF!
B26: =B25+1 -> #REF! | C26: =B26+1 -> #REF! | G26: =SUMIF(#REF!,$B26,#REF!) -> #REF! | H26: =G26*$H$9 -> #REF! | I26: =SUM(G26:H26)*I$9 -> #REF! | J26: =SUM(G26:I26)*J$9 -> #REF! | K26: =SUM(G26:J26)*K$9 -> #REF! | L26: =SUM(G26:K26)*L$9 -> #REF! | M26: =SUM(G26:L26) -> #REF! | N26: =M26*N$9 -> #REF! | O26: =M26*O$9 -> #REF! | P26: =M26*P$9 -> #REF! | Q26: =SUM(N26:P26)*Q$9 -> #REF! | R26: =SUM(M26:Q26) -> #REF!
B27: =B26+1 -> #REF! | C27: =B27+1 -> #REF! | G27: =SUMIF(#REF!,$B27,#REF!) -> #REF! | H27: =G27*$H$9 -> #REF! | I27: =SUM(G27:H27)*I$9 -> #REF! | J27: =SUM(G27:I27)*J$9 -> #REF! | K27: =SUM(G27:J27)*K$9 -> #REF! | L27: =SUM(G27:K27)*L$9 -> #REF! | M27: =SUM(G27:L27) -> #REF! | N27: =M27*N$9 -> #REF! | O27: =M27*O$9 -> #REF! | P27: =M27*P$9 -> #REF! | Q27: =SUM(N27:P27)*Q$9 -> #REF! | R27: =SUM(M27:Q27) -> #REF!
... B61: =B60+1 -> #REF! | C61: =B61+1 -> #REF! | G61: =SUMIF(#REF!,$B61,#REF!) -> #REF! | H61: =G61*$H$9 -> #REF! | I61: =SUM(G61:H61)*I$9 -> #REF! | J61: =SUM(G61:I61)*J$9 -> #REF! | K61: =SUM(G61:J61)*K$9 -> #REF! | L61: =SUM(G61:K61)*L$9 -> #REF! | M61: =SUM(G61:L61) -> #REF! | N61: =M61*N$9 -> #REF! | O61: =M61*O$9 -> #REF! | P61: =M61*P$9 -> #REF! | Q61: =SUM(N61:P61)*Q$9 -> #REF! | R61: =SUM(M61:Q61) -> #REF!
H62: =G62*$H$9 -> 0 | I62: =SUM(G62:H62)*I$9 -> 0 | J62: =SUM(G62:I62)*J$9 -> 0 | K62: =SUM(G62:J62)*K$9 -> 0 | L62: =SUM(G62:K62)*L$9 -> 0 | M62: =SUM(G62:L62) -> 0 | N62: =M62*N$9 -> 0 | O62: =M62*O$9 -> 0 | P62: =M62*P$9 -> 0 | Q62: =SUM(N62:P62)*Q$9 -> 0 | R62: =SUM(M62:Q62) -> 0 | T62: =SUM(N62:Q62)*$S$69 -> 0 | U62: =M62*$S$69 -> 0 | V62: =(K62+L62+Q62)*S$69 -> 0
A64: Summary Water Distribution | G64: =SUM(G11:G62) -> #REF! | H64: =SUM(H11:H62) -> #REF! | I64: =SUM(I11:I62) -> #REF! | J64: =SUM(J11:J62) -> #REF! | K64: =SUM(K11:K62) -> #REF! | L64: =SUM(L11:L62) -> #REF! | M64: =SUM(M11:M62) -> #REF! | N64: =SUM(N11:N62) -> #REF! | ... R64: =SUM(R11:R62) -> #REF!

Sheet Wainwright Summary
B2: Doyon Utilities, LLC
B3: Fort Wainwright Utility Inventory and Replacement Cost
B4: Fort Wainwright Summary
A6: Estimate Basis Year | E6: 2007
A7: Year of Implementation | E7: 2008
A9: Note: RCN INCLUDES Contractor Mark-ups and Studies/Enginering Costs to 2058 only | B9: CIP Projects and initial R&R Projects (RCN w. mark-ups and engineering Costs) - from CIP workbook - | C9: RCN (Total w. Enginering) Yrs 6-10 | D9: Capital Investment Yrs 1-10 | E9: RCN (Total w. Enginering) Yrs 11-50 | F9: Total 50 year Capex | G9: RCNLD (Kind-for-Kind) | H9: RCNLD (PDC Harris estimate for 30 Mwe CFB plant | I9: Appraisal Valueation (Capitalized earnings) | J9: OC | K9: OCLD | M9: Purchase Offer | N9: Valuation basis | O9: Average Depreciation Years remaining
B10: 2009-2013 | C10: 2014-2018 only
A11: Wainwright CHPP only | B11: ='CM Cost Estimating Worksheet'!#REF! -> #REF! | C11: ='CM Cost Estimating Worksheet'!#REF! -> #REF! | D11: =SUM(B11:C11) -> #REF! | E11: ='CM Cost Estimating Worksheet'!#REF! -> #REF! | F11: =SUM(D11:E11) -> #REF! | G11: ='CM Cost Estimating Worksheet'!#REF! -> #REF! | H11: =107000000*0.17 -> 18190000 | J11: ='CM Cost Estimating Worksheet'!#REF! -> #REF! | K11: ='CM Cost Estimating Worksheet'!#REF! -> #REF! | M11: =K11 -> #REF! | N11: OCLD | O11: ='CM Cost Estimating Worksheet'!#REF!-2008 -> #REF!
A12: Wainwright Heat Distribution only | B12: ='CM Cost Estimating Worksheet'!#REF! -> #REF! | C12: ='CM Cost Estimating Worksheet'!#REF! -> #REF! | D12: =SUM(B12:C12) -> #REF! | E12: ='CM Cost Estimating Worksheet'!#REF! -> #REF! | F12: =SUM(D12:E12) -> #REF! | G12: ='CM Cost Estimating Worksheet'!#REF! -> #REF! | H12: na | J12: ='CM Cost Estimating Worksheet'!#REF! -> #REF! | K12: ='CM Cost Estimating Worksheet'!#REF! -> #REF! | M12: =ROUND(K12,-2) -> #REF! | N12: OCLD | O12: ='CM Cost Estimating Worksheet'!#REF!-2008 -> #REF!
A13: Wainwright Utilidors | B13: ='CM Cost Estimating Worksheet'!#REF! -> #REF! | C13: ='CM Cost Estimating Worksheet'!#REF! -> #REF! | D13: =SUM(B13:C13) -> #REF! | E13: ='CM Cost Estimating Worksheet'!AA11 -> 0 | F13: =SUM(D13:E13) -> #REF! | G13: ='CM Cost Estimating Worksheet'!#REF! -> #REF! | H13: na | J13: ='CM Cost Estimating Worksheet'!#REF! -> #REF! | K13: ='CM Cost Estimating Worksheet'!#REF! -> #REF! | M13: =K13 -> #REF! | N13: OCLD | O13: ='CM Cost Estimating Worksheet'!#REF!-2008 -> #REF!
A14: Total CHP&P & HDS | B14: =SUM(B11:B13) -> #REF! | C14: =SUM(C11:C13) -> #REF! | D14: =SUM(D11:D13) -> #REF! | E14: =SUM(E11:E13) -> #REF! | F14: =SUM(F11:F13) -> #REF! | G14: =SUM(G11:G13) -> #REF! | H14: =SUM(H11:H13) -> 18190000 | I14: 37700000 | J14: =SUM(J11:J13) -> #REF! | K14: =SUM(K11:K13) -> #REF! | M14: =SUM(M11:M13) -> #REF! | O14: =AVERAGE(O12,O11) -> #REF!
A16: Wainwright Electrical Distribution | B16: ='Wainwright Electrical Dist'!AA168 -> 33925662 | C16: ='Wainwright Electrical Dist'!AA169 -> 2704087.7 | D16: =SUM(B16:C16) -> 36629749 | E16: ='Wainwright Electrical Dist'!AA170 -> 18795289 | F16: =SUM(D16:E16) -> 55425038 | G16: ='Wainwright Electrical Dist'!AC167 -> 14411691 | J16: ='Wainwright Electrical Dist'!AE167 -> 16384700 | K16: ='Wainwright Electrical Dist'!AF167 -> 4605102.6 | M16: =ROUND(K16,-2) -> 4605100 | N16: OCLD | O16: ='Wainwright Electrical Dist'!AG171-2008 -> 16.857021
A18: Wainwright Water Distribution | B18: ='Wainwright Water Dist'!AA247 -> 3425005.9 | C18: ='Wainwright Water Dist'!AA248 -> 101990 | D18: =SUM(B18:C18) -> 3526995.9 | E18: ='Wainwright Water Dist'!AA249 -> 47424079 | F18: =SUM(D18:E18) -> 50951075 | G18: ='Wainwright Water Dist'!AC246 -> 23031903 | J18: ='Wainwright Water Dist'!AE246 -> 17786031 | K18: ='Wainwright Water Dist'!AF246 -> 7746729.1 | M18: =ROUND(K18,-2) -> 7746700 | N18: OCLD | O18: ='Wainwright Water Dist'!AG252-2008 -> 19.184938
A20: Wainwright Wastewater Collection | B20: ='Wainwright WW Collection'!AA340 -> 9637438.7 | C20: ='Wainwright WW Collection'!AA341 -> 1049081.4 | D20: =SUM(B20:C20) -> 10686520 | E20: ='Wainwright WW Collection'!AA342 -> 33873420 | F20: =SUM(D20:E20) -> 44559940 | G20: ='Wainwright WW Collection'!AC335 -> 19164563 | J20: ='Wainwright WW Collection'!AE335 -> 9820568.3 | K20: ='Wainwright WW Collection'!AF335 -> 4420127.9 | M20: =ROUND(K20,-2) -> 4420100 | N20: OCLD | O20: ='Wainwright WW Collection'!AG343-2008 -> 29.2
A22: Total | B22: =SUM(B14:B20) -> #REF! | C22: =SUM(C14:C20) -> #REF! | D22: =SUM(D14:D20) -> #REF! | E22: =SUM(E14:E20) -> #REF! | F22: =SUM(F14:F20) -> #REF! | G22: =SUM(G11:G21) -> #REF! | J22: =SUM(J14:J20) -> #REF! | K22: =SUM(K14:K20) -> #REF! | M22: =SUM(M14:M21) -> #REF!
B24: C/S (20% min) | C24: 0.35 | D24: =$C$24*D22 -> #REF! | E24: =$C$24*E22 -> #REF! | F24: =$C$24*F22 -> #REF! | M24: financed by amortization of Purchase debt
B25: Sub-Debt | C25: 0 | D25: =D22*$C$25 -> #REF! | E25: =E22*$C$25 -> #REF! | F25: =F22*$C$25 -> #REF! | M25: by internal Depreciation charges (cashflow neurtal)
B26: Senior Debt | C26: =1-C24-C25 -> 0.65 | D26: =D22-D24-D25 -> #REF! | E26: =E22-E24-E25 -> #REF! | F26: =F22-F24-F25 -> #REF!
B27: (Investment Grade) | C27: =SUM(C24:C26) -> 1 | D27: =SUM(D24:D26) -> #REF! | E27: =SUM(E24:E26) -> #REF! | F27: =SUM(F24:F26) -> #REF!
B29: DOYON Equity | C29: 0.51 | D29: =D24*$C$29 -> #REF! | E29: =E24*$C$29 -> #REF! | F29: =F24*$C$29 -> #REF!
B30: FSW Equity | C30: 0.245 | D30: =D24*$C$30 -> #REF! | E30: =E24*$C$30 -> #REF! | F30: =F24*$C$30 -> #REF!
B31: AES Equity | C31: 0.245 | D31: =D24*$C$31 -> #REF! | E31: =E24*$C$31 -> #REF! | F31: =F24*$C$31 -> #REF!
D32: =SUM(D29:D31) -> #REF! | E32: =SUM(E29:E31) -> #REF! | F32: =SUM(F29:F31) -> #REF!
A34: Debt Financed (60%) | B34: =0.6*B22 -> #REF! | C34: =0.6*C22 -> #REF! | D34: =0.6*D22 -> #REF! | E34: =0.6*E22 -> #REF! | F34: =0.6*F22 -> #REF! | M34: Contrbution in Add of Construction Tax:
A35: Equity Financed (40%) | B35: =0.4*B22 -> #REF! | C35: =0.4*C22 -> #REF! | D35: =0.4*D22 -> #REF! | E35: =0.4*E22 -> #REF! | F35: =0.4*F22 -> #REF! | M35: Purchase Price: | N35: =M11 -> #REF! | O35: =N11 -> OCLD
M36: Appraisal Value: | N36: =I14 -> 37700000 | O36: earnings mulytiple
M37: RCNLD (CFB Boiler): | N37: =H14 -> 18190000 | O37: RCNLD (new tech)
M39: Purchase price is based on RCA standard methodology for regulated
M40: utilities based on OCLD. CIAC Tax is not applicable on power & HDS
M41: assets ifthe Proposed purchase price is in excess of FMV or other valuation
M42: methods.

Sheet Wainwright CHPP&Dist- R&R Proj
A1: Fort Wainwright CHPP and Heat Distribution R&R Projects
A4: Project Number: Year 2
A5: Project Title: Upgrade Water System
A6: Year That Payment for Project Will Begin: Year 2 of the 50 Year Contract
A8: Project Description | B8: Year Implemented | C8: Year Payments Begin | D8: Quantity | E8: Unit of Measure | F8: Cost/UOM | G8: Base Constr Cost (no markups) | H8: Contingency | I8: Bonds, Insurance | J8: General Conditions | K8: G & A | L8: Profit | M8: Total Capital Cost | N8: Studies plus Predesign | O8: Design | P8: SDC | Q8: Fee on Professional Services | R8: Total Project Cost | T8: Engineering | U8: Construction | V8: GM
H9: 0.05 | I9: 0.02 | J9: 0.05 | K9: 0.122 | L9: 0.1 | N9: 0.077 | O9: 0.05 | P9: 0.03 | Q9: 0.1
A11: - | B11: ='Wainwright Summary'!E7 -> 2008 | C11: In Initial Replacements | G11: =SUMIF(Wainwright_All_R_R_Th!$D$4:$BB$4,$B11,Wainwright_All_R_R_Th!$D$5:$BB$5) -> 0 | H11: =G11*$H$9 -> 0 | I11: =SUM(G11:H11)*I$9 -> 0 | J11: =SUM(G11:I11)*J$9 -> 0 | K11: =SUM(G11:J11)*K$9 -> 0 | L11: =SUM(G11:K11)*L$9 -> 0 | M11: =SUM(G11:L11) -> 0 | N11: =M11*N$9 -> 0 | O11: =M11*O$9 -> 0 | P11: =M11*P$9 -> 0 | Q11: =SUM(N11:P11)*Q$9 -> 0 | R11: =SUM(M11:Q11) -> 0 | T11: =SUM(N11:Q11)*$S$69 -> 0 | U11: =M11*$S$69 -> 0 | V11: =(K11+L11+Q11)*S$69 -> 0
A12: - | B12: =B11+1 -> 2009 | C12: In Initial Replacements | G12: =SUMIF(Wainwright_All_R_R_Th!$D$4:$BB$4,$B12,Wainwright_All_R_R_Th!$D$5:$BB$5) -> 12350 | H12: =G12*$H$9 -> 617.5 | I12: =SUM(G12:H12)*I$9 -> 259.35 | J12: =SUM(G12:I12)*J$9 -> 661.3425 | K12: =SUM(G12:J12)*K$9 -> 1694.3595 | L12: =SUM(G12:K12)*L$9 -> 1558.2552 | M12: =SUM(G12:L12) -> 17140.807 | N12: =M12*N$9 -> 1319.8422 | O12: =M12*O$9 -> 857.04036 | P12: =M12*P$9 -> 514.22422 | Q12: =SUM(N12:P12)*Q$9 -> 269.11067 | R12: =SUM(M12:Q12) -> 20101.025 | T12: =SUM(N12:Q12)*$S$69 -> 0 | U12: =M12*$S$69 -> 0 | V12: =(K12+L12+Q12)*S$69 -> 0
A13: - | B13: =B12+1 -> 2010 | C13: In Initial Replacements | G13: =SUMIF(Wainwright_All_R_R_Th!$D$4:$BB$4,$B13,Wainwright_All_R_R_Th!$D$5:$BB$5) -> 0 | H13: =G13*$H$9 -> 0 | I13: =SUM(G13:H13)*I$9 -> 0 | J13: =SUM(G13:I13)*J$9 -> 0 | K13: =SUM(G13:J13)*K$9 -> 0 | L13: =SUM(G13:K13)*L$9 -> 0 | M13: =SUM(G13:L13) -> 0 | N13: =M13*N$9 -> 0 | O13: =M13*O$9 -> 0 | P13: =M13*P$9 -> 0 | Q13: =SUM(N13:P13)*Q$9 -> 0 | R13: =SUM(M13:Q13) -> 0 | T13: =SUM(N13:Q13)*$S$69 -> 0 | U13: =M13*$S$69 -> 0 | V13: =(K13+L13+Q13)*S$69 -> 0
A14: - | B14: =B13+1 -> 2011 | C14: In Initial Replacements | G14: =SUMIF(Wainwright_All_R_R_Th!$D$4:$BB$4,$B14,Wainwright_All_R_R_Th!$D$5:$BB$5) -> 0 | H14: =G14*$H$9 -> 0 | I14: =SUM(G14:H14)*I$9 -> 0 | J14: =SUM(G14:I14)*J$9 -> 0 | K14: =SUM(G14:J14)*K$9 -> 0 | L14: =SUM(G14:K14)*L$9 -> 0 | M14: =SUM(G14:L14) -> 0 | N14: =M14*N$9 -> 0 | O14: =M14*O$9 -> 0 | P14: =M14*P$9 -> 0 | Q14: =SUM(N14:P14)*Q$9 -> 0 | R14: =SUM(M14:Q14) -> 0
A15: - | B15: =B14+1 -> 2012 | C15: In Initial Replacements | G15: =SUMIF(Wainwright_All_R_R_Th!$D$4:$BB$4,$B15,Wainwright_All_R_R_Th!$D$5:$BB$5) -> 0 | H15: =G15*$H$9 -> 0 | I15: =SUM(G15:H15)*I$9 -> 0 | J15: =SUM(G15:I15)*J$9 -> 0 | K15: =SUM(G15:J15)*K$9 -> 0 | L15: =SUM(G15:K15)*L$9 -> 0 | M15: =SUM(G15:L15) -> 0 | N15: =M15*N$9 -> 0 | O15: =M15*O$9 -> 0 | P15: =M15*P$9 -> 0 | Q15: =SUM(N15:P15)*Q$9 -> 0 | R15: =SUM(M15:Q15) -> 0
B16: =B15+1 -> 2013 | C16: =B16+1 -> 2014 | G16: =SUMIF(Wainwright_All_R_R_Th!$D$4:$BB$4,$B16,Wainwright_All_R_R_Th!$D$5:$BB$5) -> 0 | H16: =G16*$H$9 -> 0 | I16: =SUM(G16:H16)*I$9 -> 0 | J16: =SUM(G16:I16)*J$9 -> 0 | K16: =SUM(G16:J16)*K$9 -> 0 | L16: =SUM(G16:K16)*L$9 -> 0 | M16: =SUM(G16:L16) -> 0 | N16: =M16*N$9 -> 0 | O16: =M16*O$9 -> 0 | P16: =M16*P$9 -> 0 | Q16: =SUM(N16:P16)*Q$9 -> 0 | R16: =SUM(M16:Q16) -> 0
B17: =B16+1 -> 2014 | C17: =B17+1 -> 2015 | G17: =SUMIF(Wainwright_All_R_R_Th!$D$4:$BB$4,$B17,Wainwright_All_R_R_Th!$D$5:$BB$5) -> 0 | H17: =G17*$H$9 -> 0 | I17: =SUM(G17:H17)*I$9 -> 0 | J17: =SUM(G17:I17)*J$9 -> 0 | K17: =SUM(G17:J17)*K$9 -> 0 | L17: =SUM(G17:K17)*L$9 -> 0 | M17: =SUM(G17:L17) -> 0 | N17: =M17*N$9 -> 0 | O17: =M17*O$9 -> 0 | P17: =M17*P$9 -> 0 | Q17: =SUM(N17:P17)*Q$9 -> 0 | R17: =SUM(M17:Q17) -> 0
B18: =B17+1 -> 2015 | C18: =B18+1 -> 2016 | G18: =SUMIF(Wainwright_All_R_R_Th!$D$4:$BB$4,$B18,Wainwright_All_R_R_Th!$D$5:$BB$5) -> 0 | H18: =G18*$H$9 -> 0 | I18: =SUM(G18:H18)*I$9 -> 0 | J18: =SUM(G18:I18)*J$9 -> 0 | K18: =SUM(G18:J18)*K$9 -> 0 | L18: =SUM(G18:K18)*L$9 -> 0 | M18: =SUM(G18:L18) -> 0 | N18: =M18*N$9 -> 0 | O18: =M18*O$9 -> 0 | P18: =M18*P$9 -> 0 | Q18: =SUM(N18:P18)*Q$9 -> 0 | R18: =SUM(M18:Q18) -> 0
B19: =B18+1 -> 2016 | C19: =B19+1 -> 2017 | G19: =SUMIF(Wainwright_All_R_R_Th!$D$4:$BB$4,$B19,Wainwright_All_R_R_Th!$D$5:$BB$5) -> 0 | H19: =G19*$H$9 -> 0 | I19: =SUM(G19:H19)*I$9 -> 0 | J19: =SUM(G19:I19)*J$9 -> 0 | K19: =SUM(G19:J19)*K$9 -> 0 | L19: =SUM(G19:K19)*L$9 -> 0 | M19: =SUM(G19:L19) -> 0 | N19: =M19*N$9 -> 0 | O19: =M19*O$9 -> 0 | P19: =M19*P$9 -> 0 | Q19: =SUM(N19:P19)*Q$9 -> 0 | R19: =SUM(M19:Q19) -> 0
B20: =B19+1 -> 2017 | C20: =B20+1 -> 2018 | G20: =SUMIF(Wainwright_All_R_R_Th!$D$4:$BB$4,$B20,Wainwright_All_R_R_Th!$D$5:$BB$5) -> 0 | H20: =G20*$H$9 -> 0 | I20: =SUM(G20:H20)*I$9 -> 0 | J20: =SUM(G20:I20)*J$9 -> 0 | K20: =SUM(G20:J20)*K$9 -> 0 | L20: =SUM(G20:K20)*L$9 -> 0 | M20: =SUM(G20:L20) -> 0 | N20: =M20*N$9 -> 0 | O20: =M20*O$9 -> 0 | P20: =M20*P$9 -> 0 | Q20: =SUM(N20:P20)*Q$9 -> 0 | R20: =SUM(M20:Q20) -> 0
B21: =B20+1 -> 2018 | C21: =B21+1 -> 2019 | G21: =SUMIF(Wainwright_All_R_R_Th!$D$4:$BB$4,$B21,Wainwright_All_R_R_Th!$D$5:$BB$5) -> 0 | H21: =G21*$H$9 -> 0 | I21: =SUM(G21:H21)*I$9 -> 0 | J21: =SUM(G21:I21)*J$9 -> 0 | K21: =SUM(G21:J21)*K$9 -> 0 | L21: =SUM(G21:K21)*L$9 -> 0 | M21: =SUM(G21:L21) -> 0 | N21: =M21*N$9 -> 0 | O21: =M21*O$9 -> 0 | P21: =M21*P$9 -> 0 | Q21: =SUM(N21:P21)*Q$9 -> 0 | R21: =SUM(M21:Q21) -> 0
B22: =B21+1 -> 2019 | C22: =B22+1 -> 2020 | G22: =SUMIF(Wainwright_All_R_R_Th!$D$4:$BB$4,$B22,Wainwright_All_R_R_Th!$D$5:$BB$5) -> 0 | H22: =G22*$H$9 -> 0 | I22: =SUM(G22:H22)*I$9 -> 0 | J22: =SUM(G22:I22)*J$9 -> 0 | K22: =SUM(G22:J22)*K$9 -> 0 | L22: =SUM(G22:K22)*L$9 -> 0 | M22: =SUM(G22:L22) -> 0 | N22: =M22*N$9 -> 0 | O22: =M22*O$9 -> 0 | P22: =M22*P$9 -> 0 | Q22: =SUM(N22:P22)*Q$9 -> 0 | R22: =SUM(M22:Q22) -> 0
B23: =B22+1 -> 2020 | C23: =B23+1 -> 2021 | G23: =SUMIF(Wainwright_All_R_R_Th!$D$4:$BB$4,$B23,Wainwright_All_R_R_Th!$D$5:$BB$5) -> 0 | H23: =G23*$H$9 -> 0 | I23: =SUM(G23:H23)*I$9 -> 0 | J23: =SUM(G23:I23)*J$9 -> 0 | K23: =SUM(G23:J23)*K$9 -> 0 | L23: =SUM(G23:K23)*L$9 -> 0 | M23: =SUM(G23:L23) -> 0 | N23: =M23*N$9 -> 0 | O23: =M23*O$9 -> 0 | P23: =M23*P$9 -> 0 | Q23: =SUM(N23:P23)*Q$9 -> 0 | R23: =SUM(M23:Q23) -> 0
B24: =B23+1 -> 2021 | C24: =B24+1 -> 2022 | G24: =SUMIF(Wainwright_All_R_R_Th!$D$4:$BB$4,$B24,Wainwright_All_R_R_Th!$D$5:$BB$5) -> 0 | H24: =G24*$H$9 -> 0 | I24: =SUM(G24:H24)*I$9 -> 0 | J24: =SUM(G24:I24)*J$9 -> 0 | K24: =SUM(G24:J24)*K$9 -> 0 | L24: =SUM(G24:K24)*L$9 -> 0 | M24: =SUM(G24:L24) -> 0 | N24: =M24*N$9 -> 0 | O24: =M24*O$9 -> 0 | P24: =M24*P$9 -> 0 | Q24: =SUM(N24:P24)*Q$9 -> 0 | R24: =SUM(M24:Q24) -> 0
B25: =B24+1 -> 2022 | C25: =B25+1 -> 2023 | G25: =SUMIF(Wainwright_All_R_R_Th!$D$4:$BB$4,$B25,Wainwright_All_R_R_Th!$D$5:$BB$5) -> 0 | H25: =G25*$H$9 -> 0 | I25: =SUM(G25:H25)*I$9 -> 0 | J25: =SUM(G25:I25)*J$9 -> 0 | K25: =SUM(G25:J25)*K$9 -> 0 | L25: =SUM(G25:K25)*L$9 -> 0 | M25: =SUM(G25:L25) -> 0 | N25: =M25*N$9 -> 0 | O25: =M25*O$9 -> 0 | P25: =M25*P$9 -> 0 | Q25: =SUM(N25:P25)*Q$9 -> 0 | R25: =SUM(M25:Q25) -> 0
B26: =B25+1 -> 2023 | C26: =B26+1 -> 2024 | G26: =SUMIF(Wainwright_All_R_R_Th!$D$4:$BB$4,$B26,Wainwright_All_R_R_Th!$D$5:$BB$5) -> 0 | H26: =G26*$H$9 -> 0 | I26: =SUM(G26:H26)*I$9 -> 0 | J26: =SUM(G26:I26)*J$9 -> 0 | K26: =SUM(G26:J26)*K$9 -> 0 | L26: =SUM(G26:K26)*L$9 -> 0 | M26: =SUM(G26:L26) -> 0 | N26: =M26*N$9 -> 0 | O26: =M26*O$9 -> 0 | P26: =M26*P$9 -> 0 | Q26: =SUM(N26:P26)*Q$9 -> 0 | R26: =SUM(M26:Q26) -> 0
B27: =B26+1 -> 2024 | C27: =B27+1 -> 2025 | G27: =SUMIF(Wainwright_All_R_R_Th!$D$4:$BB$4,$B27,Wainwright_All_R_R_Th!$D$5:$BB$5) -> 0 | H27: =G27*$H$9 -> 0 | I27: =SUM(G27:H27)*I$9 -> 0 | J27: =SUM(G27:I27)*J$9 -> 0 | K27: =SUM(G27:J27)*K$9 -> 0 | L27: =SUM(G27:K27)*L$9 -> 0 | M27: =SUM(G27:L27) -> 0 | N27: =M27*N$9 -> 0 | O27: =M27*O$9 -> 0 | P27: =M27*P$9 -> 0 | Q27: =SUM(N27:P27)*Q$9 -> 0 | R27: =SUM(M27:Q27) -> 0
... B61: =B60+1 -> 2058 | C61: =B61+1 -> 2059 | G61: =SUMIF(Wainwright_All_R_R_Th!$D$4:$BB$4,$B61,Wainwright_All_R_R_Th!$D$5:$BB$5) -> 0 | H61: =G61*$H$9 -> 0 | I61: =SUM(G61:H61)*I$9 -> 0 | J61: =SUM(G61:I61)*J$9 -> 0 | K61: =SUM(G61:J61)*K$9 -> 0 | L61: =SUM(G61:K61)*L$9 -> 0 | M61: =SUM(G61:L61) -> 0 | N61: =M61*N$9 -> 0 | O61: =M61*O$9 -> 0 | P61: =M61*P$9 -> 0 | Q61: =SUM(N61:P61)*Q$9 -> 0 | R61: =SUM(M61:Q61) -> 0
H62: =G62*$H$9 -> 0 | I62: =SUM(G62:H62)*I$9 -> 0 | J62: =SUM(G62:I62)*J$9 -> 0 | K62: =SUM(G62:J62)*K$9 -> 0 | L62: =SUM(G62:K62)*L$9 -> 0 | M62: =SUM(G62:L62) -> 0 | N62: =M62*N$9 -> 0 | O62: =M62*O$9 -> 0 | P62: =M62*P$9 -> 0 | Q62: =SUM(N62:P62)*Q$9 -> 0 | R62: =SUM(M62:Q62) -> 0 | T62: =SUM(N62:Q62)*$S$69 -> 0 | U62: =M62*$S$69 -> 0 | V62: =(K62+L62+Q62)*S$69 -> 0
A64: Summary Water Distribution | G64: =SUM(G11:G62) -> 12350 | H64: =SUM(H11:H62) -> 617.5 | I64: =SUM(I11:I62) -> 259.35 | J64: =SUM(J11:J62) -> 661.3425 | K64: =SUM(K11:K62) -> 1694.3595 | L64: =SUM(L11:L62) -> 1558.2552 | M64: =SUM(M11:M62) -> 17140.807 | N64: =SUM(N11:N62) -> 1319.8422 | ... R64: =SUM(R11:R62) -> 20101.025

Sheet CM Cost Estimating Worksheet
B1: Doyon Utilities, LLC
B2: Project Estimating Worksheet
B3: FTW 336A Aircraft Parts Storage RFP FWA-09-021
A5: Asset Type X= linear | B5: Item | C5: Year Inst | D5: Qty | F5: Unit Cost | G5: RCN | H5: Contractors Mark-ups % | M5: Contractors Mark-ups $ | R5: RCN (Total Installed) | S5: Engineering Services % | W5: Engineering Services $'s | AA5: RCN (Total w. Enginering) | AB5: Design Life | AC5: RCNLD | AD5: Historical Inflation Index | AE5: OC | AF5: OCLD | AG5: RYN (Repl Year New) | AH5: Source | AI5: Notes | AJ5: RDL Repl. Design Life | AK5: MMC Major Maintenance Cost | AL5: MMY Major Maintenance Start Year | AM5: MMD Major Maintenance Program Duration (yrs) | AN5: Comments | AO5: Condition Rating (Poor, Fair, Good) | AP5: Condition Rating Comments | AQ5: Condition Rating (Poor, Fair, Good)
B6: Provide EDS engineering costs for the FTW 336A Aircraft parts Storage Building. | H6: Contingency | I6: Bonds & Insurance | J6: General Conditions | K6: Contractors G&A | L6: Contractors Profit | M6: Contingency | N6: Bonds & Insurance | O6: General Conditions | P6: Contractors G&A | Q6: Contractors Profit | S6: Studies & Pre-Design | T6: Design | U6: Services During Construction(3%) & Commissioning (2%) | V6: Fee's on Studies & Design | W6: Studies & Pre-Design | X6: Design | Y6: Services During Construction | Z6: Fee's on Studies & Design
B7: EDS | H7: 0.05 | I7: 0.02 | J7: 0.05 | K7: 0.122 | L7: 0.1 | S7: 0.05 | T7: 0.05 | U7: 0.05 | V7: 0.1
B9: Engineering EDS Area Lights & HBO Feed | C9: 2009 | D9: 1 | E9: ea | F9: 3500 | G9: =IF(ISERROR(F9*D9)," ",F9*D9) -> 3500 | H9: =H$7 -> 0.05 | I9: =I$7 -> 0.02 | J9: =J$7 -> 0.05 | K9: =K$7 -> 0.122 | L9: =L$7 -> 0.1 | M9: =G9*H9 -> 175 | N9: =(G9+M9)*I9 -> 73.5 | O9: =(G9+M9+N9)*J9 -> 187.425 | P9: =(G9+M9+N9+O9)*K9 -> 480.18285 | Q9: =(G9+M9+N9+O9+P9)*L9 -> 441.61079 | R9: =G9+SUM(M9:Q9) -> 4857.7186 | S9: =S$7 -> 0.05 | T9: =T$7 -> 0.05 | U9: =U$7 -> 0.05 | V9: =V$7 -> 0.1 | W9: =R9*S9 -> 242.88593 | X9: =R9*T9 -> 242.88593 | Y9: =R9*U9 -> 242.88593 | Z9: =(W9+X9)*V9 -> 48.577186 | AA9: =R9+SUM(W9:Z9) -> 5634.9536 | AB9: 50 | AC9: =IF(ISERROR(IF('Wainwright Summary'!$E$7-C9>AB9,0,(AB9-('Wainwright Summary'!$E$7-C9))/AB9)*AA9)," ",(IF('Wainwright Summary'!$E$7-C9>AB9,0,(AB9-('Wainwright Summary'!$E$7-C9))/AB9)*AA9)) -> 5747.6527 | AD9: =VLOOKUP(C9,'Inflation-OLD'!$A$6:$B$126,2)/VLOOKUP('Wainwright Summary'!$E$6,'Inflation-OLD'!$A$6:$B$126,2) -> 1.0404 | AE9: 0 | AF9: =IF(ISERROR((AC9/AA9)*AE9)," ",(AC9/AA9)*AE9) -> 0 | AG9: 2009 | AJ9: =AB9 -> 50
B10: Engineering EDS Building Service | C10: 2009 | D10: 1 | E10: ea | F10: 8750 | G10: 8850 | H10: =H$7 -> 0.05 | I10: =I$7 -> 0.02 | J10: =J$7 -> 0.05 | K10: =K$7 -> 0.122 | L10: =L$7 -> 0.1 | M10: =G10*H10 -> 442.5 | N10: =(G10+M10)*I10 -> 185.85 | O10: =(G10+M10+N10)*J10 -> 473.9175 | P10: =(G10+M10+N10+O10)*K10 -> 1214.1766 | Q10: =(G10+M10+N10+O10+P10)*L10 -> 1116.6444 | R10: =G10+SUM(M10:Q10) -> 12283.089 | S10: =S$7 -> 0.05 | T10: =T$7 -> 0.05 | U10: =U$7 -> 0.05 | V10: =V$7 -> 0.1 | W10: =R10*S10 -> 614.15443 | X10: =R10*T10 -> 614.15443 | Y10: =R10*U10 -> 614.15443 | Z10: =(W10+X10)*V10 -> 122.83089 | AA10: =R10+SUM(W10:Z10) -> 14248.383 | AB10: 50 | AC10: =IF(ISERROR(IF('Wainwright Summary'!$E$7-C10>AB10,0,(AB10-('Wainwright Summary'!$E$7-C10))/AB10)*AA10)," ",(IF('Wainwright Summary'!$E$7-C10>AB10,0,(AB10-('Wainwright Summary'!$E$7-C10))/AB10)*AA10)) -> 14533.35 | AD10: =VLOOKUP(C10,'Inflation-OLD'!$A$6:$B$126,2)/VLOOKUP('Wainwright Summary'!$E$6,'Inflation-OLD'!$A$6:$B$126,2) -> 1.0404 | AE10: 0 | AF10: =IF(ISERROR((AC10/AA10)*AE10)," ",(AC10/AA10)*AE10) -> 0 | AG10: 2009 | AJ10: =AB10 -> 50
B12: Total Phase 1 Project Cost | G12: =SUM(G9:G10) -> 12350 | R12: =SUM(R9:R10) -> 17140.807 | X12: Total CPM & Commissioning | Y12: =SUM(Y9:Y10) -> 857.04036 | AA12: =SUM(AA9:AA10) -> 19883.336
A147: *

Sheet Wainwright Electrical Dist
B4: Doyon Utilities, LLC
B5: Fort Wainwright Utility Inventory and Replacement Cost
B6: Fort Wainwright Electrical Distribution System
B8: Item | C8: Year Inst | D8: Quantity | F8: Unit Cost | G8: RCN | H8: Contractors Mark-ups % | M8: Contractors Mark-ups $ | R8: RCN (Total Installed) | S8: Engineering Services % | W8: Engineering Services $'s | AA8: RCN (Total w. Enginering) | AB8: Design Life | AC8: RCNLD | AD8: Historical Inflation Index | AE8: OC | AF8: OCLD | AG8: RYN (Repl Year New) | AH8: Source | AI8: Notes | AJ8: RDL Repl. Design Life | AK8: MMC Major Maintenance Cost | AL8: MMY Major Maintenance Start Year | AM8: MMD Major Maintenance Program Duration (yrs) | AN8: Comments | AO8: Condition Rating (Poor, Fair, Good) | AP8: Condition Rating Comments | AQ8: Condition Rating (Poor, Fair, Good)
H9: Contingency | I9: Bonds & Insurance | J9: General Conditions | K9: Contractors G&A | L9: Contractors Profit | M9: Contingency | N9: Bonds & Insurance | O9: General Conditions | P9: Contractors G&A | Q9: Contractors Profit | S9: Studies & Pre-Design | T9: Design | U9: Services During Construction (3%) & Commissioning (2%) >$150,000 | V9: Fee's on Studies & Design | W9: Studies & Pre-Design | X9: Design | Y9: Services During Construction | Z9: Fee's on Studies & Design
H10: 0.05 | I10: 0.02 | J10: 0.05 | K10: 0.122 | L10: 0.1 | S10: 0.077 | T10: 0.05 | U10: 0.05 | V10: 0.1
G11: =IF(ISERROR(F11*D11)," ",F11*D11)
B12: DISTRIBUTION SYSTEM | G12: =IF(ISERROR(F12*D12)," ",F12*D12)
B13: CANTONMENT AREA (NON-HOUSING) | G13: =IF(ISERROR(F13*D13)," ",F13*D13) | AC13: =IF(ISERROR(IF('Wainwright Summary'!$E$7-C13>AB13,0,(AB13-('Wainwright Summary'!$E$7-C13))/AB13)*G13)," ",(IF('Wainwright Summary'!$E$7-C13>AB13,0,(AB13-('Wainwright Summary'!$E$7-C13))/AB13)*G13)) | AE13: =IF(ISERROR(D13*F13*AD13), " ",D13*F13*AD13 ) | AF13: =IF(ISERROR((AC13/G13)*AE13)," ",(AC13/G13)*AE13) | AG13: =IF(ISERROR(C13+AB13)," ",(C13+AB13))
B14: Overhead Lines _ Replace All Overhead Facilities -(ECU4) | G14: =IF(ISERROR(F14*D14)," ",F14*D14) | AC14: =IF(ISERROR(IF('Wainwright Summary'!$E$7-C14>AB14,0,(AB14-('Wainwright Summary'!$E$7-C14))/AB14)*G14)," ",(IF('Wainwright Summary'!$E$7-C14>AB14,0,(AB14-('Wainwright Summary'!$E$7-C14))/AB14)*G14)) | AE14: =IF(ISERROR(D14*F14*AD14), " ",D14*F14*AD14 ) | AF14: =IF(ISERROR((AC14/G14)*AE14)," ",(AC14/G14)*AE14) | AG14: =IF(ISERROR(C14+AB14)," ",(C14+AB14))
B15: 3 Ph. - Open Wire, Large | C15: 1982 | D15: 46728 | E15: lf | F15: 33 | G15: =IF(ISERROR(F15*D15)," ",F15*D15) -> 1542024 | H15: =H$10 -> 0.05 | I15: =I$10 -> 0.02 | J15: =J$10 -> 0.05 | K15: =K$10 -> 0.122 | L15: =L$10 -> 0.1 | M15: =G15*H15 -> 77101.2 | N15: =(G15+M15)*I15 -> 32382.504 | O15: =(G15+M15+N15)*J15 -> 82575.385 | P15: =(G15+M15+N15+O15)*K15 -> 211558.14 | Q15: =(G15+M15+N15+O15+P15)*L15 -> 194564.12 | R15: =G15+SUM(M15:Q15) -> 2140205.3 | S15: =S$10 -> 0.077 | T15: =T$10 -> 0.05 | U15: =U$10 -> 0.05 | V15: =V$10 -> 0.1 | W15: =R15*S15 -> 164795.81 | X15: =R15*T15 -> 107010.27 | Y15: =R15*U15 -> 107010.27 | Z15: =(W15+X15)*V15 -> 27180.608 | AA15: =R15+SUM(W15:Z15) -> 2546202.3 | AB15: 50 | AC15: =IF(ISERROR(IF('Wainwright Summary'!$E$7-C15>AB15,0,(AB15-('Wainwright Summary'!$E$7-C15))/AB15)*G15)," ",(IF('Wainwright Summary'!$E$7-C15>AB15,0,(AB15-('Wainwright Summary'!$E$7-C15))/AB15)*AA15)) -> 1222177.1 | AD15: =VLOOKUP(C15,'Inflation-OLD'!$A$6:$B$126,2)/VLOOKUP('Wainwright Summary'!$E$6,'Inflation-OLD'!$A$6:$B$126,2) -> 0.54223993 | AE15: =IF(ISERROR(AA15*AD15), " ",AA15*AD15 ) -> 1380652.6 | AF15: =IF(ISERROR((AC15/AA15)*AE15)," ",(AC15/AA15)*AE15) -> 662713.23 | AG15: =IF(ISERROR(C15+AB15)," ",(C15+AB15)) -> 2032 | AJ15: =AB15 -> 50
B16: 3 Ph. - Open Wire, Small (yr 1) | C16: 1966 | D16: =172086.16/2 -> 86043.08 | E16: lf | F16: =31*1.064 -> 32.984 | G16: =IF(ISERROR(F16*D16)," ",F16*D16) -> 2838045 | H16: =H$10 -> 0.05 | I16: =I$10 -> 0.02 | J16: =J$10 -> 0.05 | K16: =K$10 -> 0.122 | L16: =L$10 -> 0.1 | M16: =G16*H16 -> 141902.25 | N16: =(G16+M16)*I16 -> 59598.944 | O16: =(G16+M16+N16)*J16 -> 151977.31 | P16: =(G16+M16+N16+O16)*K16 -> 389365.86 | Q16: =(G16+M16+N16+O16+P16)*L16 -> 358088.93 | R16: =G16+SUM(M16:Q16) -> 3938978.2 | S16: =S$10 -> 0.077 | T16: =T$10 -> 0.05 | U16: =U$10 -> 0.05 | V16: =V$10 -> 0.1 | W16: =R16*S16 -> 303301.32 | X16: =R16*T16 -> 196948.91 | Y16: =R16*U16 -> 196948.91 | Z16: =(W16+X16)*V16 -> 50025.024 | AA16: =R16+SUM(W16:Z16) -> 4686202.4 | AB16: 35 | AC16: =IF(ISERROR(IF('Wainwright Summary'!$E$7-C16>AB16,0,(AB16-('Wainwright Summary'!$E$7-C16))/AB16)*G16)," ",(IF('Wainwright Summary'!$E$7-C16>AB16,0,(AB16-('Wainwright Summary'!$E$7-C16))/AB16)*AA16)) -> 0 | AD16: =VLOOKUP(C16,'Inflation-OLD'!$A$6:$B$126,2)/VLOOKUP('Wainwright Summary'!$E$6,'Inflation-OLD'!$A$6:$B$126,2) -> 0.2003394 | AE16: =IF(ISERROR(AA16*AD16), " ",AA16*AD16 ) -> 938831 | AF16: =IF(ISERROR((AC16/AA16)*AE16)," ",(AC16/AA16)*AE16) -> 0 | AG16: 2008 | AJ16: 50 | AN16: ECU4
B17: 3 Ph. - Open Wire, Small (yr 2) | C17: 1966 | D17: =172086.16/2 -> 86043.08 | E17: lf | F17: =31*1.064 -> 32.984 | G17: =IF(ISERROR(F17*D17)," ",F17*D17) -> 2838045 | H17: =H$10 -> 0.05 | I17: =I$10 -> 0.02 | J17: =J$10 -> 0.05 | K17: =K$10 -> 0.122 | L17: =L$10 -> 0.1 | M17: =G17*H17 -> 141902.25 | N17: =(G17+M17)*I17 -> 59598.944 | O17: =(G17+M17+N17)*J17 -> 151977.31 | P17: =(G17+M17+N17+O17)*K17 -> 389365.86 | Q17: =(G17+M17+N17+O17+P17)*L17 -> 358088.93 | R17: =G17+SUM(M17:Q17) -> 3938978.2 | S17: =S$10 -> 0.077 | T17: =T$10 -> 0.05 | U17: =U$10 -> 0.05 | V17: =V$10 -> 0.1 | W17: =R17*S17 -> 303301.32 | X17: =R17*T17 -> 196948.91 | Y17: =R17*U17 -> 196948.91 | Z17: =(W17+X17)*V17 -> 50025.024 | AA17: =R17+SUM(W17:Z17) -> 4686202.4 | AB17: 35 | AC17: =IF(ISERROR(IF('Wainwright Summary'!$E$7-C17>AB17,0,(AB17-('Wainwright Summary'!$E$7-C17))/AB17)*G17)," ",(IF('Wainwright Summary'!$E$7-C17>AB17,0,(AB17-('Wainwright Summary'!$E$7-C17))/AB17)*AA17)) -> 0 | AD17: =VLOOKUP(C17,'Inflation-OLD'!$A$6:$B$126,2)/VLOOKUP('Wainwright Summary'!$E$6,'Inflation-OLD'!$A$6:$B$126,2) -> 0.2003394 | AE17: =IF(ISERROR(AA17*AD17), " ",AA17*AD17 ) -> 938831 | AF17: =IF(ISERROR((AC17/AA17)*AE17)," ",(AC17/AA17)*AE17) -> 0 | AG17: 2009 | AJ17: 50 | AN17: ECU4
B18: 1 Ph. - Open Wire | C18: 1975 | D18: 18216 | E18: lf | F18: =26*1.064 -> 27.664 | G18: =IF(ISERROR(F18*D18)," ",F18*D18) -> 503927.42 | H18: =H$10 -> 0.05 | I18: =I$10 -> 0.02 | J18: =J$10 -> 0.05 | K18: =K$10 -> 0.122 | L18: =L$10 -> 0.1 | M18: =G18*H18 -> 25196.371 | N18: =(G18+M18)*I18 -> 10582.476 | O18: =(G18+M18+N18)*J18 -> 26985.314 | P18: =(G18+M18+N18+O18)*K18 -> 69136.373 | Q18: =(G18+M18+N18+O18+P18)*L18 -> 63582.796 | R18: =G18+SUM(M18:Q18) -> 699410.75 | S18: =S$10 -> 0.077 | T18: =T$10 -> 0.05 | U18: =U$10 -> 0.05 | V18: =V$10 -> 0.1 | W18: =R18*S18 -> 53854.628 | X18: =R18*T18 -> 34970.538 | Y18: =R18*U18 -> 34970.538 | Z18: =(W18+X18)*V18 -> 8882.5166 | AA18: =R18+SUM(W18:Z18) -> 832088.97 | AB18: 35 | AC18: =IF(ISERROR(IF('Wainwright Summary'!$E$7-C18>AB18,0,(AB18-('Wainwright Summary'!$E$7-C18))/AB18)*G18)," ",(IF('Wainwright Summary'!$E$7-C18>AB18,0,(AB18-('Wainwright Summary'!$E$7-C18))/AB18)*AA18)) -> 47547.941 | AD18: =VLOOKUP(C18,'Inflation-OLD'!$A$6:$B$126,2)/VLOOKUP('Wainwright Summary'!$E$6,'Inflation-OLD'!$A$6:$B$126,2) -> 0.3204444 | AE18: =IF(ISERROR(AA18*AD18), " ",AA18*AD18 ) -> 266638.25 | AF18: =IF(ISERROR((AC18/AA18)*AE18)," ",(AC18/AA18)*AE18) -> 15236.471 | AG18: 2008 | AJ18: 50 | AN18: ECU4
B19: Gang Operated Air Break Switch | C19: 1985 | D19: 40 | E19: ea | F19: 1000 | G19: =IF(ISERROR(F19*D19)," ",F19*D19) -> 40000 | H19: =H$10 -> 0.05 | I19: =I$10 -> 0.02 | J19: =J$10 -> 0.05 | K19: =K$10 -> 0.122 | L19: =L$10 -> 0.1 | M19: =G19*H19 -> 2000 | N19: =(G19+M19)*I19 -> 840 | O19: =(G19+M19+N19)*J19 -> 2142 | P19: =(G19+M19+N19+O19)*K19 -> 5487.804 | Q19: =(G19+M19+N19+O19+P19)*L19 -> 5046.9804 | R19: =G19+SUM(M19:Q19) -> 55516.784 | S19: =S$10 -> 0.077 | T19: =T$10 -> 0.05 | U19: 0.03 | V19: =V$10 -> 0.1 | W19: =R19*S19 -> 4274.7924 | X19: =R19*T19 -> 2775.8392 | Y19: =R19*U19 -> 1665.5035 | Z19: =(W19+X19)*V19 -> 705.06316 | AA19: =R19+SUM(W19:Z19) -> 64937.983 | AB19: 35 | AC19: =IF(ISERROR(IF('Wainwright Summary'!$E$7-C19>AB19,0,(AB19-('Wainwright Summary'!$E$7-C19))/AB19)*G19)," ",(IF('Wainwright Summary'!$E$7-C19>AB19,0,(AB19-('Wainwright Summary'!$E$7-C19))/AB19)*AA19)) -> 22264.451 | AD19: =VLOOKUP(C19,'Inflation-OLD'!$A$6:$B$126,2)/VLOOKUP('Wainwright Summary'!$E$6,'Inflation-OLD'!$A$6:$B$126,2) -> 0.60685494 | AE19: =IF(ISERROR(AA19*AD19), " ",AA19*AD19 ) -> 39407.936 | AF19: =IF(ISERROR((AC19/AA19)*AE19)," ",(AC19/AA19)*AE19) -> 13511.292 | AG19: 2008 | AJ19: 50 | AN19: ECU4
B20: Secondary | C20: 1979 | D20: 61300.8 | E20: lf | F20: =16*1.064 -> 17.024 | G20: =IF(ISERROR(F20*D20)," ",F20*D20) -> 1043584.8 | H20: =H$10 -> 0.05 | I20: =I$10 -> 0.02 | J20: =J$10 -> 0.05 | K20: =K$10 -> 0.122 | L20: =L$10 -> 0.1 | M20: =G20*H20 -> 52179.241 | N20: =(G20+M20)*I20 -> 21915.281 | O20: =(G20+M20+N20)*J20 -> 55883.967 | P20: =(G20+M20+N20+O20)*K20 -> 143174.72 | Q20: =(G20+M20+N20+O20+P20)*L20 -> 131673.8 | R20: =G20+SUM(M20:Q20) -> 1448411.8 | S20: =S$10 -> 0.077 | T20: =T$10 -> 0.05 | U20: =U$10 -> 0.05 | V20: =V$10 -> 0.1 | W20: =R20*S20 -> 111527.71 | X20: =R20*T20 -> 72420.592 | Y20: =R20*U20 -> 72420.592 | Z20: =(W20+X20)*V20 -> 18394.83 | AA20: =R20+SUM(W20:Z20) -> 1723175.6 | AB20: 35 | AC20: =IF(ISERROR(IF('Wainwright Summary'!$E$7-C20>AB20,0,(AB20-('Wainwright Summary'!$E$7-C20))/AB20)*G20)," ",(IF('Wainwright Summary'!$E$7-C20>AB20,0,(AB20-('Wainwright Summary'!$E$7-C20))/AB20)*AA20)) -> 295401.52 | AD20: =VLOOKUP(C20,'Inflation-OLD'!$A$6:$B$126,2)/VLOOKUP('Wainwright Summary'!$E$6,'Inflation-OLD'!$A$6:$B$126,2) -> 0.42632751 | AE20: =IF(ISERROR(AA20*AD20), " ",AA20*AD20 ) -> 734637.15 | AF20: =IF(ISERROR((AC20/AA20)*AE20)," ",(AC20/AA20)*AE20) -> 125937.8 | AG20: 2008 | AJ20: 50 | AN20: ECU4
G21: =IF(ISERROR(F21*D21)," ",F21*D21) | AC21: =IF(ISERROR(IF('Wainwright Summary'!$E$7-C21>AB21,0,(AB21-('Wainwright Summary'!$E$7-C21))/AB21)*G21)," ",(IF('Wainwright Summary'!$E$7-C21>AB21,0,(AB21-('Wainwright Summary'!$E$7-C21))/AB21)*G21)) | AE21: =IF(ISERROR(D21*F21*AD21), " ",D21*F21*AD21 ) | AF21: =IF(ISERROR((AC21/G21)*AE21)," ",(AC21/G21)*AE21) | AG21: =IF(ISERROR(C21+AB21)," ",(C21+AB21)) | AJ21: =AB21
B22: Underground Lines | G22: =IF(ISERROR(F22*D22)," ",F22*D22) | AC22: =IF(ISERROR(IF('Wainwright Summary'!$E$7-C22>AB22,0,(AB22-('Wainwright Summary'!$E$7-C22))/AB22)*G22)," ",(IF('Wainwright Summary'!$E$7-C22>AB22,0,(AB22-('Wainwright Summary'!$E$7-C22))/AB22)*G22)) | AE22: =IF(ISERROR(D22*F22*AD22), " ",D22*F22*AD22 ) | AF22: =IF(ISERROR((AC22/G22)*AE22)," ",(AC22/G22)*AE22) | AG22: =IF(ISERROR(C22+AB22)," ",(C22+AB22)) | AJ22: =AB22
B23: 3 Ph. - Large | C23: 1990 | D23: 1056 | E23: lf | F23: 39 | G23: =IF(ISERROR(F23*D23)," ",F23*D23) -> 41184 | H23: =H$10 -> 0.05 | I23: =I$10 -> 0.02 | J23: =J$10 -> 0.05 | K23: =K$10 -> 0.122 | L23: =L$10 -> 0.1 | M23: =G23*H23 -> 2059.2 | N23: =(G23+M23)*I23 -> 864.864 | O23: =(G23+M23+N23)*J23 -> 2205.4032 | P23: =(G23+M23+N23+O23)*K23 -> 5650.243 | Q23: =(G23+M23+N23+O23+P23)*L23 -> 5196.371 | R23: =G23+SUM(M23:Q23) -> 57160.081 | S23: =S$10 -> 0.077 | T23: =T$10 -> 0.05 | U23: 0.03 | V23: =V$10 -> 0.1 | W23: =R23*S23 -> 4401.3263 | X23: =R23*T23 -> 2858.0041 | Y23: =R23*U23 -> 1714.8024 | Z23: =(W23+X23)*V23 -> 725.93303 | AA23: =R23+SUM(W23:Z23) -> 66860.147 | AB23: 40 | AC23: =IF(ISERROR(IF('Wainwright Summary'!$E$7-C23>AB23,0,(AB23-('Wainwright Summary'!$E$7-C23))/AB23)*G23)," ",(IF('Wainwright Summary'!$E$7-C23>AB23,0,(AB23-('Wainwright Summary'!$E$7-C23))/AB23)*AA23)) -> 36773.081 | AD23: =VLOOKUP(C23,'Inflation-OLD'!$A$6:$B$126,2)/VLOOKUP('Wainwright Summary'!$E$6,'Inflation-OLD'!$A$6:$B$126,2) -> 0.70977859 | AE23: =IF(ISERROR(AA23*AD23), " ",AA23*AD23 ) -> 47455.901 | AF23: =IF(ISERROR((AC23/AA23)*AE23)," ",(AC23/AA23)*AE23) -> 26100.745 | AG23: =IF(ISERROR(C23+AB23)," ",(C23+AB23)) -> 2030 | AJ23: =AB23 -> 40
B24: 3 Ph. - Small | C24: 1973 | D24: 14308.8 | E24: lf | F24: 33 | G24: =IF(ISERROR(F24*D24)," ",F24*D24) -> 472190.4 | H24: =H$10 -> 0.05 | I24: =I$10 -> 0.02 | J24: =J$10 -> 0.05 | K24: =K$10 -> 0.122 | L24: =L$10 -> 0.1 | M24: =G24*H24 -> 23609.52 | N24: =(G24+M24)*I24 -> 9915.9984 | O24: =(G24+M24+N24)*J24 -> 25285.796 | P24: =(G24+M24+N24+O24)*K24 -> 64782.209 | Q24: =(G24+M24+N24+O24+P24)*L24 -> 59578.392 | R24: =G24+SUM(M24:Q24) -> 655362.32 | S24: =S$10 -> 0.077 | T24: =T$10 -> 0.05 | U24: =U$10 -> 0.05 | V24: =V$10 -> 0.1 | W24: =R24*S24 -> 50462.898 | X24: =R24*T24 -> 32768.116 | Y24: =R24*U24 -> 32768.116 | Z24: =(W24+X24)*V24 -> 8323.1014 | AA24: =R24+SUM(W24:Z24) -> 779684.55 | AB24: 40 | AC24: =IF(ISERROR(IF('Wainwright Summary'!$E$7-C24>AB24,0,(AB24-('Wainwright Summary'!$E$7-C24))/AB24)*G24)," ",(IF('Wainwright Summary'!$E$7-C24>AB24,0,(AB24-('Wainwright Summary'!$E$7-C24))/AB24)*AA24)) -> 97460.568 | AD24: =VLOOKUP(C24,'Inflation-OLD'!$A$6:$B$126,2)/VLOOKUP('Wainwright Summary'!$E$6,'Inflation-OLD'!$A$6:$B$126,2) -> 0.27210645 | AE24: =IF(ISERROR(AA24*AD24), " ",AA24*AD24 ) -> 212157.2 | AF24: =IF(ISERROR((AC24/AA24)*AE24)," ",(AC24/AA24)*AE24) -> 26519.65 | AG24: =IF(ISERROR(C24+AB24)," ",(C24+AB24)) -> 2013 | AJ24: =AB24 -> 40
B25: 1 Ph. Direct Buried | C25: 1973 | D25: 2164.8 | E25: lf | F25: 17 | G25: =IF(ISERROR(F25*D25)," ",F25*D25) -> 36801.6 | H25: =H$10 -> 0.05 | I25: =I$10 -> 0.02 | J25: =J$10 -> 0.05 | K25: =K$10 -> 0.122 | L25: =L$10 -> 0.1 | M25: =G25*H25 -> 1840.08 | N25: =(G25+M25)*I25 -> 772.8336 | O25: =(G25+M25+N25)*J25 -> 1970.7257 | P25: =(G25+M25+N25+O25)*K25 -> 5048.9992 | Q25: =(G25+M25+N25+O25+P25)*L25 -> 4643.4238 | R25: =G25+SUM(M25:Q25) -> 51077.662 | S25: =S$10 -> 0.077 | T25: =T$10 -> 0.05 | U25: 0.03 | V25: =V$10 -> 0.1 | W25: =R25*S25 -> 3932.98 | X25: =R25*T25 -> 2553.8831 | Y25: =R25*U25 -> 1532.3299 | Z25: =(W25+X25)*V25 -> 648.68631 | AA25: =R25+SUM(W25:Z25) -> 59745.542 | AB25: 40 | AC25: =IF(ISERROR(IF('Wainwright Summary'!$E$7-C25>AB25,0,(AB25-('Wainwright Summary'!$E$7-C25))/AB25)*G25)," ",(IF('Wainwright Summary'!$E$7-C25>AB25,0,(AB25-('Wainwright Summary'!$E$7-C25))/AB25)*AA25)) -> 7468.1927 | AD25: =VLOOKUP(C25,'Inflation-OLD'!$A$6:$B$126,2)/VLOOKUP('Wainwright Summary'!$E$6,'Inflation-OLD'!$A$6:$B$126,2) -> 0.27210645 | AE25: =IF(ISERROR(AA25*AD25), " ",AA25*AD25 ) -> 16257.148 | AF25: =IF(ISERROR((AC25/AA25)*AE25)," ",(AC25/AA25)*AE25) -> 2032.1434 | AG25: =IF(ISERROR(C25+AB25)," ",(C25+AB25)) -> 2013 | AJ25: =AB25 -> 40
B26: Duct | C26: 1973 | D26: 2164.8 | E26: lf | F26: 50 | G26: =IF(ISERROR(F26*D26)," ",F26*D26) -> 108240 | H26: =H$10 -> 0.05 | I26: =I$10 -> 0.02 | J26: =J$10 -> 0.05 | K26: =K$10 -> 0.122 | L26: =L$10 -> 0.1 | M26: =G26*H26 -> 5412 | N26: =(G26+M26)*I26 -> 2273.04 | O26: =(G26+M26+N26)*J26 -> 5796.252 | P26: =(G26+M26+N26+O26)*K26 -> 14849.998 | Q26: =(G26+M26+N26+O26+P26)*L26 -> 13657.129 | R26: =G26+SUM(M26:Q26) -> 150228.42 | S26: =S$10 -> 0.077 | T26: =T$10 -> 0.05 | U26: 0.05 | V26: =V$10 -> 0.1 | W26: =R26*S26 -> 11567.588 | X26: =R26*T26 -> 7511.4209 | Y26: =R26*U26 -> 7511.4209 | Z26: =(W26+X26)*V26 -> 1907.9009 | AA26: =R26+SUM(W26:Z26) -> 178726.75 | AB26: 85 | AC26: =IF(ISERROR(IF('Wainwright Summary'!$E$7-C26>AB26,0,(AB26-('Wainwright Summary'!$E$7-C26))/AB26)*G26)," ",(IF('Wainwright Summary'!$E$7-C26>AB26,0,(AB26-('Wainwright Summary'!$E$7-C26))/AB26)*AA26)) -> 105133.38 | AD26: =VLOOKUP(C26,'Inflation-OLD'!$A$6:$B$126,2)/VLOOKUP('Wainwright Summary'!$E$6,'Inflation-OLD'!$A$6:$B$126,2) -> 0.27210645 | AE26: =IF(ISERROR(AA26*AD26), " ",AA26*AD26 ) -> 48632.702 | AF26: =IF(ISERROR((AC26/AA26)*AE26)," ",(AC26/AA26)*AE26) -> 28607.472 | AG26: =IF(ISERROR(C26+AB26)," ",(C26+AB26)) -> 2058 | AJ26: =AB26 -> 85
B27: Pad Mtd. Sectionalizing Switch (ERR2) | C27: 1970 | D27: 1 | E27: ea | F27: 40000 | G27: =IF(ISERROR(F27*D27)," ",F27*D27) -> 40000 | H27: =H$10 -> 0.05 | I27: =I$10 -> 0.02 | J27: =J$10 -> 0.05 | K27: =K$10 -> 0.122 | L27: =L$10 -> 0.1 | M27: =G27*H27 -> 2000 | N27: =(G27+M27)*I27 -> 840 | O27: =(G27+M27+N27)*J27 -> 2142 | P27: =(G27+M27+N27+O27)*K27 -> 5487.804 | Q27: =(G27+M27+N27+O27+P27)*L27 -> 5046.9804 | R27: =G27+SUM(M27:Q27) -> 55516.784 | S27: =S$10 -> 0.077 | T27: =T$10 -> 0.05 | U27: 0.03 | V27: =V$10 -> 0.1 | W27: =R27*S27 -> 4274.7924 | X27: =R27*T27 -> 2775.8392 | Y27: =R27*U27 -> 1665.5035 | Z27: =(W27+X27)*V27 -> 705.06316 | AA27: =R27+SUM(W27:Z27) -> 64937.983 | AB27: 40 | AC27: =IF(ISERROR(IF('Wainwright Summary'!$E$7-C27>AB27,0,(AB27-('Wainwright Summary'!$E$7-C27))/AB27)*G27)," ",(IF('Wainwright Summary'!$E$7-C27>AB27,0,(AB27-('Wainwright Summary'!$E$7-C27))/AB27)*AA27)) -> 3246.8991 | AD27: =VLOOKUP(C27,'Inflation-OLD'!$A$6:$B$126,2)/VLOOKUP('Wainwright Summary'!$E$6,'Inflation-OLD'!$A$6:$B$126,2) -> 0.2359352 | AE27: =IF(ISERROR(AA27*AD27), " ",AA27*AD27 ) -> 15321.156 | AF27: =IF(ISERROR((AC27/AA27)*AE27)," ",(AC27/AA27)*AE27) -> 766.05781 | AG27: =IF(ISERROR(C27+AB27)," ",(C27+AB27)) -> 2010 | AJ27: =AB27 -> 40 | AN27: In Initial R&R.
B28: Secondary | C28: 1981 | D28: 5068.8 | E28: lf | F28: 19 | G28: =IF(ISERROR(F28*D28)," ",F28*D28) -> 96307.2 | H28: =H$10 -> 0.05 | I28: =I$10 -> 0.02 | J28: =J$10 -> 0.05 | K28: =K$10 -> 0.122 | L28: =L$10 -> 0.1 | M28: =G28*H28 -> 4815.36 | N28: =(G28+M28)*I28 -> 2022.4512 | O28: =(G28+M28+N28)*J28 -> 5157.2506 | P28: =(G28+M28+N28+O28)*K28 -> 13212.876 | Q28: =(G28+M28+N28+O28+P28)*L28 -> 12151.514 | R28: =G28+SUM(M28:Q28) -> 133666.65 | S28: =S$10 -> 0.077 | T28: =T$10 -> 0.05 | U28: =U$10 -> 0.05 | V28: =V$10 -> 0.1 | W28: =R28*S28 -> 10292.332 | X28: =R28*T28 -> 6683.3326 | Y28: =R28*U28 -> 6683.3326 | Z28: =(W28+X28)*V28 -> 1697.5665 | AA28: =R28+SUM(W28:Z28) -> 159023.22 | AB28: 40 | AC28: =IF(ISERROR(IF('Wainwright Summary'!$E$7-C28>AB28,0,(AB28-('Wainwright Summary'!$E$7-C28))/AB28)*G28)," ",(IF('Wainwright Summary'!$E$7-C28>AB28,0,(AB28-('Wainwright Summary'!$E$7-C28))/AB28)*AA28)) -> 51682.545 | AD28: =VLOOKUP(C28,'Inflation-OLD'!$A$6:$B$126,2)/VLOOKUP('Wainwright Summary'!$E$6,'Inflation-OLD'!$A$6:$B$126,2) -> 0.50754841 | AE28: =IF(ISERROR(AA28*AD28), " ",AA28*AD28 ) -> 80711.981 | AF28: =IF(ISERROR((AC28/AA28)*AE28)," ",(AC28/AA28)*AE28) -> 26231.394 | AG28: =IF(ISERROR(C28+AB28)," ",(C28+AB28)) -> 2021 | AJ28: =AB28 -> 40
G29: =IF(ISERROR(F29*D29)," ",F29*D29) | AC29: =IF(ISERROR(IF('Wainwright Summary'!$E$7-C29>AB29,0,(AB29-('Wainwright Summary'!$E$7-C29))/AB29)*G29)," ",(IF('Wainwright Summary'!$E$7-C29>AB29,0,(AB29-('Wainwright Summary'!$E$7-C29))/AB29)*AA29)) | AE29: =IF(ISERROR(D29*F29*AD29), " ",D29*F29*AD29 ) | AF29: =IF(ISERROR((AC29/AA29)*AE29)," ",(AC29/AA29)*AE29) | AG29: =IF(ISERROR(C29+AB29)," ",(C29+AB29)) | AJ29: =AB29
B30: Transformers: Pole Type | G30: =IF(ISERROR(F30*D30)," ",F30*D30) | AC30: =IF(ISERROR(IF('Wainwright Summary'!$E$7-C30>AB30,0,(AB30-('Wainwright Summary'!$E$7-C30))/AB30)*G30)," ",(IF('Wainwright Summary'!$E$7-C30>AB30,0,(AB30-('Wainwright Summary'!$E$7-C30))/AB30)*AA30)) | AE30: =IF(ISERROR(D30*F30*AD30), " ",D30*F30*AD30 ) | AF30: =IF(ISERROR((AC30/AA30)*AE30)," ",(AC30/AA30)*AE30) | AG30: =IF(ISERROR(C30+AB30)," ",(C30+AB30)) | AJ30: =AB30
B31: 15 kVA & Smaller | C31: 1978 | D31: 176 | E31: ea | F31: 3200 | G31: =IF(ISERROR(F31*D31)," ",F31*D31) -> 563200 | H31: =H$10 -> 0.05 | I31: =I$10 -> 0.02 | J31: =J$10 -> 0.05 | K31: =K$10 -> 0.122 | L31: =L$10 -> 0.1 | M31: =G31*H31 -> 28160 | N31: =(G31+M31)*I31 -> 11827.2 | O31: =(G31+M31+N31)*J31 -> 30159.36 | P31: =(G31+M31+N31+O31)*K31 -> 77268.28 | Q31: =(G31+M31+N31+O31+P31)*L31 -> 71061.484 | R31: =G31+SUM(M31:Q31) -> 781676.32 | S31: =S$10 -> 0.077 | T31: =T$10 -> 0.05 | U31: =U$10 -> 0.05 | V31: =V$10 -> 0.1 | W31: =R31*S31 -> 60189.077 | X31: =R31*T31 -> 39083.816 | Y31: =R31*U31 -> 39083.816 | Z31: =(W31+X31)*V31 -> 9927.2893 | AA31: =R31+SUM(W31:Z31) -> 929960.32 | AB31: 40 | AC31: =IF(ISERROR(IF('Wainwright Summary'!$E$7-C31>AB31,0,(AB31-('Wainwright Summary'!$E$7-C31))/AB31)*G31)," ",(IF('Wainwright Summary'!$E$7-C31>AB31,0,(AB31-('Wainwright Summary'!$E$7-C31))/AB31)*AA31)) -> 232490.08 | AD31: =VLOOKUP(C31,'Inflation-OLD'!$A$6:$B$126,2)/VLOOKUP('Wainwright Summary'!$E$6,'Inflation-OLD'!$A$6:$B$126,2) -> 0.39549974 | AE31: =IF(ISERROR(AA31*AD31), " ",AA31*AD31 ) -> 367799.07 | AF31: =IF(ISERROR((AC31/AA31)*AE31)," ",(AC31/AA31)*AE31) -> 91949.767 | AG31: =IF(ISERROR(C31+AB31)," ",(C31+AB31)) -> 2018 | AJ31: =AB31 -> 40
B32: 25 kVA | C32: 1980 | D32: 191 | E32: ea | F32: 3700 | G32: =IF(ISERROR(F32*D32)," ",F32*D32) -> 706700 | H32: =H$10 -> 0.05 | I32: =I$10 -> 0.02 | J32: =J$10 -> 0.05 | K32: =K$10 -> 0.122 | L32: =L$10 -> 0.1 | M32: =G32*H32 -> 35335 | N32: =(G32+M32)*I32 -> 14840.7 | O32: =(G32+M32+N32)*J32 -> 37843.785 | P32: =(G32+M32+N32+O32)*K32 -> 96955.777 | Q32: =(G32+M32+N32+O32+P32)*L32 -> 89167.526 | R32: =G32+SUM(M32:Q32) -> 980842.79 | S32: =S$10 -> 0.077 | T32: =T$10 -> 0.05 | U32: =U$10 -> 0.05 | V32: =V$10 -> 0.1 | W32: =R32*S32 -> 75524.895 | X32: =R32*T32 -> 49042.139 | Y32: =R32*U32 -> 49042.139 | Z32: =(W32+X32)*V32 -> 12456.703 | AA32: =R32+SUM(W32:Z32) -> 1166908.7 | AB32: 40 | AC32: =IF(ISERROR(IF('Wainwright Summary'!$E$7-C32>AB32,0,(AB32-('Wainwright Summary'!$E$7-C32))/AB32)*G32)," ",(IF('Wainwright Summary'!$E$7-C32>AB32,0,(AB32-('Wainwright Summary'!$E$7-C32))/AB32)*AA32)) -> 350072.6 | AD32: =VLOOKUP(C32,'Inflation-OLD'!$A$6:$B$126,2)/VLOOKUP('Wainwright Summary'!$E$6,'Inflation-OLD'!$A$6:$B$126,2) -> 0.46299201 | AE32: =IF(ISERROR(AA32*AD32), " ",AA32*AD32 ) -> 540269.39 | AF32: =IF(ISERROR((AC32/AA32)*AE32)," ",(AC32/AA32)*AE32) -> 162080.82 | AG32: =IF(ISERROR(C32+AB32)," ",(C32+AB32)) -> 2020 | AJ32: =AB32 -> 40
B33: 37.5 kVA | C33: 1978 | D33: 82 | E33: ea | F33: 4500 | G33: =IF(ISERROR(F33*D33)," ",F33*D33) -> 369000 | H33: =H$10 -> 0.05 | I33: =I$10 -> 0.02 | J33: =J$10 -> 0.05 | K33: =K$10 -> 0.122 | L33: =L$10 -> 0.1 | M33: =G33*H33 -> 18450 | N33: =(G33+M33)*I33 -> 7749 | O33: =(G33+M33+N33)*J33 -> 19759.95 | P33: =(G33+M33+N33+O33)*K33 -> 50624.992 | Q33: =(G33+M33+N33+O33+P33)*L33 -> 46558.394 | R33: =G33+SUM(M33:Q33) -> 512142.34 | S33: =S$10 -> 0.077 | T33: =T$10 -> 0.05 | U33: =U$10 -> 0.05 | V33: =V$10 -> 0.1 | W33: =R33*S33 -> 39434.96 | X33: =R33*T33 -> 25607.117 | Y33: =R33*U33 -> 25607.117 | Z33: =(W33+X33)*V33 -> 6504.2077 | AA33: =R33+SUM(W33:Z33) -> 609295.74 | AB33: 40 | AC33: =IF(ISERROR(IF('Wainwright Summary'!$E$7-C33>AB33,0,(AB33-('Wainwright Summary'!$E$7-C33))/AB33)*G33)," ",(IF('Wainwright Summary'!$E$7-C33>AB33,0,(AB33-('Wainwright Summary'!$E$7-C33))/AB33)*AA33)) -> 152323.93 | AD33: =VLOOKUP(C33,'Inflation-OLD'!$A$6:$B$126,2)/VLOOKUP('Wainwright Summary'!$E$6,'Inflation-OLD'!$A$6:$B$126,2) -> 0.39549974 | AE33: =IF(ISERROR(AA33*AD33), " ",AA33*AD33 ) -> 240976.31 | AF33: =IF(ISERROR((AC33/AA33)*AE33)," ",(AC33/AA33)*AE33) -> 60244.077 | AG33: =IF(ISERROR(C33+AB33)," ",(C33+AB33)) -> 2018 | AJ33: =AB33 -> 40
B34: 50 kVA | C34: 1979 | D34: 118 | E34: ea | F34: 5800 | G34: =IF(ISERROR(F34*D34)," ",F34*D34) -> 684400 | H34: =H$10 -> 0.05 | I34: =I$10 -> 0.02 | J34: =J$10 -> 0.05 | K34: =K$10 -> 0.122 | L34: =L$10 -> 0.1 | M34: =G34*H34 -> 34220 | N34: =(G34+M34)*I34 -> 14372.4 | O34: =(G34+M34+N34)*J34 -> 36649.62 | P34: =(G34+M34+N34+O34)*K34 -> 93896.326 | Q34: =(G34+M34+N34+O34+P34)*L34 -> 86353.835 | R34: =G34+SUM(M34:Q34) -> 949892.18 | S34: =S$10 -> 0.077 | T34: =T$10 -> 0.05 | U34: =U$10 -> 0.05 | V34: =V$10 -> 0.1 | W34: =R34*S34 -> 73141.698 | X34: =R34*T34 -> 47494.609 | Y34: =R34*U34 -> 47494.609 | Z34: =(W34+X34)*V34 -> 12063.631 | AA34: =R34+SUM(W34:Z34) -> 1130086.7 | AB34: 40 | AC34: =IF(ISERROR(IF('Wainwright Summary'!$E$7-C34>AB34,0,(AB34-('Wainwright Summary'!$E$7-C34))/AB34)*G34)," ",(IF('Wainwright Summary'!$E$7-C34>AB34,0,(AB34-('Wainwright Summary'!$E$7-C34))/AB34)*AA34)) -> 310773.85 | AD34: =VLOOKUP(C34,'Inflation-OLD'!$A$6:$B$126,2)/VLOOKUP('Wainwright Summary'!$E$6,'Inflation-OLD'!$A$6:$B$126,2) -> 0.42632751 | AE34: =IF(ISERROR(AA34*AD34), " ",AA34*AD34 ) -> 481787.07 | AF34: =IF(ISERROR((AC34/AA34)*AE34)," ",(AC34/AA34)*AE34) -> 132491.44 | AG34: =IF(ISERROR(C34+AB34)," ",(C34+AB34)) -> 2019 | AJ34: =AB34 -> 40
B35: 75 kVA | C35: 1979 | D35: 64 | E35: ea | F35: 9500 | G35: =IF(ISERROR(F35*D35)," ",F35*D35) -> 608000 | H35: =H$10 -> 0.05 | I35: =I$10 -> 0.02 | J35: =J$10 -> 0.05 | K35: =K$10 -> 0.122 | L35: =L$10 -> 0.1 | M35: =G35*H35 -> 30400 | N35: =(G35+M35)*I35 -> 12768 | O35: =(G35+M35+N35)*J35 -> 32558.4 | P35: =(G35+M35+N35+O35)*K35 -> 83414.621 | Q35: =(G35+M35+N35+O35+P35)*L35 -> 76714.102 | R35: =G35+SUM(M35:Q35) -> 843855.12 | S35: =S$10 -> 0.077 | T35: =T$10 -> 0.05 | U35: =U$10 -> 0.05 | V35: =V$10 -> 0.1 | W35: =R35*S35 -> 64976.844 | X35: =R35*T35 -> 42192.756 | Y35: =R35*U35 -> 42192.756 | Z35: =(W35+X35)*V35 -> 10716.96 | AA35: =R35+SUM(W35:Z35) -> 1003934.4 | AB35: 40 | AC35: =IF(ISERROR(IF('Wainwright Summary'!$E$7-C35>AB35,0,(AB35-('Wainwright Summary'!$E$7-C35))/AB35)*G35)," ",(IF('Wainwright Summary'!$E$7-C35>AB35,0,(AB35-('Wainwright Summary'!$E$7-C35))/AB35)*AA35)) -> 276081.97 | AD35: =VLOOKUP(C35,'Inflation-OLD'!$A$6:$B$126,2)/VLOOKUP('Wainwright Summary'!$E$6,'Inflation-OLD'!$A$6:$B$126,2) -> 0.42632751 | AE35: =IF(ISERROR(AA35*AD35), " ",AA35*AD35 ) -> 428004.87 | AF35: =IF(ISERROR((AC35/AA35)*AE35)," ",(AC35/AA35)*AE35) -> 117701.34 | AG35: =IF(ISERROR(C35+AB35)," ",(C35+AB35)) -> 2019 | AJ35: =AB35 -> 40
B36: 100 kVA - replace transformers (ERR1) | C36: 1977 | D36: 42 | E36: ea | F36: 9500 | G36: =IF(ISERROR(F36*D36)," ",F36*D36) -> 399000 | H36: =H$10 -> 0.05 | I36: =I$10 -> 0.02 | J36: =J$10 -> 0.05 | K36: =K$10 -> 0.122 | L36: =L$10 -> 0.1 | M36: =G36*H36 -> 19950 | N36: =(G36+M36)*I36 -> 8379 | O36: =(G36+M36+N36)*J36 -> 21366.45 | P36: =(G36+M36+N36+O36)*K36 -> 54740.845 | Q36: =(G36+M36+N36+O36+P36)*L36 -> 50343.629 | R36: =G36+SUM(M36:Q36) -> 553779.92 | S36: =S$10 -> 0.077 | T36: =T$10 -> 0.05 | U36: =U$10 -> 0.05 | V36: =V$10 -> 0.1 | W36: =R36*S36 -> 42641.054 | X36: =R36*T36 -> 27688.996 | Y36: =R36*U36 -> 27688.996 | Z36: =(W36+X36)*V36 -> 7033.005 | AA36: =R36+SUM(W36:Z36) -> 658831.98 | AB36: 40 | AC36: =IF(ISERROR(IF('Wainwright Summary'!$E$7-C36>AB36,0,(AB36-('Wainwright Summary'!$E$7-C36))/AB36)*G36)," ",(IF('Wainwright Summary'!$E$7-C36>AB36,0,(AB36-('Wainwright Summary'!$E$7-C36))/AB36)*AA36)) -> 148237.19 | AD36: =VLOOKUP(C36,'Inflation-OLD'!$A$6:$B$126,2)/VLOOKUP('Wainwright Summary'!$E$6,'Inflation-OLD'!$A$6:$B$126,2) -> 0.37034428 | AE36: =IF(ISERROR(AA36*AD36), " ",AA36*AD36 ) -> 243994.66 | AF36: =IF(ISERROR((AC36/AA36)*AE36)," ",(AC36/AA36)*AE36) -> 54898.798 | AG36: 2010 | AJ36: =AB36 -> 40 | AN36: Initial R & R, ERR1
G37: =IF(ISERROR(F37*D37)," ",F37*D37) | AC37: =IF(ISERROR(IF('Wainwright Summary'!$E$7-C37>AB37,0,(AB37-('Wainwright Summary'!$E$7-C37))/AB37)*G37)," ",(IF('Wainwright Summary'!$E$7-C37>AB37,0,(AB37-('Wainwright Summary'!$E$7-C37))/AB37)*AA37)) | AE37: =IF(ISERROR(D37*F37*AD37), " ",D37*F37*AD37 ) | AF37: =IF(ISERROR((AC37/AA37)*AE37)," ",(AC37/AA37)*AE37) | AG37: =IF(ISERROR(C37+AB37)," ",(C37+AB37)) | AJ37: =AB37
B38: Transformers: Pad-Mount | G38: =IF(ISERROR(F38*D38)," ",F38*D38) | AC38: =IF(ISERROR(IF('Wainwright Summary'!$E$7-C38>AB38,0,(AB38-('Wainwright Summary'!$E$7-C38))/AB38)*G38)," ",(IF('Wainwright Summary'!$E$7-C38>AB38,0,(AB38-('Wainwright Summary'!$E$7-C38))/AB38)*AA38)) | AE38: =IF(ISERROR(D38*F38*AD38), " ",D38*F38*AD38 ) | AF38: =IF(ISERROR((AC38/AA38)*AE38)," ",(AC38/AA38)*AE38) | AG38: =IF(ISERROR(C38+AB38)," ",(C38+AB38)) | AJ38: =AB38
B39: 1P - 15 kVA & Smaller | C39: 1979 | D39: 8 | E39: ea | F39: 2975 | G39: =IF(ISERROR(F39*D39)," ",F39*D39) -> 23800 | H39: =H$10 -> 0.05 | I39: =I$10 -> 0.02 | J39: =J$10 -> 0.05 | K39: =K$10 -> 0.122 | L39: =L$10 -> 0.1 | M39: =G39*H39 -> 1190 | N39: =(G39+M39)*I39 -> 499.8 | O39: =(G39+M39+N39)*J39 -> 1274.49 | P39: =(G39+M39+N39+O39)*K39 -> 3265.2434 | Q39: =(G39+M39+N39+O39+P39)*L39 -> 3002.9533 | R39: =G39+SUM(M39:Q39) -> 33032.487 | S39: =S$10 -> 0.077 | T39: =T$10 -> 0.05 | U39: 0.03 | V39: =V$10 -> 0.1 | W39: =R39*S39 -> 2543.5015 | X39: =R39*T39 -> 1651.6243 | Y39: =R39*U39 -> 990.9746 | Z39: =(W39+X39)*V39 -> 419.51258 | AA39: =R39+SUM(W39:Z39) -> 38638.1 | AB39: 40 | AC39: =IF(ISERROR(IF('Wainwright Summary'!$E$7-C39>AB39,0,(AB39-('Wainwright Summary'!$E$7-C39))/AB39)*G39)," ",(IF('Wainwright Summary'!$E$7-C39>AB39,0,(AB39-('Wainwright Summary'!$E$7-C39))/AB39)*AA39)) -> 10625.477 | AD39: =VLOOKUP(C39,'Inflation-OLD'!$A$6:$B$126,2)/VLOOKUP('Wainwright Summary'!$E$6,'Inflation-OLD'!$A$6:$B$126,2) -> 0.42632751 | AE39: =IF(ISERROR(AA39*AD39), " ",AA39*AD39 ) -> 16472.485 | AF39: =IF(ISERROR((AC39/AA39)*AE39)," ",(AC39/AA39)*AE39) -> 4529.9334 | AG39: =IF(ISERROR(C39+AB39)," ",(C39+AB39)) -> 2019 | AJ39: =AB39 -> 40
B40: 1P - 25 kVA - Replace ERR1 | C40: 1971 | D40: 10 | E40: ea | F40: 3200 | G40: =IF(ISERROR(F40*D40)," ",F40*D40) -> 32000 | H40: =H$10 -> 0.05 | I40: =I$10 -> 0.02 | J40: =J$10 -> 0.05 | K40: =K$10 -> 0.122 | L40: =L$10 -> 0.1 | M40: =G40*H40 -> 1600 | N40: =(G40+M40)*I40 -> 672 | O40: =(G40+M40+N40)*J40 -> 1713.6 | P40: =(G40+M40+N40+O40)*K40 -> 4390.2432 | Q40: =(G40+M40+N40+O40+P40)*L40 -> 4037.5843 | R40: =G40+SUM(M40:Q40) -> 44413.428 | S40: =S$10 -> 0.077 | T40: =T$10 -> 0.05 | U40: 0.03 | V40: =V$10 -> 0.1 | W40: =R40*S40 -> 3419.8339 | X40: =R40*T40 -> 2220.6714 | Y40: =R40*U40 -> 1332.4028 | Z40: =(W40+X40)*V40 -> 564.05053 | AA40: =R40+SUM(W40:Z40) -> 51950.386 | AB40: 40 | AC40: =IF(ISERROR(IF('Wainwright Summary'!$E$7-C40>AB40,0,(AB40-('Wainwright Summary'!$E$7-C40))/AB40)*G40)," ",(IF('Wainwright Summary'!$E$7-C40>AB40,0,(AB40-('Wainwright Summary'!$E$7-C40))/AB40)*AA40)) -> 3896.279 | AD40: =VLOOKUP(C40,'Inflation-OLD'!$A$6:$B$126,2)/VLOOKUP('Wainwright Summary'!$E$6,'Inflation-OLD'!$A$6:$B$126,2) -> 0.2481841 | AE40: =IF(ISERROR(AA40*AD40), " ",AA40*AD40 ) -> 12893.26 | AF40: =IF(ISERROR((AC40/AA40)*AE40)," ",(AC40/AA40)*AE40) -> 966.99451 | AG40: =IF(ISERROR(C40+AB40)," ",(C40+AB40)) -> 2011 | AJ40: =AB40 -> 40 | AN40: In Initial R&R.
B41: 1P - 50 kVA - Replace ERR1 | C41: 1971 | D41: 3 | E41: ea | F41: 5800 | G41: =IF(ISERROR(F41*D41)," ",F41*D41) -> 17400 | H41: =H$10 -> 0.05 | I41: =I$10 -> 0.02 | J41: =J$10 -> 0.05 | K41: =K$10 -> 0.122 | L41: =L$10 -> 0.1 | M41: =G41*H41 -> 870 | N41: =(G41+M41)*I41 -> 365.4 | O41: =(G41+M41+N41)*J41 -> 931.77 | P41: =(G41+M41+N41+O41)*K41 -> 2387.1947 | Q41: =(G41+M41+N41+O41+P41)*L41 -> 2195.4365 | R41: =G41+SUM(M41:Q41) -> 24149.801 | S41: =S$10 -> 0.077 | T41: =T$10 -> 0.05 | U41: 0.03 | V41: =V$10 -> 0.1 | W41: =R41*S41 -> 1859.5347 | X41: =R41*T41 -> 1207.4901 | Y41: =R41*U41 -> 724.49404 | Z41: =(W41+X41)*V41 -> 306.70248 | AA41: =R41+SUM(W41:Z41) -> 28248.022 | AB41: 40 | AC41: =IF(ISERROR(IF('Wainwright Summary'!$E$7-C41>AB41,0,(AB41-('Wainwright Summary'!$E$7-C41))/AB41)*G41)," ",(IF('Wainwright Summary'!$E$7-C41>AB41,0,(AB41-('Wainwright Summary'!$E$7-C41))/AB41)*AA41)) -> 2118.6017 | AD41: =VLOOKUP(C41,'Inflation-OLD'!$A$6:$B$126,2)/VLOOKUP('Wainwright Summary'!$E$6,'Inflation-OLD'!$A$6:$B$126,2) -> 0.2481841 | AE41: =IF(ISERROR(AA41*AD41), " ",AA41*AD41 ) -> 7010.7102 | AF41: =IF(ISERROR((AC41/AA41)*AE41)," ",(AC41/AA41)*AE41) -> 525.80326 | AG41: =IF(ISERROR(C41+AB41)," ",(C41+AB41)) -> 2011 | AJ41: =AB41 -> 40 | AN41: In Initial R&R.
B42: 1P - 75 kVA - Replace ERR1 | C42: 1970 | D42: 2 | E42: ea | F42: 9500 | G42: =IF(ISERROR(F42*D42)," ",F42*D42) -> 19000 | H42: =H$10 -> 0.05 | I42: =I$10 -> 0.02 | J42: =J$10 -> 0.05 | K42: =K$10 -> 0.122 | L42: =L$10 -> 0.1 | M42: =G42*H42 -> 950 | N42: =(G42+M42)*I42 -> 399 | O42: =(G42+M42+N42)*J42 -> 1017.45 | P42: =(G42+M42+N42+O42)*K42 -> 2606.7069 | Q42: =(G42+M42+N42+O42+P42)*L42 -> 2397.3157 | R42: =G42+SUM(M42:Q42) -> 26370.473 | S42: =S$10 -> 0.077 | T42: =T$10 -> 0.05 | U42: 0.03 | V42: =V$10 -> 0.1 | W42: =R42*S42 -> 2030.5264 | X42: =R42*T42 -> 1318.5236 | Y42: =R42*U42 -> 791.11418 | Z42: =(W42+X42)*V42 -> 334.905 | AA42: =R42+SUM(W42:Z42) -> 30845.542 | AB42: 40 | AC42: =IF(ISERROR(IF('Wainwright Summary'!$E$7-C42>AB42,0,(AB42-('Wainwright Summary'!$E$7-C42))/AB42)*G42)," ",(IF('Wainwright Summary'!$E$7-C42>AB42,0,(AB42-('Wainwright Summary'!$E$7-C42))/AB42)*AA42)) -> 1542.2771 | AD42: =VLOOKUP(C42,'Inflation-OLD'!$A$6:$B$126,2)/VLOOKUP('Wainwright Summary'!$E$6,'Inflation-OLD'!$A$6:$B$126,2) -> 0.2359352 | AE42: =IF(ISERROR(AA42*AD42), " ",AA42*AD42 ) -> 7277.5492 | AF42: =IF(ISERROR((AC42/AA42)*AE42)," ",(AC42/AA42)*AE42) -> 363.87746 | AG42: =IF(ISERROR(C42+AB42)," ",(C42+AB42)) -> 2010 | AJ42: =AB42 -> 40 | AN42: In Initial R&R.
B43: 1P - 100 kVA - Replace ERR1 | C43: 1974 | D43: 4 | E43: ea | F43: 13267 | G43: =IF(ISERROR(F43*D43)," ",F43*D43) -> 53068 | H43: =H$10 -> 0.05 | I43: =I$10 -> 0.02 | J43: =J$10 -> 0.05 | K43: =K$10 -> 0.122 | L43: =L$10 -> 0.1 | M43: =G43*H43 -> 2653.4 | N43: =(G43+M43)*I43 -> 1114.428 | O43: =(G43+M43+N43)*J43 -> 2841.7914 | P43: =(G43+M43+N43+O43)*K43 -> 7280.6696 | Q43: =(G43+M43+N43+O43+P43)*L43 -> 6695.8289 | R43: =G43+SUM(M43:Q43) -> 73654.118 | S43: =S$10 -> 0.077 | T43: =T$10 -> 0.05 | U43: 0.03 | V43: =V$10 -> 0.1 | W43: =R43*S43 -> 5671.3671 | X43: =R43*T43 -> 3682.7059 | Y43: =R43*U43 -> 2209.6235 | Z43: =(W43+X43)*V43 -> 935.4073 | AA43: =R43+SUM(W43:Z43) -> 86153.222 | AB43: 40 | AC43: =IF(ISERROR(IF('Wainwright Summary'!$E$7-C43>AB43,0,(AB43-('Wainwright Summary'!$E$7-C43))/AB43)*G43)," ",(IF('Wainwright Summary'!$E$7-C43>AB43,0,(AB43-('Wainwright Summary'!$E$7-C43))/AB43)*AA43)) -> 12922.983 | AD43: =VLOOKUP(C43,'Inflation-OLD'!$A$6:$B$126,2)/VLOOKUP('Wainwright Summary'!$E$6,'Inflation-OLD'!$A$6:$B$126,2) -> 0.29142519 | AE43: =IF(ISERROR(AA43*AD43), " ",AA43*AD43 ) -> 25107.219 | AF43: =IF(ISERROR((AC43/AA43)*AE43)," ",(AC43/AA43)*AE43) -> 3766.0829 | AG43: 2011 | AJ43: =AB43 -> 40
B44: 1P - 167 kVA - Replace ERR1 | C44: 1970 | D44: 2 | E44: ea | F44: 15000 | G44: =IF(ISERROR(F44*D44)," ",F44*D44) -> 30000 | H44: =H$10 -> 0.05 | I44: =I$10 -> 0.02 | J44: =J$10 -> 0.05 | K44: =K$10 -> 0.122 | L44: =L$10 -> 0.1 | M44: =G44*H44 -> 1500 | N44: =(G44+M44)*I44 -> 630 | O44: =(G44+M44+N44)*J44 -> 1606.5 | P44: =(G44+M44+N44+O44)*K44 -> 4115.853 | Q44: =(G44+M44+N44+O44+P44)*L44 -> 3785.2353 | R44: =G44+SUM(M44:Q44) -> 41637.588 | S44: =S$10 -> 0.077 | T44: =T$10 -> 0.05 | U44: 0.03 | V44: =V$10 -> 0.1 | W44: =R44*S44 -> 3206.0943 | X44: =R44*T44 -> 2081.8794 | Y44: =R44*U44 -> 1249.1276 | Z44: =(W44+X44)*V44 -> 528.79737 | AA44: =R44+SUM(W44:Z44) -> 48703.487 | AB44: 40 | AC44: =IF(ISERROR(IF('Wainwright Summary'!$E$7-C44>AB44,0,(AB44-('Wainwright Summary'!$E$7-C44))/AB44)*G44)," ",(IF('Wainwright Summary'!$E$7-C44>AB44,0,(AB44-('Wainwright Summary'!$E$7-C44))/AB44)*AA44)) -> 2435.1744 | AD44: =VLOOKUP(C44,'Inflation-OLD'!$A$6:$B$126,2)/VLOOKUP('Wainwright Summary'!$E$6,'Inflation-OLD'!$A$6:$B$126,2) -> 0.2359352 | AE44: =IF(ISERROR(AA44*AD44), " ",AA44*AD44 ) -> 11490.867 | AF44: =IF(ISERROR((AC44/AA44)*AE44)," ",(AC44/AA44)*AE44) -> 574.54336 | AG44: =IF(ISERROR(C44+AB44)," ",(C44+AB44)) -> 2010 | AJ44: =AB44 -> 40 | AN44: In Initial R&R.
B45: 1P - 833 kVA | C45: 1980 | D45: 6 | E45: ea | F45: 22500 | G45: =IF(ISERROR(F45*D45)," ",F45*D45) -> 135000 | H45: =H$10 -> 0.05 | I45: =I$10 -> 0.02 | J45: =J$10 -> 0.05 | K45: =K$10 -> 0.122 | L45: =L$10 -> 0.1 | M45: =G45*H45 -> 6750 | N45: =(G45+M45)*I45 -> 2835 | O45: =(G45+M45+N45)*J45 -> 7229.25 | P45: =(G45+M45+N45+O45)*K45 -> 18521.338 | Q45: =(G45+M45+N45+O45+P45)*L45 -> 17033.559 | R45: =G45+SUM(M45:Q45) -> 187369.15 | S45: =S$10 -> 0.077 | T45: =T$10 -> 0.05 | U45: =U$10 -> 0.05 | V45: =V$10 -> 0.1 | W45: =R45*S45 -> 14427.424 | X45: =R45*T45 -> 9368.4574 | Y45: =R45*U45 -> 9368.4574 | Z45: =(W45+X45)*V45 -> 2379.5882 | AA45: =R45+SUM(W45:Z45) -> 222913.07 | AB45: 40 | AC45: =IF(ISERROR(IF('Wainwright Summary'!$E$7-C45>AB45,0,(AB45-('Wainwright Summary'!$E$7-C45))/AB45)*G45)," ",(IF('Wainwright Summary'!$E$7-C45>AB45,0,(AB45-('Wainwright Summary'!$E$7-C45))/AB45)*AA45)) -> 66873.922 | AD45: =VLOOKUP(C45,'Inflation-OLD'!$A$6:$B$126,2)/VLOOKUP('Wainwright Summary'!$E$6,'Inflation-OLD'!$A$6:$B$126,2) -> 0.46299201 | AE45: =IF(ISERROR(AA45*AD45), " ",AA45*AD45 ) -> 103206.97 | AF45: =IF(ISERROR((AC45/AA45)*AE45)," ",(AC45/AA45)*AE45) -> 30962.092 | AG45: =IF(ISERROR(C45+AB45)," ",(C45+AB45)) -> 2020 | AJ45: =AB45 -> 40
B46: 3P - 150 kVA - Replace ERR1 | C46: 1979 | D46: 3 | E46: ea | F46: 14300 | G46: =IF(ISERROR(F46*D46)," ",F46*D46) -> 42900 | H46: =H$10 -> 0.05 | I46: =I$10 -> 0.02 | J46: =J$10 -> 0.05 | K46: =K$10 -> 0.122 | L46: =L$10 -> 0.1 | M46: =G46*H46 -> 2145 | N46: =(G46+M46)*I46 -> 900.9 | O46: =(G46+M46+N46)*J46 -> 2297.295 | P46: =(G46+M46+N46+O46)*K46 -> 5885.6698 | Q46: =(G46+M46+N46+O46+P46)*L46 -> 5412.8865 | R46: =G46+SUM(M46:Q46) -> 59541.751 | S46: =S$10 -> 0.077 | T46: =T$10 -> 0.05 | U46: 0.03 | V46: =V$10 -> 0.1 | W46: =R46*S46 -> 4584.7148 | X46: =R46*T46 -> 2977.0876 | Y46: =R46*U46 -> 1786.2525 | Z46: =(W46+X46)*V46 -> 756.18024 | AA46: =R46+SUM(W46:Z46) -> 69645.986 | AB46: 40 | AC46: =IF(ISERROR(IF('Wainwright Summary'!$E$7-C46>AB46,0,(AB46-('Wainwright Summary'!$E$7-C46))/AB46)*G46)," ",(IF('Wainwright Summary'!$E$7-C46>AB46,0,(AB46-('Wainwright Summary'!$E$7-C46))/AB46)*AA46)) -> 19152.646 | AD46: =VLOOKUP(C46,'Inflation-OLD'!$A$6:$B$126,2)/VLOOKUP('Wainwright Summary'!$E$6,'Inflation-OLD'!$A$6:$B$126,2) -> 0.42632751 | AE46: =IF(ISERROR(AA46*AD46), " ",AA46*AD46 ) -> 29692 | AF46: =IF(ISERROR((AC46/AA46)*AE46)," ",(AC46/AA46)*AE46) -> 8165.3001 | AG46: =IF(ISERROR(C46+AB46)," ",(C46+AB46)) -> 2019 | AJ46: =AB46 -> 40
B47: 3P - 225 kVA | C47: 1974 | D47: 10 | E47: ea | F47: 17571 | G47: =IF(ISERROR(F47*D47)," ",F47*D47) -> 175710 | H47: =H$10 -> 0.05 | I47: =I$10 -> 0.02 | J47: =J$10 -> 0.05 | K47: =K$10 -> 0.122 | L47: =L$10 -> 0.1 | M47: =G47*H47 -> 8785.5 | N47: =(G47+M47)*I47 -> 3689.91 | O47: =(G47+M47+N47)*J47 -> 9409.2705 | P47: =(G47+M47+N47+O47)*K47 -> 24106.551 | Q47: =(G47+M47+N47+O47+P47)*L47 -> 22170.123 | R47: =G47+SUM(M47:Q47) -> 243871.35 | S47: =S$10 -> 0.077 | T47: =T$10 -> 0.05 | U47: =U$10 -> 0.05 | V47: =V$10 -> 0.1 | W47: =R47*S47 -> 18778.094 | X47: =R47*T47 -> 12193.568 | Y47: =R47*U47 -> 12193.568 | Z47: =(W47+X47)*V47 -> 3097.1662 | AA47: =R47+SUM(W47:Z47) -> 290133.75 | AB47: 40 | AC47: =IF(ISERROR(IF('Wainwright Summary'!$E$7-C47>AB47,0,(AB47-('Wainwright Summary'!$E$7-C47))/AB47)*G47)," ",(IF('Wainwright Summary'!$E$7-C47>AB47,0,(AB47-('Wainwright Summary'!$E$7-C47))/AB47)*AA47)) -> 43520.063 | AD47: =VLOOKUP(C47,'Inflation-OLD'!$A$6:$B$126,2)/VLOOKUP('Wainwright Summary'!$E$6,'Inflation-OLD'!$A$6:$B$126,2) -> 0.29142519 | AE47: =IF(ISERROR(AA47*AD47), " ",AA47*AD47 ) -> 84552.284 | AF47: =IF(ISERROR((AC47/AA47)*AE47)," ",(AC47/AA47)*AE47) -> 12682.843 | AG47: =IF(ISERROR(C47+AB47)," ",(C47+AB47)) -> 2014 | AJ47: =AB47 -> 40
B48: 3P - 300 kVA | C48: 1980 | D48: 6 | E48: ea | F48: 20300 | G48: =IF(ISERROR(F48*D48)," ",F48*D48) -> 121800 | H48: =H$10 -> 0.05 | I48: =I$10 -> 0.02 | J48: =J$10 -> 0.05 | K48: =K$10 -> 0.122 | L48: =L$10 -> 0.1 | M48: =G48*H48 -> 6090 | N48: =(G48+M48)*I48 -> 2557.8 | O48: =(G48+M48+N48)*J48 -> 6522.39 | P48: =(G48+M48+N48+O48)*K48 -> 16710.363 | Q48: =(G48+M48+N48+O48+P48)*L48 -> 15368.055 | R48: =G48+SUM(M48:Q48) -> 169048.61 | S48: =S$10 -> 0.077 | T48: =T$10 -> 0.05 | U48: =U$10 -> 0.05 | V48: =V$10 -> 0.1 | W48: =R48*S48 -> 13016.743 | X48: =R48*T48 -> 8452.4304 | Y48: =R48*U48 -> 8452.4304 | Z48: =(W48+X48)*V48 -> 2146.9173 | AA48: =R48+SUM(W48:Z48) -> 201117.13 | AB48: 40 | AC48: =IF(ISERROR(IF('Wainwright Summary'!$E$7-C48>AB48,0,(AB48-('Wainwright Summary'!$E$7-C48))/AB48)*G48)," ",(IF('Wainwright Summary'!$E$7-C48>AB48,0,(AB48-('Wainwright Summary'!$E$7-C48))/AB48)*AA48)) -> 60335.139 | AD48: =VLOOKUP(C48,'Inflation-OLD'!$A$6:$B$126,2)/VLOOKUP('Wainwright Summary'!$E$6,'Inflation-OLD'!$A$6:$B$126,2) -> 0.46299201 | AE48: =IF(ISERROR(AA48*AD48), " ",AA48*AD48 ) -> 93115.624 | AF48: =IF(ISERROR((AC48/AA48)*AE48)," ",(AC48/AA48)*AE48) -> 27934.687 | AG48: =IF(ISERROR(C48+AB48)," ",(C48+AB48)) -> 2020 | AJ48: =AB48 -> 40
B49: 3P - 500 kVA | C49: 1982 | D49: 12 | E49: ea | F49: 21724 | G49: =IF(ISERROR(F49*D49)," ",F49*D49) -> 260688 | H49: =H$10 -> 0.05 | I49: =I$10 -> 0.02 | J49: =J$10 -> 0.05 | K49: =K$10 -> 0.122 | L49: =L$10 -> 0.1 | M49: =G49*H49 -> 13034.4 | N49: =(G49+M49)*I49 -> 5474.448 | O49: =(G49+M49+N49)*J49 -> 13959.842 | P49: =(G49+M49+N49+O49)*K49 -> 35765.116 | Q49: =(G49+M49+N49+O49+P49)*L49 -> 32892.181 | R49: =G49+SUM(M49:Q49) -> 361813.99 | S49: =S$10 -> 0.077 | T49: =T$10 -> 0.05 | U49: =U$10 -> 0.05 | V49: =V$10 -> 0.1 | W49: =R49*S49 -> 27859.677 | X49: =R49*T49 -> 18090.699 | Y49: =R49*U49 -> 18090.699 | Z49: =(W49+X49)*V49 -> 4595.0376 | AA49: =R49+SUM(W49:Z49) -> 430450.1 | AB49: 40 | AC49: =IF(ISERROR(IF('Wainwright Summary'!$E$7-C49>AB49,0,(AB49-('Wainwright Summary'!$E$7-C49))/AB49)*G49)," ",(IF('Wainwright Summary'!$E$7-C49>AB49,0,(AB49-('Wainwright Summary'!$E$7-C49))/AB49)*AA49)) -> 150657.54 | AD49: =VLOOKUP(C49,'Inflation-OLD'!$A$6:$B$126,2)/VLOOKUP('Wainwright Summary'!$E$6,'Inflation-OLD'!$A$6:$B$126,2) -> 0.54223993 | AE49: =IF(ISERROR(AA49*AD49), " ",AA49*AD49 ) -> 233407.23 | AF49: =IF(ISERROR((AC49/AA49)*AE49)," ",(AC49/AA49)*AE49) -> 81692.532 | AG49: =IF(ISERROR(C49+AB49)," ",(C49+AB49)) -> 2022 | AJ49: =AB49 -> 40
B50: 3P - 750 kVA | C50: 1979 | D50: 11 | E50: ea | F50: 28500 | G50: =IF(ISERROR(F50*D50)," ",F50*D50) -> 313500 | H50: =H$10 -> 0.05 | I50: =I$10 -> 0.02 | J50: =J$10 -> 0.05 | K50: =K$10 -> 0.122 | L50: =L$10 -> 0.1 | M50: =G50*H50 -> 15675 | N50: =(G50+M50)*I50 -> 6583.5 | O50: =(G50+M50+N50)*J50 -> 16787.925 | P50: =(G50+M50+N50+O50)*K50 -> 43010.664 | Q50: =(G50+M50+N50+O50+P50)*L50 -> 39555.709 | R50: =G50+SUM(M50:Q50) -> 435112.8 | S50: =S$10 -> 0.077 | T50: =T$10 -> 0.05 | U50: =U$10 -> 0.05 | V50: =V$10 -> 0.1 | W50: =R50*S50 -> 33503.685 | X50: =R50*T50 -> 21755.64 | Y50: =R50*U50 -> 21755.64 | Z50: =(W50+X50)*V50 -> 5525.9325 | AA50: =R50+SUM(W50:Z50) -> 517653.7 | AB50: 40 | AC50: =IF(ISERROR(IF('Wainwright Summary'!$E$7-C50>AB50,0,(AB50-('Wainwright Summary'!$E$7-C50))/AB50)*G50)," ",(IF('Wainwright Summary'!$E$7-C50>AB50,0,(AB50-('Wainwright Summary'!$E$7-C50))/AB50)*AA50)) -> 142354.77 | AD50: =VLOOKUP(C50,'Inflation-OLD'!$A$6:$B$126,2)/VLOOKUP('Wainwright Summary'!$E$6,'Inflation-OLD'!$A$6:$B$126,2) -> 0.42632751 | AE50: =IF(ISERROR(AA50*AD50), " ",AA50*AD50 ) -> 220690.01 | AF50: =IF(ISERROR((AC50/AA50)*AE50)," ",(AC50/AA50)*AE50) -> 60689.754 | AG50: =IF(ISERROR(C50+AB50)," ",(C50+AB50)) -> 2019 | AJ50: =AB50 -> 40
B51: 3P - 1000 kVA | C51: 1986 | D51: 4 | E51: ea | F51: 46000 | G51: =IF(ISERROR(F51*D51)," ",F51*D51) -> 184000 | H51: =H$10 -> 0.05 | I51: =I$10 -> 0.02 | J51: =J$10 -> 0.05 | K51: =K$10 -> 0.122 | L51: =L$10 -> 0.1 | M51: =G51*H51 -> 9200 | N51: =(G51+M51)*I51 -> 3864 | O51: =(G51+M51+N51)*J51 -> 9853.2 | P51: =(G51+M51+N51+O51)*K51 -> 25243.898 | Q51: =(G51+M51+N51+O51+P51)*L51 -> 23216.11 | R51: =G51+SUM(M51:Q51) -> 255377.21 | S51: =S$10 -> 0.077 | T51: =T$10 -> 0.05 | U51: =U$10 -> 0.05 | V51: =V$10 -> 0.1 | W51: =R51*S51 -> 19664.045 | X51: =R51*T51 -> 12768.86 | Y51: =R51*U51 -> 12768.86 | Z51: =(W51+X51)*V51 -> 3243.2905 | AA51: =R51+SUM(W51:Z51) -> 303822.26 | AB51: 40 | AC51: =IF(ISERROR(IF('Wainwright Summary'!$E$7-C51>AB51,0,(AB51-('Wainwright Summary'!$E$7-C51))/AB51)*G51)," ",(IF('Wainwright Summary'!$E$7-C51>AB51,0,(AB51-('Wainwright Summary'!$E$7-C51))/AB51)*AA51)) -> 136720.02 | AD51: =VLOOKUP(C51,'Inflation-OLD'!$A$6:$B$126,2)/VLOOKUP('Wainwright Summary'!$E$6,'Inflation-OLD'!$A$6:$B$126,2) -> 0.62132344 | AE51: =IF(ISERROR(AA51*AD51), " ",AA51*AD51 ) -> 188771.89 | AF51: =IF(ISERROR((AC51/AA51)*AE51)," ",(AC51/AA51)*AE51) -> 84947.352 | AG51: =IF(ISERROR(C51+AB51)," ",(C51+AB51)) -> 2026 | AJ51: =AB51 -> 40
B52: 3P - 2000 kVA | C52: 1991 | D52: 1 | E52: ea | F52: 46000 | G52: =IF(ISERROR(F52*D52)," ",F52*D52) -> 46000 | H52: =H$10 -> 0.05 | I52: =I$10 -> 0.02 | J52: =J$10 -> 0.05 | K52: =K$10 -> 0.122 | L52: =L$10 -> 0.1 | M52: =G52*H52 -> 2300 | N52: =(G52+M52)*I52 -> 966 | O52: =(G52+M52+N52)*J52 -> 2463.3 | P52: =(G52+M52+N52+O52)*K52 -> 6310.9746 | Q52: =(G52+M52+N52+O52+P52)*L52 -> 5804.0275 | R52: =G52+SUM(M52:Q52) -> 63844.302 | S52: =S$10 -> 0.077 | T52: =T$10 -> 0.05 | U52: 0.03 | V52: =V$10 -> 0.1 | W52: =R52*S52 -> 4916.0113 | X52: =R52*T52 -> 3192.2151 | Y52: =R52*U52 -> 1915.3291 | Z52: =(W52+X52)*V52 -> 810.82264 | AA52: =R52+SUM(W52:Z52) -> 74678.68 | AB52: 40 | AC52: =IF(ISERROR(IF('Wainwright Summary'!$E$7-C52>AB52,0,(AB52-('Wainwright Summary'!$E$7-C52))/AB52)*G52)," ",(IF('Wainwright Summary'!$E$7-C52>AB52,0,(AB52-('Wainwright Summary'!$E$7-C52))/AB52)*AA52)) -> 42940.241 | AD52: =VLOOKUP(C52,'Inflation-OLD'!$A$6:$B$126,2)/VLOOKUP('Wainwright Summary'!$E$6,'Inflation-OLD'!$A$6:$B$126,2) -> 0.73600275 | AE52: =IF(ISERROR(AA52*AD52), " ",AA52*AD52 ) -> 54963.714 | AF52: =IF(ISERROR((AC52/AA52)*AE52)," ",(AC52/AA52)*AE52) -> 31604.135 | AG52: =IF(ISERROR(C52+AB52)," ",(C52+AB52)) -> 2031 | AJ52: =AB52 -> 40
G53: =IF(ISERROR(F53*D53)," ",F53*D53) | AC53: =IF(ISERROR(IF('Wainwright Summary'!$E$7-C53>AB53,0,(AB53-('Wainwright Summary'!$E$7-C53))/AB53)*G53)," ",(IF('Wainwright Summary'!$E$7-C53>AB53,0,(AB53-('Wainwright Summary'!$E$7-C53))/AB53)*AA53)) | AE53: =IF(ISERROR(D53*F53*AD53), " ",D53*F53*AD53 ) | AF53: =IF(ISERROR((AC53/AA53)*AE53)," ",(AC53/AA53)*AE53) | AG53: =IF(ISERROR(C53+AB53)," ",(C53+AB53)) | AJ53: =AB53
B54: Street Lights | G54: =IF(ISERROR(F54*D54)," ",F54*D54) | AC54: =IF(ISERROR(IF('Wainwright Summary'!$E$7-C54>AB54,0,(AB54-('Wainwright Summary'!$E$7-C54))/AB54)*G54)," ",(IF('Wainwright Summary'!$E$7-C54>AB54,0,(AB54-('Wainwright Summary'!$E$7-C54))/AB54)*AA54)) | AE54: =IF(ISERROR(D54*F54*AD54), " ",D54*F54*AD54 ) | AF54: =IF(ISERROR((AC54/AA54)*AE54)," ",(AC54/AA54)*AE54) | AG54: =IF(ISERROR(C54+AB54)," ",(C54+AB54)) | AJ54: =AB54
B55: Street Light Circuits - ECU4 | C55: 1980 | D55: 54172.8 | E55: lf | F55: =16*1.064 -> 17.024 | G55: =IF(ISERROR(F55*D55)," ",F55*D55) -> 922237.75 | H55: =H$10 -> 0.05 | I55: =I$10 -> 0.02 | J55: =J$10 -> 0.05 | K55: =K$10 -> 0.122 | L55: =L$10 -> 0.1 | M55: =G55*H55 -> 46111.887 | N55: =(G55+M55)*I55 -> 19366.993 | O55: =(G55+M55+N55)*J55 -> 49385.831 | P55: =(G55+M55+N55+O55)*K55 -> 126526.5 | Q55: =(G55+M55+N55+O55+P55)*L55 -> 116362.9 | R55: =G55+SUM(M55:Q55) -> 1279991.9 | S55: =S$10 -> 0.077 | T55: =T$10 -> 0.05 | U55: =U$10 -> 0.05 | V55: =V$10 -> 0.1 | W55: =R55*S55 -> 98559.373 | X55: =R55*T55 -> 63999.593 | Y55: =R55*U55 -> 63999.593 | Z55: =(W55+X55)*V55 -> 16255.897 | AA55: =R55+SUM(W55:Z55) -> 1522806.3 | AB55: 50 | AC55: =IF(ISERROR(IF('Wainwright Summary'!$E$7-C55>AB55,0,(AB55-('Wainwright Summary'!$E$7-C55))/AB55)*G55)," ",(IF('Wainwright Summary'!$E$7-C55>AB55,0,(AB55-('Wainwright Summary'!$E$7-C55))/AB55)*AA55)) -> 670034.78 | AD55: =VLOOKUP(C55,'Inflation-OLD'!$A$6:$B$126,2)/VLOOKUP('Wainwright Summary'!$E$6,'Inflation-OLD'!$A$6:$B$126,2) -> 0.46299201 | AE55: =IF(ISERROR(AA55*AD55), " ",AA55*AD55 ) -> 705047.15 | AF55: =IF(ISERROR((AC55/AA55)*AE55)," ",(AC55/AA55)*AE55) -> 310220.75 | AG55: =IF(ISERROR(C55+AB55)," ",(C55+AB55)) -> 2030 | AJ55: =AB55 -> 50
B56: Fixtures with Poles (no conductor on map) | C56: 1980 | D56: 361 | E56: ea | F56: 1000 | G56: =IF(ISERROR(F56*D56)," ",F56*D56) -> 361000 | H56: =H$10 -> 0.05 | I56: =I$10 -> 0.02 | J56: =J$10 -> 0.05 | K56: =K$10 -> 0.122 | L56: =L$10 -> 0.1 | M56: =G56*H56 -> 18050 | N56: =(G56+M56)*I56 -> 7581 | O56: =(G56+M56+N56)*J56 -> 19331.55 | P56: =(G56+M56+N56+O56)*K56 -> 49527.431 | Q56: =(G56+M56+N56+O56+P56)*L56 -> 45548.998 | R56: =G56+SUM(M56:Q56) -> 501038.98 | S56: =S$10 -> 0.077 | T56: =T$10 -> 0.05 | U56: =U$10 -> 0.05 | V56: =V$10 -> 0.1 | W56: =R56*S56 -> 38580.001 | X56: =R56*T56 -> 25051.949 | Y56: =R56*U56 -> 25051.949 | Z56: =(W56+X56)*V56 -> 6363.195 | AA56: =R56+SUM(W56:Z56) -> 596086.07 | AB56: 50 | AC56: =IF(ISERROR(IF('Wainwright Summary'!$E$7-C56>AB56,0,(AB56-('Wainwright Summary'!$E$7-C56))/AB56)*G56)," ",(IF('Wainwright Summary'!$E$7-C56>AB56,0,(AB56-('Wainwright Summary'!$E$7-C56))/AB56)*AA56)) -> 262277.87 | AD56: =VLOOKUP(C56,'Inflation-OLD'!$A$6:$B$126,2)/VLOOKUP('Wainwright Summary'!$E$6,'Inflation-OLD'!$A$6:$B$126,2) -> 0.46299201 | AE56: =IF(ISERROR(AA56*AD56), " ",AA56*AD56 ) -> 275983.09 | AF56: =IF(ISERROR((AC56/AA56)*AE56)," ",(AC56/AA56)*AE56) -> 121432.56 | AG56: =IF(ISERROR(C56+AB56)," ",(C56+AB56)) -> 2030 | AJ56: =AB56 -> 50
B57: Fixtures without Poles | C57: 1977 | D57: 248 | E57: ea | F57: 500 | G57: =IF(ISERROR(F57*D57)," ",F57*D57) -> 124000 | H57: =H$10 -> 0.05 | I57: =I$10 -> 0.02 | J57: =J$10 -> 0.05 | K57: =K$10 -> 0.122 | L57: =L$10 -> 0.1 | M57: =G57*H57 -> 6200 | N57: =(G57+M57)*I57 -> 2604 | O57: =(G57+M57+N57)*J57 -> 6640.2 | P57: =(G57+M57+N57+O57)*K57 -> 17012.192 | Q57: =(G57+M57+N57+O57+P57)*L57 -> 15645.639 | R57: =G57+SUM(M57:Q57) -> 172102.03 | S57: =S$10 -> 0.077 | T57: =T$10 -> 0.05 | U57: =U$10 -> 0.05 | V57: =V$10 -> 0.1 | W57: =R57*S57 -> 13251.856 | X57: =R57*T57 -> 8605.1016 | Y57: =R57*U57 -> 8605.1016 | Z57: =(W57+X57)*V57 -> 2185.6958 | AA57: =R57+SUM(W57:Z57) -> 204749.79 | AB57: 50 | AC57: =IF(ISERROR(IF('Wainwright Summary'!$E$7-C57>AB57,0,(AB57-('Wainwright Summary'!$E$7-C57))/AB57)*G57)," ",(IF('Wainwright Summary'!$E$7-C57>AB57,0,(AB57-('Wainwright Summary'!$E$7-C57))/AB57)*AA57)) -> 77804.919 | AD57: =VLOOKUP(C57,'Inflation-OLD'!$A$6:$B$126,2)/VLOOKUP('Wainwright Summary'!$E$6,'Inflation-OLD'!$A$6:$B$126,2) -> 0.37034428 | AE57: =IF(ISERROR(AA57*AD57), " ",AA57*AD57 ) -> 75827.913 | AF57: =IF(ISERROR((AC57/AA57)*AE57)," ",(AC57/AA57)*AE57) -> 28814.607 | AG57: =IF(ISERROR(C57+AB57)," ",(C57+AB57)) -> 2027 | AJ57: =AB57 -> 50
B58: Fixtures with Poles -ECU4 | C58: 1979 | D58: 181 | E58: ea | F58: 1000 | G58: =IF(ISERROR(F58*D58)," ",F58*D58) -> 181000 | H58: =H$10 -> 0.05 | I58: =I$10 -> 0.02 | J58: =J$10 -> 0.05 | K58: =K$10 -> 0.122 | L58: =L$10 -> 0.1 | M58: =G58*H58 -> 9050 | N58: =(G58+M58)*I58 -> 3801 | O58: =(G58+M58+N58)*J58 -> 9692.55 | P58: =(G58+M58+N58+O58)*K58 -> 24832.313 | Q58: =(G58+M58+N58+O58+P58)*L58 -> 22837.586 | R58: =G58+SUM(M58:Q58) -> 251213.45 | S58: =S$10 -> 0.077 | T58: =T$10 -> 0.05 | U58: =U$10 -> 0.05 | V58: =V$10 -> 0.1 | W58: =R58*S58 -> 19343.436 | X58: =R58*T58 -> 12560.672 | Y58: =R58*U58 -> 12560.672 | Z58: =(W58+X58)*V58 -> 3190.4108 | AA58: =R58+SUM(W58:Z58) -> 298868.64 | AB58: 50 | AC58: =IF(ISERROR(IF('Wainwright Summary'!$E$7-C58>AB58,0,(AB58-('Wainwright Summary'!$E$7-C58))/AB58)*G58)," ",(IF('Wainwright Summary'!$E$7-C58>AB58,0,(AB58-('Wainwright Summary'!$E$7-C58))/AB58)*AA58)) -> 125524.83 | AD58: =VLOOKUP(C58,'Inflation-OLD'!$A$6:$B$126,2)/VLOOKUP('Wainwright Summary'!$E$6,'Inflation-OLD'!$A$6:$B$126,2) -> 0.42632751 | AE58: =IF(ISERROR(AA58*AD58), " ",AA58*AD58 ) -> 127415.92 | AF58: =IF(ISERROR((AC58/AA58)*AE58)," ",(AC58/AA58)*AE58) -> 53514.688 | AG58: =IF(ISERROR(C58+AB58)," ",(C58+AB58)) -> 2029 | AJ58: =AB58 -> 50
G59: =IF(ISERROR(F59*D59)," ",F59*D59) | AC59: =IF(ISERROR(IF('Wainwright Summary'!$E$7-C59>AB59,0,(AB59-('Wainwright Summary'!$E$7-C59))/AB59)*G59)," ",(IF('Wainwright Summary'!$E$7-C59>AB59,0,(AB59-('Wainwright Summary'!$E$7-C59))/AB59)*AA59)) | AE59: =IF(ISERROR(D59*F59*AD59), " ",D59*F59*AD59 ) | AF59: =IF(ISERROR((AC59/AA59)*AE59)," ",(AC59/AA59)*AE59) | AG59: =IF(ISERROR(C59+AB59)," ",(C59+AB59)) | AJ59: =AB59
G61: =IF(ISERROR(F61*D61)," ",F61*D61) | AC61: =IF(ISERROR(IF('Wainwright Summary'!$E$7-C61>AB61,0,(AB61-('Wainwright Summary'!$E$7-C61))/AB61)*G61)," ",(IF('Wainwright Summary'!$E$7-C61>AB61,0,(AB61-('Wainwright Summary'!$E$7-C61))/AB61)*AA61)) | AE61: =IF(ISERROR(D61*F61*AD61), " ",D61*F61*AD61 ) | AF61: =IF(ISERROR((AC61/AA61)*AE61)," ",(AC61/AA61)*AE61) | AG61: =IF(ISERROR(C61+AB61)," ",(C61+AB61)) | AJ61: =AB61
B62: Emergency Generators | G62: =IF(ISERROR(F62*D62)," ",F62*D62) | AC62: =IF(ISERROR(IF('Wainwright Summary'!$E$7-C62>AB62,0,(AB62-('Wainwright Summary'!$E$7-C62))/AB62)*G62)," ",(IF('Wainwright Summary'!$E$7-C62>AB62,0,(AB62-('Wainwright Summary'!$E$7-C62))/AB62)*AA62)) | AE62: =IF(ISERROR(D62*F62*AD62), " ",D62*F62*AD62 ) | AF62: =IF(ISERROR((AC62/AA62)*AE62)," ",(AC62/AA62)*AE62) | AG62: =IF(ISERROR(C62+AB62)," ",(C62+AB62)) | AJ62: =AB62
B63: Hospital Generator (Building 4065) - 400-kW | C63: 1997 | D63: 2 | E63: ea | F63: 350000 | G63: =IF(ISERROR(F63*D63)," ",F63*D63) -> 700000 | H63: 0 | I63: 0 | J63: 0 | K63: 0 | L63: 0 | M63: =G63*H63 -> 0 | N63: =(G63+M63)*I63 -> 0 | O63: =(G63+M63+N63)*J63 -> 0 | P63: =(G63+M63+N63+O63)*K63 -> 0 | Q63: =(G63+M63+N63+O63+P63)*L63 -> 0 | R63: =G63+SUM(M63:Q63) -> 700000 | S63: 0 | T63: 0 | U63: =U$10 -> 0.05 | V63: 0 | W63: =R63*S63 -> 0 | X63: =R63*T63 -> 0 | Y63: =R63*U63 -> 35000 | Z63: =(W63+X63)*V63 -> 0 | AA63: =R63+SUM(W63:Z63) -> 735000 | AB63: 50 | AC63: =IF(ISERROR(IF('Wainwright Summary'!$E$7-C63>AB63,0,(AB63-('Wainwright Summary'!$E$7-C63))/AB63)*G63)," ",(IF('Wainwright Summary'!$E$7-C63>AB63,0,(AB63-('Wainwright Summary'!$E$7-C63))/AB63)*AA63)) -> 573300 | AD63: =VLOOKUP(C63,'Inflation-OLD'!$A$6:$B$126,2)/VLOOKUP('Wainwright Summary'!$E$6,'Inflation-OLD'!$A$6:$B$126,2) -> 0.83604914 | AE63: =IF(ISERROR(AA63*AD63), " ",AA63*AD63 ) -> 614496.12 | AF63: =IF(ISERROR((AC63/AA63)*AE63)," ",(AC63/AA63)*AE63) -> 479306.97 | AG63: =IF(ISERROR(C63+AB63)," ",(C63+AB63)) -> 2047 | AJ63: =AB63 -> 50
B64: MP Station Generator (Building 3028) - 15-kW | C64: 1976 | D64: 1 | E64: ea | F64: 5700 | G64: =IF(ISERROR(F64*D64)," ",F64*D64) -> 5700 | H64: 0 | I64: 0 | J64: 0 | K64: 0 | L64: 0 | M64: =G64*H64 -> 0 | N64: =(G64+M64)*I64 -> 0 | O64: =(G64+M64+N64)*J64 -> 0 | P64: =(G64+M64+N64+O64)*K64 -> 0 | Q64: =(G64+M64+N64+O64+P64)*L64 -> 0 | R64: =G64+SUM(M64:Q64) -> 5700 | S64: 0 | T64: 0 | U64: 0.03 | V64: 0 | W64: =R64*S64 -> 0 | X64: =R64*T64 -> 0 | Y64: =R64*U64 -> 171 | Z64: =(W64+X64)*V64 -> 0 | AA64: =R64+SUM(W64:Z64) -> 5871 | AB64: 50 | AC64: =IF(ISERROR(IF('Wainwright Summary'!$E$7-C64>AB64,0,(AB64-('Wainwright Summary'!$E$7-C64))/AB64)*G64)," ",(IF('Wainwright Summary'!$E$7-C64>AB64,0,(AB64-('Wainwright Summary'!$E$7-C64))/AB64)*AA64)) -> 2113.56 | AD64: =VLOOKUP(C64,'Inflation-OLD'!$A$6:$B$126,2)/VLOOKUP('Wainwright Summary'!$E$6,'Inflation-OLD'!$A$6:$B$126,2) -> 0.34354467 | AE64: =IF(ISERROR(AA64*AD64), " ",AA64*AD64 ) -> 2016.9508 | AF64: =IF(ISERROR((AC64/AA64)*AE64)," ",(AC64/AA64)*AE64) -> 726.10228 | AG64: =IF(ISERROR(C64+AB64)," ",(C64+AB64)) -> 2026 | AJ64: =AB64 -> 50
B65: Fire Station #1 Generator (Building 3004) - 25-kW | C65: 1993 | D65: 1 | E65: ea | F65: 18000 | G65: =IF(ISERROR(F65*D65)," ",F65*D65) -> 18000 | H65: 0 | I65: 0 | J65: 0 | K65: 0 | L65: 0 | M65: =G65*H65 -> 0 | N65: =(G65+M65)*I65 -> 0 | O65: =(G65+M65+N65)*J65 -> 0 | P65: =(G65+M65+N65+O65)*K65 -> 0 | Q65: =(G65+M65+N65+O65+P65)*L65 -> 0 | R65: =G65+SUM(M65:Q65) -> 18000 | S65: 0 | T65: 0 | U65: 0.03 | V65: 0 | W65: =R65*S65 -> 0 | X65: =R65*T65 -> 0 | Y65: =R65*U65 -> 540 | Z65: =(W65+X65)*V65 -> 0 | AA65: =R65+SUM(W65:Z65) -> 18540 | AB65: 50 | AC65: =IF(ISERROR(IF('Wainwright Summary'!$E$7-C65>AB65,0,(AB65-('Wainwright Summary'!$E$7-C65))/AB65)*G65)," ",(IF('Wainwright Summary'!$E$7-C65>AB65,0,(AB65-('Wainwright Summary'!$E$7-C65))/AB65)*AA65)) -> 12978 | AD65: =VLOOKUP(C65,'Inflation-OLD'!$A$6:$B$126,2)/VLOOKUP('Wainwright Summary'!$E$6,'Inflation-OLD'!$A$6:$B$126,2) -> 0.77209179 | AE65: =IF(ISERROR(AA65*AD65), " ",AA65*AD65 ) -> 14314.582 | AF65: =IF(ISERROR((AC65/AA65)*AE65)," ",(AC65/AA65)*AE65) -> 10020.207 | AG65: =IF(ISERROR(C65+AB65)," ",(C65+AB65)) -> 2043 | AJ65: =AB65 -> 50
B66: Coded Message Center Generator (Building 3407) - 60-kW | C66: 2001 | D66: 1 | E66: ea | F66: 27750 | G66: =IF(ISERROR(F66*D66)," ",F66*D66) -> 27750 | H66: 0 | I66: 0 | J66: 0 | K66: 0 | L66: 0 | M66: =G66*H66 -> 0 | N66: =(G66+M66)*I66 -> 0 | O66: =(G66+M66+N66)*J66 -> 0 | P66: =(G66+M66+N66+O66)*K66 -> 0 | Q66: =(G66+M66+N66+O66+P66)*L66 -> 0 | R66: =G66+SUM(M66:Q66) -> 27750 | S66: 0 | T66: 0 | U66: 0.03 | V66: 0 | W66: =R66*S66 -> 0 | X66: =R66*T66 -> 0 | Y66: =R66*U66 -> 832.5 | Z66: =(W66+X66)*V66 -> 0 | AA66: =R66+SUM(W66:Z66) -> 28582.5 | AB66: 50 | AC66: =IF(ISERROR(IF('Wainwright Summary'!$E$7-C66>AB66,0,(AB66-('Wainwright Summary'!$E$7-C66))/AB66)*G66)," ",(IF('Wainwright Summary'!$E$7-C66>AB66,0,(AB66-('Wainwright Summary'!$E$7-C66))/AB66)*AA66)) -> 24580.95 | AD66: =VLOOKUP(C66,'Inflation-OLD'!$A$6:$B$126,2)/VLOOKUP('Wainwright Summary'!$E$6,'Inflation-OLD'!$A$6:$B$126,2) -> 0.88800421 | AE66: =IF(ISERROR(AA66*AD66), " ",AA66*AD66 ) -> 25381.38 | AF66: =IF(ISERROR((AC66/AA66)*AE66)," ",(AC66/AA66)*AE66) -> 21827.987 | AG66: =IF(ISERROR(C66+AB66)," ",(C66+AB66)) -> 2051 | AJ66: =AB66 -> 50
B67: Commissary Generator (Building 3703) - 25-kW | C67: 1989 | D67: 1 | E67: ea | F67: 18000 | G67: =IF(ISERROR(F67*D67)," ",F67*D67) -> 18000 | H67: 0 | I67: 0 | J67: 0 | K67: 0 | L67: 0 | M67: =G67*H67 -> 0 | N67: =(G67+M67)*I67 -> 0 | O67: =(G67+M67+N67)*J67 -> 0 | P67: =(G67+M67+N67+O67)*K67 -> 0 | Q67: =(G67+M67+N67+O67+P67)*L67 -> 0 | R67: =G67+SUM(M67:Q67) -> 18000 | S67: 0 | T67: 0 | U67: 0.03 | V67: 0 | W67: =R67*S67 -> 0 | X67: =R67*T67 -> 0 | Y67: =R67*U67 -> 540 | Z67: =(W67+X67)*V67 -> 0 | AA67: =R67+SUM(W67:Z67) -> 18540 | AB67: 50 | AC67: =IF(ISERROR(IF('Wainwright Summary'!$E$7-C67>AB67,0,(AB67-('Wainwright Summary'!$E$7-C67))/AB67)*G67)," ",(IF('Wainwright Summary'!$E$7-C67>AB67,0,(AB67-('Wainwright Summary'!$E$7-C67))/AB67)*AA67)) -> 11494.8 | AD67: =VLOOKUP(C67,'Inflation-OLD'!$A$6:$B$126,2)/VLOOKUP('Wainwright Summary'!$E$6,'Inflation-OLD'!$A$6:$B$126,2) -> 0.68380105 | AE67: =IF(ISERROR(AA67*AD67), " ",AA67*AD67 ) -> 12677.672 | AF67: =IF(ISERROR((AC67/AA67)*AE67)," ",(AC67/AA67)*AE67) -> 7860.1564 | AG67: =IF(ISERROR(C67+AB67)," ",(C67+AB67)) -> 2039 | AJ67: =AB67 -> 50
B68: Runway Lighting Generator (Building 1563) - 150-kW | C68: 1970 | D68: 1 | E68: ea | F68: 20250 | G68: =IF(ISERROR(F68*D68)," ",F68*D68) -> 20250 | H68: 0 | I68: 0 | J68: 0 | K68: 0 | L68: 0 | M68: =G68*H68 -> 0 | N68: =(G68+M68)*I68 -> 0 | O68: =(G68+M68+N68)*J68 -> 0 | P68: =(G68+M68+N68+O68)*K68 -> 0 | Q68: =(G68+M68+N68+O68+P68)*L68 -> 0 | R68: =G68+SUM(M68:Q68) -> 20250 | S68: 0 | T68: 0 | U68: 0.03 | V68: 0 | W68: =R68*S68 -> 0 | X68: =R68*T68 -> 0 | Y68: =R68*U68 -> 607.5 | Z68: =(W68+X68)*V68 -> 0 | AA68: =R68+SUM(W68:Z68) -> 20857.5 | AB68: 50 | AC68: =IF(ISERROR(IF('Wainwright Summary'!$E$7-C68>AB68,0,(AB68-('Wainwright Summary'!$E$7-C68))/AB68)*G68)," ",(IF('Wainwright Summary'!$E$7-C68>AB68,0,(AB68-('Wainwright Summary'!$E$7-C68))/AB68)*AA68)) -> 5005.8 | AD68: =VLOOKUP(C68,'Inflation-OLD'!$A$6:$B$126,2)/VLOOKUP('Wainwright Summary'!$E$6,'Inflation-OLD'!$A$6:$B$126,2) -> 0.2359352 | AE68: =IF(ISERROR(AA68*AD68), " ",AA68*AD68 ) -> 4921.0185 | AF68: =IF(ISERROR((AC68/AA68)*AE68)," ",(AC68/AA68)*AE68) -> 1181.0444 | AG68: =IF(ISERROR(C68+AB68)," ",(C68+AB68)) -> 2020 | AJ68: =AB68 -> 50
B69: Control Tower Generator (Building 1580) - 100-kW | C69: 1982 | D69: 1 | E69: ea | F69: 25350 | G69: =IF(ISERROR(F69*D69)," ",F69*D69) -> 25350 | H69: 0 | I69: 0 | J69: 0 | K69: 0 | L69: 0 | M69: =G69*H69 -> 0 | N69: =(G69+M69)*I69 -> 0 | O69: =(G69+M69+N69)*J69 -> 0 | P69: =(G69+M69+N69+O69)*K69 -> 0 | Q69: =(G69+M69+N69+O69+P69)*L69 -> 0 | R69: =G69+SUM(M69:Q69) -> 25350 | S69: 0 | T69: 0 | U69: 0.03 | V69: 0 | W69: =R69*S69 -> 0 | X69: =R69*T69 -> 0 | Y69: =R69*U69 -> 760.5 | Z69: =(W69+X69)*V69 -> 0 | AA69: =R69+SUM(W69:Z69) -> 26110.5 | AB69: 50 | AC69: =IF(ISERROR(IF('Wainwright Summary'!$E$7-C69>AB69,0,(AB69-('Wainwright Summary'!$E$7-C69))/AB69)*G69)," ",(IF('Wainwright Summary'!$E$7-C69>AB69,0,(AB69-('Wainwright Summary'!$E$7-C69))/AB69)*AA69)) -> 12533.04 | AD69: =VLOOKUP(C69,'Inflation-OLD'!$A$6:$B$126,2)/VLOOKUP('Wainwright Summary'!$E$6,'Inflation-OLD'!$A$6:$B$126,2) -> 0.54223993 | AE69: =IF(ISERROR(AA69*AD69), " ",AA69*AD69 ) -> 14158.156 | AF69: =IF(ISERROR((AC69/AA69)*AE69)," ",(AC69/AA69)*AE69) -> 6795.9148 | AG69: =IF(ISERROR(C69+AB69)," ",(C69+AB69)) -> 2032 | AJ69: =AB69 -> 50
B70: Army Headquarters Generator (Building 1555) - 200-kW | C70: 1993 | D70: 1 | E70: ea | F70: 43875 | G70: =IF(ISERROR(F70*D70)," ",F70*D70) -> 43875 | H70: 0 | I70: 0 | J70: 0 | K70: 0 | L70: 0 | M70: =G70*H70 -> 0 | N70: =(G70+M70)*I70 -> 0 | O70: =(G70+M70+N70)*J70 -> 0 | P70: =(G70+M70+N70+O70)*K70 -> 0 | Q70: =(G70+M70+N70+O70+P70)*L70 -> 0 | R70: =G70+SUM(M70:Q70) -> 43875 | S70: 0 | T70: 0 | U70: 0.03 | V70: 0 | W70: =R70*S70 -> 0 | X70: =R70*T70 -> 0 | Y70: =R70*U70 -> 1316.25 | Z70: =(W70+X70)*V70 -> 0 | AA70: =R70+SUM(W70:Z70) -> 45191.25 | AB70: 50 | AC70: =IF(ISERROR(IF('Wainwright Summary'!$E$7-C70>AB70,0,(AB70-('Wainwright Summary'!$E$7-C70))/AB70)*G70)," ",(IF('Wainwright Summary'!$E$7-C70>AB70,0,(AB70-('Wainwright Summary'!$E$7-C70))/AB70)*AA70)) -> 31633.875 | AD70: =VLOOKUP(C70,'Inflation-OLD'!$A$6:$B$126,2)/VLOOKUP('Wainwright Summary'!$E$6,'Inflation-OLD'!$A$6:$B$126,2) -> 0.77209179 | AE70: =IF(ISERROR(AA70*AD70), " ",AA70*AD70 ) -> 34891.793 | AF70: =IF(ISERROR((AC70/AA70)*AE70)," ",(AC70/AA70)*AE70) -> 24424.255 | AG70: =IF(ISERROR(C70+AB70)," ",(C70+AB70)) -> 2043 | AJ70: =AB70 -> 50
B71: Command Center Generator (Building 1060) - 250-kW | C71: 1993 | D71: 1 | E71: ea | F71: 44250 | G71: =IF(ISERROR(F71*D71)," ",F71*D71) -> 44250 | H71: 0 | I71: 0 | J71: 0 | K71: 0 | L71: 0 | M71: =G71*H71 -> 0 | N71: =(G71+M71)*I71 -> 0 | O71: =(G71+M71+N71)*J71 -> 0 | P71: =(G71+M71+N71+O71)*K71 -> 0 | Q71: =(G71+M71+N71+O71+P71)*L71 -> 0 | R71: =G71+SUM(M71:Q71) -> 44250 | S71: 0 | T71: 0 | U71: 0.03 | V71: 0 | W71: =R71*S71 -> 0 | X71: =R71*T71 -> 0 | Y71: =R71*U71 -> 1327.5 | Z71: =(W71+X71)*V71 -> 0 | AA71: =R71+SUM(W71:Z71) -> 45577.5 | AB71: 50 | AC71: =IF(ISERROR(IF('Wainwright Summary'!$E$7-C71>AB71,0,(AB71-('Wainwright Summary'!$E$7-C71))/AB71)*G71)," ",(IF('Wainwright Summary'!$E$7-C71>AB71,0,(AB71-('Wainwright Summary'!$E$7-C71))/AB71)*AA71)) -> 31904.25 | AD71: =VLOOKUP(C71,'Inflation-OLD'!$A$6:$B$126,2)/VLOOKUP('Wainwright Summary'!$E$6,'Inflation-OLD'!$A$6:$B$126,2) -> 0.77209179 | AE71: =IF(ISERROR(AA71*AD71), " ",AA71*AD71 ) -> 35190.013 | AF71: =IF(ISERROR((AC71/AA71)*AE71)," ",(AC71/AA71)*AE71) -> 24633.009 | AG71: =IF(ISERROR(C71+AB71)," ",(C71+AB71)) -> 2043 | AJ71: =AB71 -> 50
B72: Birch Hill Transmitter Generator (Building 1193) - 25-kW | C72: 1990 | D72: 1 | E72: ea | F72: 5700 | G72: =IF(ISERROR(F72*D72)," ",F72*D72) -> 5700 | H72: 0 | I72: 0 | J72: 0 | K72: 0 | L72: 0 | M72: =G72*H72 -> 0 | N72: =(G72+M72)*I72 -> 0 | O72: =(G72+M72+N72)*J72 -> 0 | P72: =(G72+M72+N72+O72)*K72 -> 0 | Q72: =(G72+M72+N72+O72+P72)*L72 -> 0 | R72: =G72+SUM(M72:Q72) -> 5700 | S72: 0 | T72: 0 | U72: 0.03 | V72: 0 | W72: =R72*S72 -> 0 | X72: =R72*T72 -> 0 | Y72: =R72*U72 -> 171 | Z72: =(W72+X72)*V72 -> 0 | AA72: =R72+SUM(W72:Z72) -> 5871 | AB72: 50 | AC72: =IF(ISERROR(IF('Wainwright Summary'!$E$7-C72>AB72,0,(AB72-('Wainwright Summary'!$E$7-C72))/AB72)*G72)," ",(IF('Wainwright Summary'!$E$7-C72>AB72,0,(AB72-('Wainwright Summary'!$E$7-C72))/AB72)*AA72)) -> 3757.44 | AD72: =VLOOKUP(C72,'Inflation-OLD'!$A$6:$B$126,2)/VLOOKUP('Wainwright Summary'!$E$6,'Inflation-OLD'!$A$6:$B$126,2) -> 0.70977859 | AE72: =IF(ISERROR(AA72*AD72), " ",AA72*AD72 ) -> 4167.1101 | AF72: =IF(ISERROR((AC72/AA72)*AE72)," ",(AC72/AA72)*AE72) -> 2666.9505 | AG72: =IF(ISERROR(C72+AB72)," ",(C72+AB72)) -> 2040 | AJ72: =AB72 -> 50 | AN72: Assume installation date of 1990.
B73: Replace Black Rapids Generator - new 250 kW (ECU3) | C73: 2009 | D73: 2 | E73: ea | F73: =(335100*1.064)/2 -> 178273.2 | G73: =IF(ISERROR(F73*D73)," ",F73*D73) -> 356546.4 | H73: 0 | I73: 0 | J73: 0 | K73: 0 | L73: 0 | M73: =G73*H73 -> 0 | N73: =(G73+M73)*I73 -> 0 | O73: =(G73+M73+N73)*J73 -> 0 | P73: =(G73+M73+N73+O73)*K73 -> 0 | Q73: =(G73+M73+N73+O73+P73)*L73 -> 0 | R73: =G73+SUM(M73:Q73) -> 356546.4 | S73: 0 | T73: 0 | U73: 0.06 | V73: 0 | W73: =R73*S73 -> 0 | X73: =R73*T73 -> 0 | Y73: =R73*U73 -> 21392.784 | Z73: =(W73+X73)*V73 -> 0 | AA73: =R73+SUM(W73:Z73) -> 377939.18 | AB73: 20 | AC73: 0 | AD73: 0 | AE73: 0 | AF73: 0 | AG73: 2009 | AJ73: 50
B74: Black Rapids Generator - 125 kW (abandoned) | C74: 1990 | D74: 2 | E74: ea | F74: 84000 | G74: =IF(ISERROR(F74*D74)," ",F74*D74) -> 168000 | H74: 0 | I74: 0 | J74: 0 | K74: 0 | L74: 0 | M74: =G74*H74 -> 0 | N74: =(G74+M74)*I74 -> 0 | O74: =(G74+M74+N74)*J74 -> 0 | P74: =(G74+M74+N74+O74)*K74 -> 0 | Q74: =(G74+M74+N74+O74+P74)*L74 -> 0 | R74: =G74+SUM(M74:Q74) -> 168000 | S74: 0 | T74: 0 | U74: 0.06 | V74: 0 | W74: =R74*S74 -> 0 | X74: =R74*T74 -> 0 | Y74: =R74*U74 -> 10080 | Z74: =(W74+X74)*V74 -> 0 | AA74: =R74+SUM(W74:Z74) -> 178080 | AB74: 50 | AC74: 0 | AD74: =VLOOKUP(C74,'Inflation-OLD'!$A$6:$B$126,2)/VLOOKUP('Wainwright Summary'!$E$6,'Inflation-OLD'!$A$6:$B$126,2) -> 0.70977859 | AE74: =IF(ISERROR(AA74*AD74), " ",AA74*AD74 ) -> 126397.37 | AF74: =IF(ISERROR((AC74/AA74)*AE74)," ",(AC74/AA74)*AE74) -> 0 | AG74: 9999 | AJ74: =AB74 -> 50 | AN74: taken out of service, no scap value, due to deficiency, see new BR Generator Project above
B75: Black Rapids Generator 125 kW (remains) | C75: 1990 | D75: 1 | E75: ea | F75: 84000 | G75: =IF(ISERROR(F75*D75)," ",F75*D75) -> 84000 | H75: 0 | I75: 0 | J75: 0 | K75: 0 | L75: 0 | M75: =G75*H75 -> 0 | N75: =(G75+M75)*I75 -> 0 | O75: =(G75+M75+N75)*J75 -> 0 | P75: =(G75+M75+N75+O75)*K75 -> 0 | Q75: =(G75+M75+N75+O75+P75)*L75 -> 0 | R75: =G75+SUM(M75:Q75) -> 84000 | S75: 0 | T75: 0 | U75: 0.06 | V75: 0 | W75: =R75*S75 -> 0 | X75: =R75*T75 -> 0 | Y75: =R75*U75 -> 5040 | Z75: =(W75+X75)*V75 -> 0 | AA75: =R75+SUM(W75:Z75) -> 89040 | AB75: 50 | AC75: =IF(ISERROR(IF('Wainwright Summary'!$E$7-C75>AB75,0,(AB75-('Wainwright Summary'!$E$7-C75))/AB75)*G75)," ",(IF('Wainwright Summary'!$E$7-C75>AB75,0,(AB75-('Wainwright Summary'!$E$7-C75))/AB75)*AA75)) -> 56985.6 | AD75: =VLOOKUP(C75,'Inflation-OLD'!$A$6:$B$126,2)/VLOOKUP('Wainwright Summary'!$E$6,'Inflation-OLD'!$A$6:$B$126,2) -> 0.70977859 | AE75: =IF(ISERROR(AA75*AD75), " ",AA75*AD75 ) -> 63198.686 | AF75: =IF(ISERROR((AC75/AA75)*AE75)," ",(AC75/AA75)*AE75) -> 40447.159 | AG75: =IF(ISERROR(C75+AB75)," ",(C75+AB75)) -> 2040 | AJ75: =AB75 -> 50
B76: Upgrade Boilio Lake Feeder #9 (ECU2) - allocated portion only | C76: 1950 | D76: 18 | E76: miles | F76: =63618*1.064 -> 67689.552 | G76: =IF(ISERROR(F76*D76)," ",F76*D76) -> 1218411.9 | H76: 0 | I76: 0 | J76: 0 | K76: 0 | L76: 0 | M76: =G76*H76 -> 0 | N76: =(G76+M76)*I76 -> 0 | O76: =(G76+M76+N76)*J76 -> 0 | P76: =(G76+M76+N76+O76)*K76 -> 0 | Q76: =(G76+M76+N76+O76+P76)*L76 -> 0 | R76: =G76+SUM(M76:Q76) -> 1218411.9 | S76: 0 | T76: 0 | U76: =U$10 -> 0.05 | V76: 0 | W76: =R76*S76 -> 0 | X76: =R76*T76 -> 0 | Y76: =R76*U76 -> 60920.597 | Z76: =(W76+X76)*V76 -> 0 | AA76: =R76+SUM(W76:Z76) -> 1279332.5 | AB76: 50 | AC76: =IF(ISERROR(IF('Wainwright Summary'!$E$7-C76>AB76,0,(AB76-('Wainwright Summary'!$E$7-C76))/AB76)*G76)," ",(IF('Wainwright Summary'!$E$7-C76>AB76,0,(AB76-('Wainwright Summary'!$E$7-C76))/AB76)*AA76)) -> 0 | AD76: =VLOOKUP(C76,'Inflation-OLD'!$A$6:$B$126,2)/VLOOKUP('Wainwright Summary'!$E$6,'Inflation-OLD'!$A$6:$B$126,2) -> 0.14287644 | AE76: =IF(ISERROR(AA76*AD76), " ",AA76*AD76 ) -> 182786.48 | AF76: =IF(ISERROR((AC76/AA76)*AE76)," ",(AC76/AA76)*AE76) -> 0 | AG76: 2008 | AJ76: =AB76 -> 50
B78: Runway Radar - 35 KW | C78: 2005 | D78: 1 | E78: ea | F78: 20000 | G78: =IF(ISERROR(F78*D78)," ",F78*D78) -> 20000 | H78: 0 | I78: 0 | J78: 0 | K78: 0 | L78: 0 | M78: =G78*H78 -> 0 | N78: =(G78+M78)*I78 -> 0 | O78: =(G78+M78+N78)*J78 -> 0 | P78: =(G78+M78+N78+O78)*K78 -> 0 | Q78: =(G78+M78+N78+O78+P78)*L78 -> 0 | R78: =G78+SUM(M78:Q78) -> 20000 | U78: 0.03 | W78: =R78*S78 -> 0 | X78: =R78*T78 -> 0 | Y78: =R78*U78 -> 600 | Z78: =(W78+X78)*V78 -> 0 | AA78: =R78+SUM(W78:Z78) -> 20600 | AB78: 50 | AC78: =IF(ISERROR(IF('Wainwright Summary'!$E$7-C78>AB78,0,(AB78-('Wainwright Summary'!$E$7-C78))/AB78)*G78)," ",(IF('Wainwright Summary'!$E$7-C78>AB78,0,(AB78-('Wainwright Summary'!$E$7-C78))/AB78)*AA78)) -> 19364 | AD78: =VLOOKUP(C78,'Inflation-OLD'!$A$6:$B$126,2)/VLOOKUP('Wainwright Summary'!$E$6,'Inflation-OLD'!$A$6:$B$126,2) -> 0.96116878 | AE78: =IF(ISERROR(AA78*AD78), " ",AA78*AD78 ) -> 19800.077 | AF78: =IF(ISERROR((AC78/AA78)*AE78)," ",(AC78/AA78)*AE78) -> 18612.072 | AG78: =IF(ISERROR(C78+AB78)," ",(C78+AB78)) -> 2055 | AJ78: =AB78 -> 50
B79: Range Adminisitration - 7 KW | C79: 2003 | D79: 1 | E79: ea | F79: 5000 | G79: =IF(ISERROR(F79*D79)," ",F79*D79) -> 5000 | H79: 0 | I79: 0 | J79: 0 | K79: 0 | L79: 0 | M79: =G79*H79 -> 0 | N79: =(G79+M79)*I79 -> 0 | O79: =(G79+M79+N79)*J79 -> 0 | P79: =(G79+M79+N79+O79)*K79 -> 0 | Q79: =(G79+M79+N79+O79+P79)*L79 -> 0 | R79: =G79+SUM(M79:Q79) -> 5000 | U79: 0.03 | W79: =R79*S79 -> 0 | X79: =R79*T79 -> 0 | Y79: =R79*U79 -> 150 | Z79: =(W79+X79)*V79 -> 0 | AA79: =R79+SUM(W79:Z79) -> 5150 | AB79: 50 | AC79: =IF(ISERROR(IF('Wainwright Summary'!$E$7-C79>AB79,0,(AB79-('Wainwright Summary'!$E$7-C79))/AB79)*G79)," ",(IF('Wainwright Summary'!$E$7-C79>AB79,0,(AB79-('Wainwright Summary'!$E$7-C79))/AB79)*AA79)) -> 4635 | AD79: =VLOOKUP(C79,'Inflation-OLD'!$A$6:$B$126,2)/VLOOKUP('Wainwright Summary'!$E$6,'Inflation-OLD'!$A$6:$B$126,2) -> 0.92384663 | AE79: =IF(ISERROR(AA79*AD79), " ",AA79*AD79 ) -> 4757.8101 | AF79: =IF(ISERROR((AC79/AA79)*AE79)," ",(AC79/AA79)*AE79) -> 4282.0291 | AG79: =IF(ISERROR(C79+AB79)," ",(C79+AB79)) -> 2053 | AJ79: =AB79 -> 50
G80: =IF(ISERROR(F80*D80)," ",F80*D80) | AC80: =IF(ISERROR(IF('Wainwright Summary'!$E$7-C80>AB80,0,(AB80-('Wainwright Summary'!$E$7-C80))/AB80)*G80)," ",(IF('Wainwright Summary'!$E$7-C80>AB80,0,(AB80-('Wainwright Summary'!$E$7-C80))/AB80)*AA80)) | AE80: =IF(ISERROR(D80*F80*AD80), " ",D80*F80*AD80 ) | AF80: =IF(ISERROR((AC80/AA80)*AE80)," ",(AC80/AA80)*AE80) | AG80: =IF(ISERROR(C80+AB80)," ",(C80+AB80)) | AJ80: =AB80
B81: HOUSING AREAS' | G81: =IF(ISERROR(F81*D81)," ",F81*D81) | AC81: =IF(ISERROR(IF('Wainwright Summary'!$E$7-C81>AB81,0,(AB81-('Wainwright Summary'!$E$7-C81))/AB81)*G81)," ",(IF('Wainwright Summary'!$E$7-C81>AB81,0,(AB81-('Wainwright Summary'!$E$7-C81))/AB81)*AA81)) | AE81: =IF(ISERROR(D81*F81*AD81), " ",D81*F81*AD81 ) | AF81: =IF(ISERROR((AC81/AA81)*AE81)," ",(AC81/AA81)*AE81) | AG81: =IF(ISERROR(C81+AB81)," ",(C81+AB81)) | AJ81: =AB81
B82: Overhead Lines | G82: =IF(ISERROR(F82*D82)," ",F82*D82) | AC82: =IF(ISERROR(IF('Wainwright Summary'!$E$7-C82>AB82,0,(AB82-('Wainwright Summary'!$E$7-C82))/AB82)*G82)," ",(IF('Wainwright Summary'!$E$7-C82>AB82,0,(AB82-('Wainwright Summary'!$E$7-C82))/AB82)*AA82)) | AE82: =IF(ISERROR(D82*F82*AD82), " ",D82*F82*AD82 ) | AF82: =IF(ISERROR((AC82/AA82)*AE82)," ",(AC82/AA82)*AE82) | AG82: =IF(ISERROR(C82+AB82)," ",(C82+AB82)) | AJ82: =AB82
B83: 3 Ph. - Open Wire, Large | C83: 1982 | D83: 4329.6 | E83: lf | F83: 33 | G83: =IF(ISERROR(F83*D83)," ",F83*D83) -> 142876.8 | H83: =H$10 -> 0.05 | I83: =I$10 -> 0.02 | J83: =J$10 -> 0.05 | K83: =K$10 -> 0.122 | L83: =L$10 -> 0.1 | M83: =G83*H83 -> 7143.84 | N83: =(G83+M83)*I83 -> 3000.4128 | O83: =(G83+M83+N83)*J83 -> 7651.0526 | P83: =(G83+M83+N83+O83)*K83 -> 19601.997 | Q83: =(G83+M83+N83+O83+P83)*L83 -> 18027.41 | R83: =G83+SUM(M83:Q83) -> 198301.51 | S83: =S$10 -> 0.077 | T83: =T$10 -> 0.05 | U83: =U$10 -> 0.05 | V83: =V$10 -> 0.1 | W83: =R83*S83 -> 15269.216 | X83: =R83*T83 -> 9915.0756 | Y83: =R83*U83 -> 9915.0756 | Z83: =(W83+X83)*V83 -> 2518.4292 | AA83: =R83+SUM(W83:Z83) -> 235919.31 | AB83: 50 | AC83: =IF(ISERROR(IF('Wainwright Summary'!$E$7-C83>AB83,0,(AB83-('Wainwright Summary'!$E$7-C83))/AB83)*G83)," ",(IF('Wainwright Summary'!$E$7-C83>AB83,0,(AB83-('Wainwright Summary'!$E$7-C83))/AB83)*AA83)) -> 113241.27 | AD83: =VLOOKUP(C83,'Inflation-OLD'!$A$6:$B$126,2)/VLOOKUP('Wainwright Summary'!$E$6,'Inflation-OLD'!$A$6:$B$126,2) -> 0.54223993 | AE83: =IF(ISERROR(AA83*AD83), " ",AA83*AD83 ) -> 127924.87 | AF83: =IF(ISERROR((AC83/AA83)*AE83)," ",(AC83/AA83)*AE83) -> 61403.938 | AG83: =IF(ISERROR(C83+AB83)," ",(C83+AB83)) -> 2032 | AJ83: =AB83 -> 50
B84: 3 Ph. - Open Wire, Small | C84: 1981 | D84: 37012.8 | E84: lf | F84: =31*1.064 -> 32.984 | G84: =IF(ISERROR(F84*D84)," ",F84*D84) -> 1220830.2 | H84: =H$10 -> 0.05 | I84: =I$10 -> 0.02 | J84: =J$10 -> 0.05 | K84: =K$10 -> 0.122 | L84: =L$10 -> 0.1 | M84: =G84*H84 -> 61041.51 | N84: =(G84+M84)*I84 -> 25637.434 | O84: =(G84+M84+N84)*J84 -> 65375.457 | P84: =(G84+M84+N84+O84)*K84 -> 167491.92 | Q84: =(G84+M84+N84+O84+P84)*L84 -> 154037.65 | R84: =G84+SUM(M84:Q84) -> 1694414.2 | S84: =S$10 -> 0.077 | T84: =T$10 -> 0.05 | U84: =U$10 -> 0.05 | V84: =V$10 -> 0.1 | W84: =R84*S84 -> 130469.89 | X84: =R84*T84 -> 84720.708 | Y84: =R84*U84 -> 84720.708 | Z84: =(W84+X84)*V84 -> 21519.06 | AA84: =R84+SUM(W84:Z84) -> 2015844.5 | AB84: 50 | AC84: =IF(ISERROR(IF('Wainwright Summary'!$E$7-C84>AB84,0,(AB84-('Wainwright Summary'!$E$7-C84))/AB84)*G84)," ",(IF('Wainwright Summary'!$E$7-C84>AB84,0,(AB84-('Wainwright Summary'!$E$7-C84))/AB84)*AA84)) -> 927288.49 | AD84: =VLOOKUP(C84,'Inflation-OLD'!$A$6:$B$126,2)/VLOOKUP('Wainwright Summary'!$E$6,'Inflation-OLD'!$A$6:$B$126,2) -> 0.50754841 | AE84: =IF(ISERROR(AA84*AD84), " ",AA84*AD84 ) -> 1023138.7 | AF84: =IF(ISERROR((AC84/AA84)*AE84)," ",(AC84/AA84)*AE84) -> 470643.8 | AG84: =IF(ISERROR(C84+AB84)," ",(C84+AB84)) -> 2031 | AJ84: =AB84 -> 50
B85: 1 Ph. - Open Wire | C85: 1976 | D85: 6283.2 | E85: lf | F85: =26*1.064 -> 27.664 | G85: =IF(ISERROR(F85*D85)," ",F85*D85) -> 173818.44 | H85: =H$10 -> 0.05 | I85: =I$10 -> 0.02 | J85: =J$10 -> 0.05 | K85: =K$10 -> 0.122 | L85: =L$10 -> 0.1 | M85: =G85*H85 -> 8690.9222 | N85: =(G85+M85)*I85 -> 3650.1873 | O85: =(G85+M85+N85)*J85 -> 9307.9777 | P85: =(G85+M85+N85+O85)*K85 -> 23847.039 | Q85: =(G85+M85+N85+O85+P85)*L85 -> 21931.457 | R85: =G85+SUM(M85:Q85) -> 241246.03 | S85: =S$10 -> 0.077 | T85: =T$10 -> 0.05 | U85: =U$10 -> 0.05 | V85: =V$10 -> 0.1 | W85: =R85*S85 -> 18575.944 | X85: =R85*T85 -> 12062.301 | Y85: =R85*U85 -> 12062.301 | Z85: =(W85+X85)*V85 -> 3063.8246 | AA85: =R85+SUM(W85:Z85) -> 287010.4 | AB85: 50 | AC85: =IF(ISERROR(IF('Wainwright Summary'!$E$7-C85>AB85,0,(AB85-('Wainwright Summary'!$E$7-C85))/AB85)*G85)," ",(IF('Wainwright Summary'!$E$7-C85>AB85,0,(AB85-('Wainwright Summary'!$E$7-C85))/AB85)*AA85)) -> 103323.74 | AD85: =VLOOKUP(C85,'Inflation-OLD'!$A$6:$B$126,2)/VLOOKUP('Wainwright Summary'!$E$6,'Inflation-OLD'!$A$6:$B$126,2) -> 0.34354467 | AE85: =IF(ISERROR(AA85*AD85), " ",AA85*AD85 ) -> 98600.894 | AF85: =IF(ISERROR((AC85/AA85)*AE85)," ",(AC85/AA85)*AE85) -> 35496.322 | AG85: =IF(ISERROR(C85+AB85)," ",(C85+AB85)) -> 2026 | AJ85: =AB85 -> 50
B86: Gang Operated Air Break Switch | C86: 1972 | D86: 5 | E86: ea | F86: 10000 | G86: =IF(ISERROR(F86*D86)," ",F86*D86) -> 50000 | H86: =H$10 -> 0.05 | I86: =I$10 -> 0.02 | J86: =J$10 -> 0.05 | K86: =K$10 -> 0.122 | L86: =L$10 -> 0.1 | M86: =G86*H86 -> 2500 | N86: =(G86+M86)*I86 -> 1050 | O86: =(G86+M86+N86)*J86 -> 2677.5 | P86: =(G86+M86+N86+O86)*K86 -> 6859.755 | Q86: =(G86+M86+N86+O86+P86)*L86 -> 6308.7255 | R86: =G86+SUM(M86:Q86) -> 69395.981 | S86: =S$10 -> 0.077 | T86: =T$10 -> 0.05 | U86: 0.03 | V86: =V$10 -> 0.1 | W86: =R86*S86 -> 5343.4905 | X86: =R86*T86 -> 3469.799 | Y86: =R86*U86 -> 2081.8794 | Z86: =(W86+X86)*V86 -> 881.32895 | AA86: =R86+SUM(W86:Z86) -> 81172.478 | AB86: 50 | AC86: =IF(ISERROR(IF('Wainwright Summary'!$E$7-C86>AB86,0,(AB86-('Wainwright Summary'!$E$7-C86))/AB86)*G86)," ",(IF('Wainwright Summary'!$E$7-C86>AB86,0,(AB86-('Wainwright Summary'!$E$7-C86))/AB86)*AA86)) -> 22728.294 | AD86: =VLOOKUP(C86,'Inflation-OLD'!$A$6:$B$126,2)/VLOOKUP('Wainwright Summary'!$E$6,'Inflation-OLD'!$A$6:$B$126,2) -> 0.26018638 | AE86: =IF(ISERROR(AA86*AD86), " ",AA86*AD86 ) -> 21119.974 | AF86: =IF(ISERROR((AC86/AA86)*AE86)," ",(AC86/AA86)*AE86) -> 5913.5926 | AG86: =IF(ISERROR(C86+AB86)," ",(C86+AB86)) -> 2022 | AJ86: =AB86 -> 50
B87: Secondary | C87: 1980 | D87: 41923.2 | E87: lf | F87: =16*1.064 -> 17.024 | G87: =IF(ISERROR(F87*D87)," ",F87*D87) -> 713700.56 | H87: =H$10 -> 0.05 | I87: =I$10 -> 0.02 | J87: =J$10 -> 0.05 | K87: =K$10 -> 0.122 | L87: =L$10 -> 0.1 | M87: =G87*H87 -> 35685.028 | N87: =(G87+M87)*I87 -> 14987.712 | O87: =(G87+M87+N87)*J87 -> 38218.665 | P87: =(G87+M87+N87+O87)*K87 -> 97916.219 | Q87: =(G87+M87+N87+O87+P87)*L87 -> 90050.818 | R87: =G87+SUM(M87:Q87) -> 990559 | S87: =S$10 -> 0.077 | T87: =T$10 -> 0.05 | U87: =U$10 -> 0.05 | V87: =V$10 -> 0.1 | W87: =R87*S87 -> 76273.043 | X87: =R87*T87 -> 49527.95 | Y87: =R87*U87 -> 49527.95 | Z87: =(W87+X87)*V87 -> 12580.099 | AA87: =R87+SUM(W87:Z87) -> 1178468 | AB87: 50 | AC87: =IF(ISERROR(IF('Wainwright Summary'!$E$7-C87>AB87,0,(AB87-('Wainwright Summary'!$E$7-C87))/AB87)*G87)," ",(IF('Wainwright Summary'!$E$7-C87>AB87,0,(AB87-('Wainwright Summary'!$E$7-C87))/AB87)*AA87)) -> 518525.94 | AD87: =VLOOKUP(C87,'Inflation-OLD'!$A$6:$B$126,2)/VLOOKUP('Wainwright Summary'!$E$6,'Inflation-OLD'!$A$6:$B$126,2) -> 0.46299201 | AE87: =IF(ISERROR(AA87*AD87), " ",AA87*AD87 ) -> 545621.29 | AF87: =IF(ISERROR((AC87/AA87)*AE87)," ",(AC87/AA87)*AE87) -> 240073.37 | AG87: =IF(ISERROR(C87+AB87)," ",(C87+AB87)) -> 2030 | AJ87: =AB87 -> 50
G88: =IF(ISERROR(F88*D88)," ",F88*D88) | AC88: =IF(ISERROR(IF('Wainwright Summary'!$E$7-C88>AB88,0,(AB88-('Wainwright Summary'!$E$7-C88))/AB88)*G88)," ",(IF('Wainwright Summary'!$E$7-C88>AB88,0,(AB88-('Wainwright Summary'!$E$7-C88))/AB88)*AA88)) | AE88: =IF(ISERROR(D88*F88*AD88), " ",D88*F88*AD88 ) | AF88: =IF(ISERROR((AC88/AA88)*AE88)," ",(AC88/AA88)*AE88) | AG88: =IF(ISERROR(C88+AB88)," ",(C88+AB88)) | AJ88: =AB88
B89: Underground Lines | G89: =IF(ISERROR(F89*D89)," ",F89*D89) | AC89: =IF(ISERROR(IF('Wainwright Summary'!$E$7-C89>AB89,0,(AB89-('Wainwright Summary'!$E$7-C89))/AB89)*G89)," ",(IF('Wainwright Summary'!$E$7-C89>AB89,0,(AB89-('Wainwright Summary'!$E$7-C89))/AB89)*AA89)) | AE89: =IF(ISERROR(D89*F89*AD89), " ",D89*F89*AD89 ) | AF89: =IF(ISERROR((AC89/AA89)*AE89)," ",(AC89/AA89)*AE89) | AG89: =IF(ISERROR(C89+AB89)," ",(C89+AB89)) | AJ89: =AB89
B90: Secondary | C90: 1980 | D90: 1320 | E90: lf | F90: 19 | G90: =IF(ISERROR(F90*D90)," ",F90*D90) -> 25080 | H90: =H$10 -> 0.05 | I90: =I$10 -> 0.02 | J90: =J$10 -> 0.05 | K90: =K$10 -> 0.122 | L90: =L$10 -> 0.1 | M90: =G90*H90 -> 1254 | N90: =(G90+M90)*I90 -> 526.68 | O90: =(G90+M90+N90)*J90 -> 1343.034 | P90: =(G90+M90+N90+O90)*K90 -> 3440.8531 | Q90: =(G90+M90+N90+O90+P90)*L90 -> 3164.4567 | R90: =G90+SUM(M90:Q90) -> 34809.024 | S90: =S$10 -> 0.077 | T90: =T$10 -> 0.05 | U90: 0.03 | V90: =V$10 -> 0.1 | W90: =R90*S90 -> 2680.2948 | X90: =R90*T90 -> 1740.4512 | Y90: =R90*U90 -> 1044.2707 | Z90: =(W90+X90)*V90 -> 442.0746 | AA90: =R90+SUM(W90:Z90) -> 40716.115 | AB90: 40 | AC90: =IF(ISERROR(IF('Wainwright Summary'!$E$7-C90>AB90,0,(AB90-('Wainwright Summary'!$E$7-C90))/AB90)*G90)," ",(IF('Wainwright Summary'!$E$7-C90>AB90,0,(AB90-('Wainwright Summary'!$E$7-C90))/AB90)*AA90)) -> 12214.835 | AD90: =VLOOKUP(C90,'Inflation-OLD'!$A$6:$B$126,2)/VLOOKUP('Wainwright Summary'!$E$6,'Inflation-OLD'!$A$6:$B$126,2) -> 0.46299201 | AE90: =IF(ISERROR(AA90*AD90), " ",AA90*AD90 ) -> 18851.236 | AF90: =IF(ISERROR((AC90/AA90)*AE90)," ",(AC90/AA90)*AE90) -> 5655.3708 | AG90: =IF(ISERROR(C90+AB90)," ",(C90+AB90)) -> 2020 | AJ90: =AB90 -> 40
G91: =IF(ISERROR(F91*D91)," ",F91*D91) | AC91: =IF(ISERROR(IF('Wainwright Summary'!$E$7-C91>AB91,0,(AB91-('Wainwright Summary'!$E$7-C91))/AB91)*G91)," ",(IF('Wainwright Summary'!$E$7-C91>AB91,0,(AB91-('Wainwright Summary'!$E$7-C91))/AB91)*AA91)) | AE91: =IF(ISERROR(D91*F91*AD91), " ",D91*F91*AD91 ) | AF91: =IF(ISERROR((AC91/AA91)*AE91)," ",(AC91/AA91)*AE91) | AG91: =IF(ISERROR(C91+AB91)," ",(C91+AB91)) | AJ91: =AB91
B92: Transformers: Pole Type | G92: =IF(ISERROR(F92*D92)," ",F92*D92) | AC92: =IF(ISERROR(IF('Wainwright Summary'!$E$7-C92>AB92,0,(AB92-('Wainwright Summary'!$E$7-C92))/AB92)*G92)," ",(IF('Wainwright Summary'!$E$7-C92>AB92,0,(AB92-('Wainwright Summary'!$E$7-C92))/AB92)*AA92)) | AE92: =IF(ISERROR(D92*F92*AD92), " ",D92*F92*AD92 ) | AF92: =IF(ISERROR((AC92/AA92)*AE92)," ",(AC92/AA92)*AE92) | AG92: =IF(ISERROR(C92+AB92)," ",(C92+AB92)) | AJ92: =AB92
B93: 15 kVA & Smaller | C93: 1982 | D93: 39 | E93: ea | F93: 3200 | G93: =IF(ISERROR(F93*D93)," ",F93*D93) -> 124800 | H93: =H$10 -> 0.05 | I93: =I$10 -> 0.02 | J93: =J$10 -> 0.05 | K93: =K$10 -> 0.122 | L93: =L$10 -> 0.1 | M93: =G93*H93 -> 6240 | N93: =(G93+M93)*I93 -> 2620.8 | O93: =(G93+M93+N93)*J93 -> 6683.04 | P93: =(G93+M93+N93+O93)*K93 -> 17121.948 | Q93: =(G93+M93+N93+O93+P93)*L93 -> 15746.579 | R93: =G93+SUM(M93:Q93) -> 173212.37 | S93: =S$10 -> 0.077 | T93: =T$10 -> 0.05 | U93: =U$10 -> 0.05 | V93: =V$10 -> 0.1 | W93: =R93*S93 -> 13337.352 | X93: =R93*T93 -> 8660.6184 | Y93: =R93*U93 -> 8660.6184 | Z93: =(W93+X93)*V93 -> 2199.7971 | AA93: =R93+SUM(W93:Z93) -> 206070.75 | AB93: 40 | AC93: =IF(ISERROR(IF('Wainwright Summary'!$E$7-C93>AB93,0,(AB93-('Wainwright Summary'!$E$7-C93))/AB93)*G93)," ",(IF('Wainwright Summary'!$E$7-C93>AB93,0,(AB93-('Wainwright Summary'!$E$7-C93))/AB93)*AA93)) -> 72124.764 | AD93: =VLOOKUP(C93,'Inflation-OLD'!$A$6:$B$126,2)/VLOOKUP('Wainwright Summary'!$E$6,'Inflation-OLD'!$A$6:$B$126,2) -> 0.54223993 | AE93: =IF(ISERROR(AA93*AD93), " ",AA93*AD93 ) -> 111739.79 | AF93: =IF(ISERROR((AC93/AA93)*AE93)," ",(AC93/AA93)*AE93) -> 39108.927 | AG93: =IF(ISERROR(C93+AB93)," ",(C93+AB93)) -> 2022 | AJ93: =AB93 -> 40
B94: 25 kVA | C94: 1983 | D94: 79 | E94: ea | F94: 3700 | G94: =IF(ISERROR(F94*D94)," ",F94*D94) -> 292300 | H94: =H$10 -> 0.05 | I94: =I$10 -> 0.02 | J94: =J$10 -> 0.05 | K94: =K$10 -> 0.122 | L94: =L$10 -> 0.1 | M94: =G94*H94 -> 14615 | N94: =(G94+M94)*I94 -> 6138.3 | O94: =(G94+M94+N94)*J94 -> 15652.665 | P94: =(G94+M94+N94+O94)*K94 -> 40102.128 | Q94: =(G94+M94+N94+O94+P94)*L94 -> 36880.809 | R94: =G94+SUM(M94:Q94) -> 405688.9 | S94: =S$10 -> 0.077 | T94: =T$10 -> 0.05 | U94: =U$10 -> 0.05 | V94: =V$10 -> 0.1 | W94: =R94*S94 -> 31238.045 | X94: =R94*T94 -> 20284.445 | Y94: =R94*U94 -> 20284.445 | Z94: =(W94+X94)*V94 -> 5152.2491 | AA94: =R94+SUM(W94:Z94) -> 482648.09 | AB94: 40 | AC94: =IF(ISERROR(IF('Wainwright Summary'!$E$7-C94>AB94,0,(AB94-('Wainwright Summary'!$E$7-C94))/AB94)*G94)," ",(IF('Wainwright Summary'!$E$7-C94>AB94,0,(AB94-('Wainwright Summary'!$E$7-C94))/AB94)*AA94)) -> 180993.03 | AD94: =VLOOKUP(C94,'Inflation-OLD'!$A$6:$B$126,2)/VLOOKUP('Wainwright Summary'!$E$6,'Inflation-OLD'!$A$6:$B$126,2) -> 0.56657332 | AE94: =IF(ISERROR(AA94*AD94), " ",AA94*AD94 ) -> 273455.53 | AF94: =IF(ISERROR((AC94/AA94)*AE94)," ",(AC94/AA94)*AE94) -> 102545.82 | AG94: =IF(ISERROR(C94+AB94)," ",(C94+AB94)) -> 2023 | AJ94: =AB94 -> 40
B95: 37.5 kVA | C95: 1981 | D95: 18 | E95: ea | F95: 4500 | G95: =IF(ISERROR(F95*D95)," ",F95*D95) -> 81000 | H95: =H$10 -> 0.05 | I95: =I$10 -> 0.02 | J95: =J$10 -> 0.05 | K95: =K$10 -> 0.122 | L95: =L$10 -> 0.1 | M95: =G95*H95 -> 4050 | N95: =(G95+M95)*I95 -> 1701 | O95: =(G95+M95+N95)*J95 -> 4337.55 | P95: =(G95+M95+N95+O95)*K95 -> 11112.803 | Q95: =(G95+M95+N95+O95+P95)*L95 -> 10220.135 | R95: =G95+SUM(M95:Q95) -> 112421.49 | S95: =S$10 -> 0.077 | T95: =T$10 -> 0.05 | U95: 0.03 | V95: =V$10 -> 0.1 | W95: =R95*S95 -> 8656.4546 | X95: =R95*T95 -> 5621.0744 | Y95: =R95*U95 -> 3372.6447 | Z95: =(W95+X95)*V95 -> 1427.7529 | AA95: =R95+SUM(W95:Z95) -> 131499.41 | AB95: 40 | AC95: =IF(ISERROR(IF('Wainwright Summary'!$E$7-C95>AB95,0,(AB95-('Wainwright Summary'!$E$7-C95))/AB95)*G95)," ",(IF('Wainwright Summary'!$E$7-C95>AB95,0,(AB95-('Wainwright Summary'!$E$7-C95))/AB95)*AA95)) -> 42737.31 | AD95: =VLOOKUP(C95,'Inflation-OLD'!$A$6:$B$126,2)/VLOOKUP('Wainwright Summary'!$E$6,'Inflation-OLD'!$A$6:$B$126,2) -> 0.50754841 | AE95: =IF(ISERROR(AA95*AD95), " ",AA95*AD95 ) -> 66742.32 | AF95: =IF(ISERROR((AC95/AA95)*AE95)," ",(AC95/AA95)*AE95) -> 21691.254 | AG95: =IF(ISERROR(C95+AB95)," ",(C95+AB95)) -> 2021 | AJ95: =AB95 -> 40
B96: 50 kVA | C96: 1982 | D96: 69 | E96: ea | F96: 5800 | G96: =IF(ISERROR(F96*D96)," ",F96*D96) -> 400200 | H96: =H$10 -> 0.05 | I96: =I$10 -> 0.02 | J96: =J$10 -> 0.05 | K96: =K$10 -> 0.122 | L96: =L$10 -> 0.1 | M96: =G96*H96 -> 20010 | N96: =(G96+M96)*I96 -> 8404.2 | O96: =(G96+M96+N96)*J96 -> 21430.71 | P96: =(G96+M96+N96+O96)*K96 -> 54905.479 | Q96: =(G96+M96+N96+O96+P96)*L96 -> 50495.039 | R96: =G96+SUM(M96:Q96) -> 555445.43 | S96: =S$10 -> 0.077 | T96: =T$10 -> 0.05 | U96: =U$10 -> 0.05 | V96: =V$10 -> 0.1 | W96: =R96*S96 -> 42769.298 | X96: =R96*T96 -> 27772.271 | Y96: =R96*U96 -> 27772.271 | Z96: =(W96+X96)*V96 -> 7054.1569 | AA96: =R96+SUM(W96:Z96) -> 660813.43 | AB96: 40 | AC96: =IF(ISERROR(IF('Wainwright Summary'!$E$7-C96>AB96,0,(AB96-('Wainwright Summary'!$E$7-C96))/AB96)*G96)," ",(IF('Wainwright Summary'!$E$7-C96>AB96,0,(AB96-('Wainwright Summary'!$E$7-C96))/AB96)*AA96)) -> 231284.7 | AD96: =VLOOKUP(C96,'Inflation-OLD'!$A$6:$B$126,2)/VLOOKUP('Wainwright Summary'!$E$6,'Inflation-OLD'!$A$6:$B$126,2) -> 0.54223993 | AE96: =IF(ISERROR(AA96*AD96), " ",AA96*AD96 ) -> 358319.43 | AF96: =IF(ISERROR((AC96/AA96)*AE96)," ",(AC96/AA96)*AE96) -> 125411.8 | AG96: =IF(ISERROR(C96+AB96)," ",(C96+AB96)) -> 2022 | AJ96: =AB96 -> 40
B97: 75 kVA | C97: 1981 | D97: 26 | E97: ea | F97: 9500 | G97: =IF(ISERROR(F97*D97)," ",F97*D97) -> 247000 | H97: =H$10 -> 0.05 | I97: =I$10 -> 0.02 | J97: =J$10 -> 0.05 | K97: =K$10 -> 0.122 | L97: =L$10 -> 0.1 | M97: =G97*H97 -> 12350 | N97: =(G97+M97)*I97 -> 5187 | O97: =(G97+M97+N97)*J97 -> 13226.85 | P97: =(G97+M97+N97+O97)*K97 -> 33887.19 | Q97: =(G97+M97+N97+O97+P97)*L97 -> 31165.104 | R97: =G97+SUM(M97:Q97) -> 342816.14 | S97: =S$10 -> 0.077 | T97: =T$10 -> 0.05 | U97: =U$10 -> 0.05 | V97: =V$10 -> 0.1 | W97: =R97*S97 -> 26396.843 | X97: =R97*T97 -> 17140.807 | Y97: =R97*U97 -> 17140.807 | Z97: =(W97+X97)*V97 -> 4353.765 | AA97: =R97+SUM(W97:Z97) -> 407848.37 | AB97: 40 | AC97: =IF(ISERROR(IF('Wainwright Summary'!$E$7-C97>AB97,0,(AB97-('Wainwright Summary'!$E$7-C97))/AB97)*G97)," ",(IF('Wainwright Summary'!$E$7-C97>AB97,0,(AB97-('Wainwright Summary'!$E$7-C97))/AB97)*AA97)) -> 132550.72 | AD97: =VLOOKUP(C97,'Inflation-OLD'!$A$6:$B$126,2)/VLOOKUP('Wainwright Summary'!$E$6,'Inflation-OLD'!$A$6:$B$126,2) -> 0.50754841 | AE97: =IF(ISERROR(AA97*AD97), " ",AA97*AD97 ) -> 207002.79 | AF97: =IF(ISERROR((AC97/AA97)*AE97)," ",(AC97/AA97)*AE97) -> 67275.907 | AG97: =IF(ISERROR(C97+AB97)," ",(C97+AB97)) -> 2021 | AJ97: =AB97 -> 40
B98: 100 kVA | C98: 1980 | D98: 12 | E98: ea | F98: 11000 | G98: =IF(ISERROR(F98*D98)," ",F98*D98) -> 132000 | H98: =H$10 -> 0.05 | I98: =I$10 -> 0.02 | J98: =J$10 -> 0.05 | K98: =K$10 -> 0.122 | L98: =L$10 -> 0.1 | M98: =G98*H98 -> 6600 | N98: =(G98+M98)*I98 -> 2772 | O98: =(G98+M98+N98)*J98 -> 7068.6 | P98: =(G98+M98+N98+O98)*K98 -> 18109.753 | Q98: =(G98+M98+N98+O98+P98)*L98 -> 16655.035 | R98: =G98+SUM(M98:Q98) -> 183205.39 | S98: =S$10 -> 0.077 | T98: =T$10 -> 0.05 | U98: =U$10 -> 0.05 | V98: =V$10 -> 0.1 | W98: =R98*S98 -> 14106.815 | X98: =R98*T98 -> 9160.2694 | Y98: =R98*U98 -> 9160.2694 | Z98: =(W98+X98)*V98 -> 2326.7084 | AA98: =R98+SUM(W98:Z98) -> 217959.45 | AB98: 40 | AC98: =IF(ISERROR(IF('Wainwright Summary'!$E$7-C98>AB98,0,(AB98-('Wainwright Summary'!$E$7-C98))/AB98)*G98)," ",(IF('Wainwright Summary'!$E$7-C98>AB98,0,(AB98-('Wainwright Summary'!$E$7-C98))/AB98)*AA98)) -> 65387.835 | AD98: =VLOOKUP(C98,'Inflation-OLD'!$A$6:$B$126,2)/VLOOKUP('Wainwright Summary'!$E$6,'Inflation-OLD'!$A$6:$B$126,2) -> 0.46299201 | AE98: =IF(ISERROR(AA98*AD98), " ",AA98*AD98 ) -> 100913.48 | AF98: =IF(ISERROR((AC98/AA98)*AE98)," ",(AC98/AA98)*AE98) -> 30274.045 | AG98: =IF(ISERROR(C98+AB98)," ",(C98+AB98)) -> 2020 | AJ98: =AB98 -> 40
G99: =IF(ISERROR(F99*D99)," ",F99*D99) | AC99: =IF(ISERROR(IF('Wainwright Summary'!$E$7-C99>AB99,0,(AB99-('Wainwright Summary'!$E$7-C99))/AB99)*G99)," ",(IF('Wainwright Summary'!$E$7-C99>AB99,0,(AB99-('Wainwright Summary'!$E$7-C99))/AB99)*AA99)) | AE99: =IF(ISERROR(D99*F99*AD99), " ",D99*F99*AD99 ) | AF99: =IF(ISERROR((AC99/AA99)*AE99)," ",(AC99/AA99)*AE99) | AG99: =IF(ISERROR(C99+AB99)," ",(C99+AB99)) | AJ99: =AB99
B100: Transformers: Pad-Mount | G100: =IF(ISERROR(F100*D100)," ",F100*D100) | AC100: =IF(ISERROR(IF('Wainwright Summary'!$E$7-C100>AB100,0,(AB100-('Wainwright Summary'!$E$7-C100))/AB100)*G100)," ",(IF('Wainwright Summary'!$E$7-C100>AB100,0,(AB100-('Wainwright Summary'!$E$7-C100))/AB100)*AA100)) | AE100: =IF(ISERROR(D100*F100*AD100), " ",D100*F100*AD100 ) | AF100: =IF(ISERROR((AC100/AA100)*AE100)," ",(AC100/AA100)*AE100) | AG100: =IF(ISERROR(C100+AB100)," ",(C100+AB100)) | AJ100: =AB100
B101: 1P - 15 kVA & Smaller | C101: 1982 | D101: 6 | E101: ea | F101: 2975 | G101: =IF(ISERROR(F101*D101)," ",F101*D101) -> 17850 | H101: =H$10 -> 0.05 | I101: =I$10 -> 0.02 | J101: =J$10 -> 0.05 | K101: =K$10 -> 0.122 | L101: =L$10 -> 0.1 | M101: =G101*H101 -> 892.5 | N101: =(G101+M101)*I101 -> 374.85 | O101: =(G101+M101+N101)*J101 -> 955.8675 | P101: =(G101+M101+N101+O101)*K101 -> 2448.9325 | Q101: =(G101+M101+N101+O101+P101)*L101 -> 2252.215 | R101: =G101+SUM(M101:Q101) -> 24774.365 | S101: =S$10 -> 0.077 | T101: =T$10 -> 0.05 | U101: 0.03 | V101: =V$10 -> 0.1 | W101: =R101*S101 -> 1907.6261 | X101: =R101*T101 -> 1238.7183 | Y101: =R101*U101 -> 743.23095 | Z101: =(W101+X101)*V101 -> 314.63444 | AA101: =R101+SUM(W101:Z101) -> 28978.575 | AB101: 40 | AC101: =IF(ISERROR(IF('Wainwright Summary'!$E$7-C101>AB101,0,(AB101-('Wainwright Summary'!$E$7-C101))/AB101)*G101)," ",(IF('Wainwright Summary'!$E$7-C101>AB101,0,(AB101-('Wainwright Summary'!$E$7-C101))/AB101)*AA101)) -> 10142.501 | AD101: =VLOOKUP(C101,'Inflation-OLD'!$A$6:$B$126,2)/VLOOKUP('Wainwright Summary'!$E$6,'Inflation-OLD'!$A$6:$B$126,2) -> 0.54223993 | AE101: =IF(ISERROR(AA101*AD101), " ",AA101*AD101 ) -> 15713.34 | AF101: =IF(ISERROR((AC101/AA101)*AE101)," ",(AC101/AA101)*AE101) -> 5499.6691 | AG101: =IF(ISERROR(C101+AB101)," ",(C101+AB101)) -> 2022 | AJ101: =AB101 -> 40
B102: 1P - 25 kVA | C102: 1984 | D102: 6 | E102: ea | F102: 3200 | G102: =IF(ISERROR(F102*D102)," ",F102*D102) -> 19200 | H102: =H$10 -> 0.05 | I102: =I$10 -> 0.02 | J102: =J$10 -> 0.05 | K102: =K$10 -> 0.122 | L102: =L$10 -> 0.1 | M102: =G102*H102 -> 960 | N102: =(G102+M102)*I102 -> 403.2 | O102: =(G102+M102+N102)*J102 -> 1028.16 | P102: =(G102+M102+N102+O102)*K102 -> 2634.1459 | Q102: =(G102+M102+N102+O102+P102)*L102 -> 2422.5506 | R102: =G102+SUM(M102:Q102) -> 26648.057 | S102: =S$10 -> 0.077 | T102: =T$10 -> 0.05 | U102: 0.03 | V102: =V$10 -> 0.1 | W102: =R102*S102 -> 2051.9004 | X102: =R102*T102 -> 1332.4028 | Y102: =R102*U102 -> 799.4417 | Z102: =(W102+X102)*V102 -> 338.43032 | AA102: =R102+SUM(W102:Z102) -> 31170.232 | AB102: 40 | AC102: =IF(ISERROR(IF('Wainwright Summary'!$E$7-C102>AB102,0,(AB102-('Wainwright Summary'!$E$7-C102))/AB102)*G102)," ",(IF('Wainwright Summary'!$E$7-C102>AB102,0,(AB102-('Wainwright Summary'!$E$7-C102))/AB102)*AA102)) -> 12468.093 | AD102: =VLOOKUP(C102,'Inflation-OLD'!$A$6:$B$126,2)/VLOOKUP('Wainwright Summary'!$E$6,'Inflation-OLD'!$A$6:$B$126,2) -> 0.58778282 | AE102: =IF(ISERROR(AA102*AD102), " ",AA102*AD102 ) -> 18321.327 | AF102: =IF(ISERROR((AC102/AA102)*AE102)," ",(AC102/AA102)*AE102) -> 7328.5307 | AG102: =IF(ISERROR(C102+AB102)," ",(C102+AB102)) -> 2024 | AJ102: =AB102 -> 40
B103: 1P - 50 kVA | C103: 1982 | D103: 5 | E103: ea | F103: 5800 | G103: =IF(ISERROR(F103*D103)," ",F103*D103) -> 29000 | H103: =H$10 -> 0.05 | I103: =I$10 -> 0.02 | J103: =J$10 -> 0.05 | K103: =K$10 -> 0.122 | L103: =L$10 -> 0.1 | M103: =G103*H103 -> 1450 | N103: =(G103+M103)*I103 -> 609 | O103: =(G103+M103+N103)*J103 -> 1552.95 | P103: =(G103+M103+N103+O103)*K103 -> 3978.6579 | Q103: =(G103+M103+N103+O103+P103)*L103 -> 3659.0608 | R103: =G103+SUM(M103:Q103) -> 40249.669 | S103: =S$10 -> 0.077 | T103: =T$10 -> 0.05 | U103: 0.03 | V103: =V$10 -> 0.1 | W103: =R103*S103 -> 3099.2245 | X103: =R103*T103 -> 2012.4834 | Y103: =R103*U103 -> 1207.4901 | Z103: =(W103+X103)*V103 -> 511.17079 | AA103: =R103+SUM(W103:Z103) -> 47080.037 | AB103: 40 | AC103: =IF(ISERROR(IF('Wainwright Summary'!$E$7-C103>AB103,0,(AB103-('Wainwright Summary'!$E$7-C103))/AB103)*G103)," ",(IF('Wainwright Summary'!$E$7-C103>AB103,0,(AB103-('Wainwright Summary'!$E$7-C103))/AB103)*AA103)) -> 16478.013 | AD103: =VLOOKUP(C103,'Inflation-OLD'!$A$6:$B$126,2)/VLOOKUP('Wainwright Summary'!$E$6,'Inflation-OLD'!$A$6:$B$126,2) -> 0.54223993 | AE103: =IF(ISERROR(AA103*AD103), " ",AA103*AD103 ) -> 25528.676 | AF103: =IF(ISERROR((AC103/AA103)*AE103)," ",(AC103/AA103)*AE103) -> 8935.0367 | AG103: =IF(ISERROR(C103+AB103)," ",(C103+AB103)) -> 2022 | AJ103: =AB103 -> 40
B104: 1P - 100 kVA | C104: 1980 | D104: 3 | E104: ea | F104: 13267 | G104: =IF(ISERROR(F104*D104)," ",F104*D104) -> 39801 | H104: =H$10 -> 0.05 | I104: =I$10 -> 0.02 | J104: =J$10 -> 0.05 | K104: =K$10 -> 0.122 | L104: =L$10 -> 0.1 | M104: =G104*H104 -> 1990.05 | N104: =(G104+M104)*I104 -> 835.821 | O104: =(G104+M104+N104)*J104 -> 2131.3436 | P104: =(G104+M104+N104+O104)*K104 -> 5460.5022 | Q104: =(G104+M104+N104+O104+P104)*L104 -> 5021.8717 | R104: =G104+SUM(M104:Q104) -> 55240.588 | S104: =S$10 -> 0.077 | T104: =T$10 -> 0.05 | U104: 0.03 | V104: =V$10 -> 0.1 | W104: =R104*S104 -> 4253.5253 | X104: =R104*T104 -> 2762.0294 | Y104: =R104*U104 -> 1657.2177 | Z104: =(W104+X104)*V104 -> 701.55547 | AA104: =R104+SUM(W104:Z104) -> 64614.916 | AB104: 40 | AC104: =IF(ISERROR(IF('Wainwright Summary'!$E$7-C104>AB104,0,(AB104-('Wainwright Summary'!$E$7-C104))/AB104)*G104)," ",(IF('Wainwright Summary'!$E$7-C104>AB104,0,(AB104-('Wainwright Summary'!$E$7-C104))/AB104)*AA104)) -> 19384.475 | AD104: =VLOOKUP(C104,'Inflation-OLD'!$A$6:$B$126,2)/VLOOKUP('Wainwright Summary'!$E$6,'Inflation-OLD'!$A$6:$B$126,2) -> 0.46299201 | AE104: =IF(ISERROR(AA104*AD104), " ",AA104*AD104 ) -> 29916.19 | AF104: =IF(ISERROR((AC104/AA104)*AE104)," ",(AC104/AA104)*AE104) -> 8974.857 | AG104: =IF(ISERROR(C104+AB104)," ",(C104+AB104)) -> 2020 | AJ104: =AB104 -> 40
B105: 3P - 112.5 kVA & Smaller | C105: 2003 | D105: 9 | E105: ea | F105: 13600 | G105: =IF(ISERROR(F105*D105)," ",F105*D105) -> 122400 | H105: =H$10 -> 0.05 | I105: =I$10 -> 0.02 | J105: =J$10 -> 0.05 | K105: =K$10 -> 0.122 | L105: =L$10 -> 0.1 | M105: =G105*H105 -> 6120 | N105: =(G105+M105)*I105 -> 2570.4 | O105: =(G105+M105+N105)*J105 -> 6554.52 | P105: =(G105+M105+N105+O105)*K105 -> 16792.68 | Q105: =(G105+M105+N105+O105+P105)*L105 -> 15443.76 | R105: =G105+SUM(M105:Q105) -> 169881.36 | S105: =S$10 -> 0.077 | T105: =T$10 -> 0.05 | U105: =U$10 -> 0.05 | V105: =V$10 -> 0.1 | W105: =R105*S105 -> 13080.865 | X105: =R105*T105 -> 8494.068 | Y105: =R105*U105 -> 8494.068 | Z105: =(W105+X105)*V105 -> 2157.4933 | AA105: =R105+SUM(W105:Z105) -> 202107.85 | AB105: 40 | AC105: =IF(ISERROR(IF('Wainwright Summary'!$E$7-C105>AB105,0,(AB105-('Wainwright Summary'!$E$7-C105))/AB105)*G105)," ",(IF('Wainwright Summary'!$E$7-C105>AB105,0,(AB105-('Wainwright Summary'!$E$7-C105))/AB105)*AA105)) -> 176844.37 | AD105: =VLOOKUP(C105,'Inflation-OLD'!$A$6:$B$126,2)/VLOOKUP('Wainwright Summary'!$E$6,'Inflation-OLD'!$A$6:$B$126,2) -> 0.92384663 | AE105: =IF(ISERROR(AA105*AD105), " ",AA105*AD105 ) -> 186716.66 | AF105: =IF(ISERROR((AC105/AA105)*AE105)," ",(AC105/AA105)*AE105) -> 163377.08 | AG105: =IF(ISERROR(C105+AB105)," ",(C105+AB105)) -> 2043 | AJ105: =AB105 -> 40
B106: 3P - 225 kVA | C106: 1986 | D106: 2 | E106: ea | F106: 17571 | G106: =IF(ISERROR(F106*D106)," ",F106*D106) -> 35142 | H106: =H$10 -> 0.05 | I106: =I$10 -> 0.02 | J106: =J$10 -> 0.05 | K106: =K$10 -> 0.122 | L106: =L$10 -> 0.1 | M106: =G106*H106 -> 1757.1 | N106: =(G106+M106)*I106 -> 737.982 | O106: =(G106+M106+N106)*J106 -> 1881.8541 | P106: =(G106+M106+N106+O106)*K106 -> 4821.3102 | Q106: =(G106+M106+N106+O106+P106)*L106 -> 4434.0246 | R106: =G106+SUM(M106:Q106) -> 48774.271 | S106: =S$10 -> 0.077 | T106: =T$10 -> 0.05 | U106: 0.03 | V106: =V$10 -> 0.1 | W106: =R106*S106 -> 3755.6189 | X106: =R106*T106 -> 2438.7135 | Y106: =R106*U106 -> 1463.2281 | Z106: =(W106+X106)*V106 -> 619.43324 | AA106: =R106+SUM(W106:Z106) -> 57051.265 | AB106: 40 | AC106: =IF(ISERROR(IF('Wainwright Summary'!$E$7-C106>AB106,0,(AB106-('Wainwright Summary'!$E$7-C106))/AB106)*G106)," ",(IF('Wainwright Summary'!$E$7-C106>AB106,0,(AB106-('Wainwright Summary'!$E$7-C106))/AB106)*AA106)) -> 25673.069 | AD106: =VLOOKUP(C106,'Inflation-OLD'!$A$6:$B$126,2)/VLOOKUP('Wainwright Summary'!$E$6,'Inflation-OLD'!$A$6:$B$126,2) -> 0.62132344 | AE106: =IF(ISERROR(AA106*AD106), " ",AA106*AD106 ) -> 35447.288 | AF106: =IF(ISERROR((AC106/AA106)*AE106)," ",(AC106/AA106)*AE106) -> 15951.28 | AG106: =IF(ISERROR(C106+AB106)," ",(C106+AB106)) -> 2026 | AJ106: =AB106 -> 40
...

Sheet Wainwright Elec - R&R Proj
A1: Fort Wainwright Electrical Distribution R&R Projects
A4: Project Number: Year 2
A5: Project Title: Upgrade Water System
A6: Year That Payment for Project Will Begin: Year 2 of the 50 Year Contract
A8: Project Description | B8: Year Implemented | C8: Year Payments Begin | D8: Quantity | E8: Unit of Measure | F8: Cost/UOM | G8: Base Constr Cost (no markups) | H8: Contingency | I8: Bonds, Insurance | J8: General Conditions | K8: G & A | L8: Profit | M8: Total Capital Cost | N8: Studies plus Predesign | O8: Design | P8: SDC | Q8: Fee on Professional Services | R8: Total Project Cost | T8: Engineering | U8: Construction | V8: GM
H9: 0.05 | I9: 0.02 | J9: 0.05 | K9: 0.122 | L9: 0.1 | N9: 0.077 | O9: 0.05 | P9: 0.03 | Q9: 0.1
A11: - | B11: ='Wainwright Summary'!E7 -> 2008 | C11: In Initial Replacements | G11: =SUMIF(Wainwright_All_R_R_Th!$D$11:$BB$11,$B11,Wainwright_All_R_R_Th!$D$12:$BB$12) -> 13310917 | H11: =G11*$H$9 -> 665545.86 | I11: =SUM(G11:H11)*I$9 -> 279529.26 | J11: =SUM(G11:I11)*J$9 -> 712799.61 | K11: =SUM(G11:J11)*K$9 -> 1826192.6 | L11: =SUM(G11:K11)*L$9 -> 1679498.4 | M11: =SUM(G11:L11) -> 18474483 | N11: =M11*N$9 -> 1422535.2 | O11: =M11*O$9 -> 923724.15 | P11: =M11*P$9 -> 554234.49 | Q11: =SUM(N11:P11)*Q$9 -> 290049.38 | R11: =SUM(M11:Q11) -> 21665026 | T11: =SUM(N11:Q11)*$S$69 -> 0 | U11: =M11*$S$69 -> 0 | V11: =(K11+L11+Q11)*S$69 -> 0
A12: - | B12: =B11+1 -> 2009 | C12: In Initial Replacements | G12: =SUMIF(Wainwright_All_R_R_Th!$D$11:$BB$11,$B12,Wainwright_All_R_R_Th!$D$12:$BB$12) -> 7450591.4 | H12: =G12*$H$9 -> 372529.57 | I12: =SUM(G12:H12)*I$9 -> 156462.42 | J12: =SUM(G12:I12)*J$9 -> 398979.17 | K12: =SUM(G12:J12)*K$9 -> 1022184.6 | L12: =SUM(G12:K12)*L$9 -> 940074.71 | M12: =SUM(G12:L12) -> 10340822 | N12: =M12*N$9 -> 796243.28 | O12: =M12*O$9 -> 517041.09 | P12: =M12*P$9 -> 310224.66 | Q12: =SUM(N12:P12)*Q$9 -> 162350.9 | R12: =SUM(M12:Q12) -> 12126682 | T12: =SUM(N12:Q12)*$S$69 -> 0 | U12: =M12*$S$69 -> 0 | V12: =(K12+L12+Q12)*S$69 -> 0
A13: - | B13: =B12+1 -> 2010 | C13: In Initial Replacements | G13: =SUMIF(Wainwright_All_R_R_Th!$D$11:$BB$11,$B13,Wainwright_All_R_R_Th!$D$12:$BB$12) -> 4744000 | H13: =G13*$H$9 -> 237200 | I13: =SUM(G13:H13)*I$9 -> 99624 | J13: =SUM(G13:I13)*J$9 -> 254041.2 | K13: =SUM(G13:J13)*K$9 -> 650853.55 | L13: =SUM(G13:K13)*L$9 -> 598571.88 | M13: =SUM(G13:L13) -> 6584290.6 | N13: =M13*N$9 -> 506990.38 | O13: =M13*O$9 -> 329214.53 | P13: =M13*P$9 -> 197528.72 | Q13: =SUM(N13:P13)*Q$9 -> 103373.36 | R13: =SUM(M13:Q13) -> 7721397.6 | T13: =SUM(N13:Q13)*$S$69 -> 0 | U13: =M13*$S$69 -> 0 | V13: =(K13+L13+Q13)*S$69 -> 0
A14: - | B14: =B13+1 -> 2011 | C14: In Initial Replacements | G14: =SUMIF(Wainwright_All_R_R_Th!$D$11:$BB$11,$B14,Wainwright_All_R_R_Th!$D$12:$BB$12) -> 102468 | H14: =G14*$H$9 -> 5123.4 | I14: =SUM(G14:H14)*I$9 -> 2151.828 | J14: =SUM(G14:I14)*J$9 -> 5487.1614 | K14: =SUM(G14:J14)*K$9 -> 14058.108 | L14: =SUM(G14:K14)*L$9 -> 12928.85 | M14: =SUM(G14:L14) -> 142217.35 | N14: =M14*N$9 -> 10950.736 | O14: =M14*O$9 -> 7110.8673 | P14: =M14*P$9 -> 4266.5204 | Q14: =SUM(N14:P14)*Q$9 -> 2232.8123 | R14: =SUM(M14:Q14) -> 166778.28
A15: - | B15: =B14+1 -> 2012 | C15: In Initial Replacements | G15: =SUMIF(Wainwright_All_R_R_Th!$D$11:$BB$11,$B15,Wainwright_All_R_R_Th!$D$12:$BB$12) -> 0 | H15: =G15*$H$9 -> 0 | I15: =SUM(G15:H15)*I$9 -> 0 | J15: =SUM(G15:I15)*J$9 -> 0 | K15: =SUM(G15:J15)*K$9 -> 0 | L15: =SUM(G15:K15)*L$9 -> 0 | M15: =SUM(G15:L15) -> 0 | N15: =M15*N$9 -> 0 | O15: =M15*O$9 -> 0 | P15: =M15*P$9 -> 0 | Q15: =SUM(N15:P15)*Q$9 -> 0 | R15: =SUM(M15:Q15) -> 0
B16: =B15+1 -> 2013 | C16: =B16+1 -> 2014 | G16: =SUMIF(Wainwright_All_R_R_Th!$D$11:$BB$11,$B16,Wainwright_All_R_R_Th!$D$12:$BB$12) -> 508992 | H16: =G16*$H$9 -> 25449.6 | I16: =SUM(G16:H16)*I$9 -> 10688.832 | J16: =SUM(G16:I16)*J$9 -> 27256.522 | K16: =SUM(G16:J16)*K$9 -> 69831.208 | L16: =SUM(G16:K16)*L$9 -> 64221.816 | M16: =SUM(G16:L16) -> 706439.98 | N16: =M16*N$9 -> 54395.878 | O16: =M16*O$9 -> 35321.999 | P16: =M16*P$9 -> 21193.199 | Q16: =SUM(N16:P16)*Q$9 -> 11091.108 | R16: =SUM(M16:Q16) -> 828442.16
B17: =B16+1 -> 2014 | C17: =B17+1 -> 2015 | G17: =SUMIF(Wainwright_All_R_R_Th!$D$11:$BB$11,$B17,Wainwright_All_R_R_Th!$D$12:$BB$12) -> 175710 | H17: =G17*$H$9 -> 8785.5 | I17: =SUM(G17:H17)*I$9 -> 3689.91 | J17: =SUM(G17:I17)*J$9 -> 9409.2705 | K17: =SUM(G17:J17)*K$9 -> 24106.551 | L17: =SUM(G17:K17)*L$9 -> 22170.123 | M17: =SUM(G17:L17) -> 243871.35 | N17: =M17*N$9 -> 18778.094 | O17: =M17*O$9 -> 12193.568 | P17: =M17*P$9 -> 7316.1406 | Q17: =SUM(N17:P17)*Q$9 -> 3828.7803 | R17: =SUM(M17:Q17) -> 285987.94
B18: =B17+1 -> 2015 | C18: =B18+1 -> 2016 | G18: =SUMIF(Wainwright_All_R_R_Th!$D$11:$BB$11,$B18,Wainwright_All_R_R_Th!$D$12:$BB$12) -> 0 | H18: =G18*$H$9 -> 0 | I18: =SUM(G18:H18)*I$9 -> 0 | J18: =SUM(G18:I18)*J$9 -> 0 | K18: =SUM(G18:J18)*K$9 -> 0 | L18: =SUM(G18:K18)*L$9 -> 0 | M18: =SUM(G18:L18) -> 0 | N18: =M18*N$9 -> 0 | O18: =M18*O$9 -> 0 | P18: =M18*P$9 -> 0 | Q18: =SUM(N18:P18)*Q$9 -> 0 | R18: =SUM(M18:Q18) -> 0
B19: =B18+1 -> 2016 | C19: =B19+1 -> 2017 | G19: =SUMIF(Wainwright_All_R_R_Th!$D$11:$BB$11,$B19,Wainwright_All_R_R_Th!$D$12:$BB$12) -> 0 | H19: =G19*$H$9 -> 0 | I19: =SUM(G19:H19)*I$9 -> 0 | J19: =SUM(G19:I19)*J$9 -> 0 | K19: =SUM(G19:J19)*K$9 -> 0 | L19: =SUM(G19:K19)*L$9 -> 0 | M19: =SUM(G19:L19) -> 0 | N19: =M19*N$9 -> 0 | O19: =M19*O$9 -> 0 | P19: =M19*P$9 -> 0 | Q19: =SUM(N19:P19)*Q$9 -> 0 | R19: =SUM(M19:Q19) -> 0
B20: =B19+1 -> 2017 | C20: =B20+1 -> 2018 | G20: =SUMIF(Wainwright_All_R_R_Th!$D$11:$BB$11,$B20,Wainwright_All_R_R_Th!$D$12:$BB$12) -> 0 | H20: =G20*$H$9 -> 0 | I20: =SUM(G20:H20)*I$9 -> 0 | J20: =SUM(G20:I20)*J$9 -> 0 | K20: =SUM(G20:J20)*K$9 -> 0 | L20: =SUM(G20:K20)*L$9 -> 0 | M20: =SUM(G20:L20) -> 0 | N20: =M20*N$9 -> 0 | O20: =M20*O$9 -> 0 | P20: =M20*P$9 -> 0 | Q20: =SUM(N20:P20)*Q$9 -> 0 | R20: =SUM(M20:Q20) -> 0
B21: =B20+1 -> 2018 | C21: =B21+1 -> 2019 | G21: =SUMIF(Wainwright_All_R_R_Th!$D$11:$BB$11,$B21,Wainwright_All_R_R_Th!$D$12:$BB$12) -> 953924 | H21: =G21*$H$9 -> 47696.2 | I21: =SUM(G21:H21)*I$9 -> 20032.404 | J21: =SUM(G21:I21)*J$9 -> 51082.63 | K21: =SUM(G21:J21)*K$9 -> 130873.7 | L21: =SUM(G21:K21)*L$9 -> 120360.89 | M21: =SUM(G21:L21) -> 1323969.8 | N21: =M21*N$9 -> 101945.68 | O21: =M21*O$9 -> 66198.491 | P21: =M21*P$9 -> 39719.095 | Q21: =SUM(N21:P21)*Q$9 -> 20786.326 | R21: =SUM(M21:Q21) -> 1552619.4
B22: =B21+1 -> 2019 | C22: =B22+1 -> 2020 | G22: =SUMIF(Wainwright_All_R_R_Th!$D$11:$BB$11,$B22,Wainwright_All_R_R_Th!$D$12:$BB$12) -> 1672600 | H22: =G22*$H$9 -> 83630 | I22: =SUM(G22:H22)*I$9 -> 35124.6 | J22: =SUM(G22:I22)*J$9 -> 89567.73 | K22: =SUM(G22:J22)*K$9 -> 229472.52 | L22: =SUM(G22:K22)*L$9 -> 211039.49 | M22: =SUM(G22:L22) -> 2321434.3 | N22: =M22*N$9 -> 178750.44 | O22: =M22*O$9 -> 116071.72 | P22: =M22*P$9 -> 69643.03 | Q22: =SUM(N22:P22)*Q$9 -> 36446.519 | R22: =SUM(M22:Q22) -> 2722346.1
B23: =B22+1 -> 2020 | C23: =B23+1 -> 2021 | G23: =SUMIF(Wainwright_All_R_R_Th!$D$11:$BB$11,$B23,Wainwright_All_R_R_Th!$D$12:$BB$12) -> 1233831 | H23: =G23*$H$9 -> 61691.55 | I23: =SUM(G23:H23)*I$9 -> 25910.451 | J23: =SUM(G23:I23)*J$9 -> 66071.65 | K23: =SUM(G23:J23)*K$9 -> 169275.57 | L23: =SUM(G23:K23)*L$9 -> 155678.02 | M23: =SUM(G23:L23) -> 1712458.2 | N23: =M23*N$9 -> 131859.28 | O23: =M23*O$9 -> 85622.912 | P23: =M23*P$9 -> 51373.747 | Q23: =SUM(N23:P23)*Q$9 -> 26885.594 | R23: =SUM(M23:Q23) -> 2008199.8
B24: =B23+1 -> 2021 | C24: =B24+1 -> 2022 | G24: =SUMIF(Wainwright_All_R_R_Th!$D$11:$BB$11,$B24,Wainwright_All_R_R_Th!$D$12:$BB$12) -> 424307.2 | H24: =G24*$H$9 -> 21215.36 | I24: =SUM(G24:H24)*I$9 -> 8910.4512 | J24: =SUM(G24:I24)*J$9 -> 22721.651 | K24: =SUM(G24:J24)*K$9 -> 58212.869 | L24: =SUM(G24:K24)*L$9 -> 53536.753 | M24: =SUM(G24:L24) -> 588904.28 | N24: =M24*N$9 -> 45345.63 | O24: =M24*O$9 -> 29445.214 | P24: =M24*P$9 -> 17667.129 | Q24: =SUM(N24:P24)*Q$9 -> 9245.7973 | R24: =SUM(M24:Q24) -> 690608.05
B25: =B24+1 -> 2022 | C25: =B25+1 -> 2023 | G25: =SUMIF(Wainwright_All_R_R_Th!$D$11:$BB$11,$B25,Wainwright_All_R_R_Th!$D$12:$BB$12) -> 901738 | H25: =G25*$H$9 -> 45086.9 | I25: =SUM(G25:H25)*I$9 -> 18936.498 | J25: =SUM(G25:I25)*J$9 -> 48288.07 | K25: =SUM(G25:J25)*K$9 -> 123714.04 | L25: =SUM(G25:K25)*L$9 -> 113776.35 | M25: =SUM(G25:L25) -> 1251539.9 | N25: =M25*N$9 -> 96368.569 | O25: =M25*O$9 -> 62576.993 | P25: =M25*P$9 -> 37546.196 | Q25: =SUM(N25:P25)*Q$9 -> 19649.176 | R25: =SUM(M25:Q25) -> 1467680.8
B26: =B25+1 -> 2023 | C26: =B26+1 -> 2024 | G26: =SUMIF(Wainwright_All_R_R_Th!$D$11:$BB$11,$B26,Wainwright_All_R_R_Th!$D$12:$BB$12) -> 292300 | H26: =G26*$H$9 -> 14615 | I26: =SUM(G26:H26)*I$9 -> 6138.3 | J26: =SUM(G26:I26)*J$9 -> 15652.665 | K26: =SUM(G26:J26)*K$9 -> 40102.128 | L26: =SUM(G26:K26)*L$9 -> 36880.809 | M26: =SUM(G26:L26) -> 405688.9 | N26: =M26*N$9 -> 31238.045 | O26: =M26*O$9 -> 20284.445 | P26: =M26*P$9 -> 12170.667 | Q26: =SUM(N26:P26)*Q$9 -> 6369.3158 | R26: =SUM(M26:Q26) -> 475751.38
B27: =B26+1 -> 2024 | C27: =B27+1 -> 2025 | G27: =SUMIF(Wainwright_All_R_R_Th!$D$11:$BB$11,$B27,Wainwright_All_R_R_Th!$D$12:$BB$12) -> 19200 | H27: =G27*$H$9 -> 960 | I27: =SUM(G27:H27)*I$9 -> 403.2 | J27: =SUM(G27:I27)*J$9 -> 1028.16 | K27: =SUM(G27:J27)*K$9 -> 2634.1459 | L27: =SUM(G27:K27)*L$9 -> 2422.5506 | M27: =SUM(G27:L27) -> 26648.057 | N27: =M27*N$9 -> 2051.9004 | O27: =M27*O$9 -> 1332.4028 | P27: =M27*P$9 -> 799.4417 | Q27: =SUM(N27:P27)*Q$9 -> 418.37449 | R27: =SUM(M27:Q27) -> 31250.176
... B61: =B60+1 -> 2058 | C61: =B61+1 -> 2059 | G61: =SUMIF(Wainwright_All_R_R_Th!$D$11:$BB$11,$B61,Wainwright_All_R_R_Th!$D$12:$BB$12) -> 108240 | H61: =G61*$H$9 -> 5412 | I61: =SUM(G61:H61)*I$9 -> 2273.04 | J61: =SUM(G61:I61)*J$9 -> 5796.252 | K61: =SUM(G61:J61)*K$9 -> 14849.998 | L61: =SUM(G61:K61)*L$9 -> 13657.129 | M61: =SUM(G61:L61) -> 150228.42 | N61: =M61*N$9 -> 11567.588 | O61: =M61*O$9 -> 7511.4209 | P61: =M61*P$9 -> 4506.8526 | Q61: =SUM(N61:P61)*Q$9 -> 2358.5862 | R61: =SUM(M61:Q61) -> 176172.87
H62: =G62*$H$9 -> 0 | I62: =SUM(G62:H62)*I$9 -> 0 | J62: =SUM(G62:I62)*J$9 -> 0 | K62: =SUM(G62:J62)*K$9 -> 0 | L62: =SUM(G62:K62)*L$9 -> 0 | M62: =SUM(G62:L62) -> 0 | N62: =M62*N$9 -> 0 | O62: =M62*O$9 -> 0 | P62: =M62*P$9 -> 0 | Q62: =SUM(N62:P62)*Q$9 -> 0 | R62: =SUM(M62:Q62) -> 0 | T62: =SUM(N62:Q62)*$S$69 -> 0 | U62: =M62*$S$69 -> 0 | V62: =(K62+L62+Q62)*S$69 -> 0
A64: Summary Water Distribution | G64: =SUM(G11:G62) -> 39013448 | H64: =SUM(H11:H62) -> 1950672.4 | I64: =SUM(I11:I62) -> 819282.4 | J64: =SUM(J11:J62) -> 2089170.1 | K64: =SUM(K11:K62) -> 5352453.9 | L64: =SUM(L11:L62) -> 4922502.7 | M64: =SUM(M11:M62) -> 54147529 | N64: =SUM(N11:N62) -> 4169359.8 | ... R64: =SUM(R11:R62) -> 63498808

Sheet Wainwright Water Dist
B4: Doyon Utilities, LLC
B5: Forts Wainwright Utility Inventory and Replacement Cost
B6: Fort Wainwright Potable Water Distribution System
A8: Asset Type X= linear | B8: Item | C8: Year Inst | D8: Quantity | F8: Unit Cost | G8: RCN | H8: Contractors Mark-ups % | M8: Contractors Mark-ups $ | R8: RCN (Total Installed) | S8: Engineering Services % | W8: Engineering Services $'s | AA8: RCN (Total w. Enginering) | AB8: Design Life | AC8: RCNLD | AD8: Historical Inflation Index | AE8: OC | AF8: OCLD | AG8: RYN (Repl Year New) | AH8: Source | AI8: Notes | AJ8: RDL Repl. Design Life | AK8: MMC Major Maintenance Cost | AL8: MMY Major Maintenance Start Year | AM8: MMD Major Maintenance Program Duration (yrs) | AN8: Comments | AO8: Condition Rating (Poor, Fair, Good) | AP8: Condition Rating Comments | AR8: 2005$ Unit cost etsimates | AS8: inflator to 2008$ | AT8: 2008$ Unitcost estimate
H9: Contingency | I9: Bonds & Insurance | J9: General Conditions | K9: Contractors G&A | L9: Contractors Profit | M9: Contingency | N9: Bonds & Insurance | O9: General Conditions | P9: Contractors G&A | Q9: Contractors Profit | S9: Studies & Pre-Design | T9: Design | U9: Services During Construction (3%) & Commissioning (2%) | V9: Fee's on Studies & Design | W9: Studies & Pre-Design | X9: Design | Y9: Services During Construction | Z9: Fee's on Studies & Design | AS9: 1
H10: 0.05 | I10: 0.02 | J10: 0.05 | K10: 0.122 | L10: 0.1 | S10: 0.077 | T10: 0.05 | U10: 0.05 | V10: 0.1
B11: NON-PIPING ITEMS
B13: WATER SOURCES
B14: Building 3559 | C14: 1988 | D14: 1 | E14: ea | F14: =AT14 -> 60000 | G14: =IF(ISERROR(F14*D14)," ",F14*D14) -> 60000 | M14: =G14*H14 -> 0 | N14: =(G14+M14)*I14 -> 0 | O14: =(G14+M14+N14)*J14 -> 0 | P14: =(G14+M14+N14+O14)*K14 -> 0 | Q14: =(G14+M14+N14+O14+P14)*L14 -> 0 | R14: =G14+SUM(M14:Q14) -> 60000 | T14: =T$10 -> 0.05 | U14: 0.03 | V14: =V$10 -> 0.1 | W14: =R14*S14 -> 0 | X14: =R14*T14 -> 3000 | Y14: =R14*U14 -> 1800 | Z14: =(W14+X14)*V14 -> 300 | AA14: =R14+SUM(W14:Z14) -> 65100 | AB14: 75 | AC14: =IF(ISERROR(IF('Wainwright Summary'!$E$7-C14>AB14,0,(AB14-('Wainwright Summary'!$E$7-C14))/AB14)*G14)," ",(IF('Wainwright Summary'!$E$7-C14>AB14,0,(AB14-('Wainwright Summary'!$E$7-C14))/AB14)*G14)) -> 44000 | AD14: =VLOOKUP(C14,'Inflation-OLD'!$A$6:$B$126,2)/VLOOKUP('Wainwright Summary'!$E$6,'Inflation-OLD'!$A$6:$B$126,2) -> 0.65831676 | AE14: =IF(ISERROR(AA14*AD14), " ",AA14*AD14 ) -> 42856.421 | AF14: =IF(ISERROR((AC14/G14)*AE14)," ",(AC14/G14)*AE14) -> 31428.042 | AG14: =IF(ISERROR(C14+AB14)," ",(C14+AB14)) -> 2063 | AJ14: =AB14 -> 75 | AN14: One of 2 primary main water supply wells. | AR14: 60000 | AS14: =$AS$9 -> 1 | AT14: =AR14*AS14 -> 60000
B15: Building 3559 Well #1 - 55.8-ft depth, 12-in dia. | C15: 1988 | D15: 1 | E15: ea | F15: 7000 | G15: =IF(ISERROR(F15*D15)," ",F15*D15) -> 7000 | H15: 0 | I15: 0 | J15: 0 | K15: 0 | L15: 0 | M15: =G15*H15 -> 0 | N15: =(G15+M15)*I15 -> 0 | O15: =(G15+M15+N15)*J15 -> 0 | P15: =(G15+M15+N15+O15)*K15 -> 0 | Q15: =(G15+M15+N15+O15+P15)*L15 -> 0 | R15: =G15+SUM(M15:Q15) -> 7000 | T15: =T$10 -> 0.05 | U15: 0.03 | V15: =V$10 -> 0.1 | W15: =R15*S15 -> 0 | X15: =R15*T15 -> 350 | Y15: =R15*U15 -> 210 | Z15: =(W15+X15)*V15 -> 35 | AA15: =R15+SUM(W15:Z15) -> 7595 | AB15: 50 | AC15: =IF(ISERROR(IF('Wainwright Summary'!$E$7-C15>AB15,0,(AB15-('Wainwright Summary'!$E$7-C15))/AB15)*G15)," ",(IF('Wainwright Summary'!$E$7-C15>AB15,0,(AB15-('Wainwright Summary'!$E$7-C15))/AB15)*G15)) -> 4200 | AD15: =VLOOKUP(C15,'Inflation-OLD'!$A$6:$B$126,2)/VLOOKUP('Wainwright Summary'!$E$6,'Inflation-OLD'!$A$6:$B$126,2) -> 0.65831676 | AE15: =IF(ISERROR(AA15*AD15), " ",AA15*AD15 ) -> 4999.9158 | AF15: =IF(ISERROR((AC15/G15)*AE15)," ",(AC15/G15)*AE15) -> 2999.9495 | AG15: 2060 | AJ15: =AB15 -> 50 | AK15: =ROUND(0.5*AA15,-2) -> 3800 | AL15: 2038 | AM15: 1 | AN15: Unknown if building, telemetry, controls, etc. | AR15: 15000 | AS15: =$AS$9 -> 1 | AT15: =AR15*AS15 -> 15000
B16: Building 3559 Well #1 Pump & Motor - 2200-gpm VFD | C16: 1988 | D16: 1 | E16: ea | F16: =AT16 -> 25000 | G16: =IF(ISERROR(F16*D16)," ",F16*D16) -> 25000 | H16: 0 | I16: 0 | J16: 0 | K16: 0 | L16: 0 | M16: =G16*H16 -> 0 | N16: =(G16+M16)*I16 -> 0 | O16: =(G16+M16+N16)*J16 -> 0 | P16: =(G16+M16+N16+O16)*K16 -> 0 | Q16: =(G16+M16+N16+O16+P16)*L16 -> 0 | R16: =G16+SUM(M16:Q16) -> 25000 | T16: =T$10 -> 0.05 | U16: 0.03 | V16: =V$10 -> 0.1 | W16: =R16*S16 -> 0 | X16: =R16*T16 -> 1250 | Y16: =R16*U16 -> 750 | Z16: =(W16+X16)*V16 -> 125 | AA16: =R16+SUM(W16:Z16) -> 27125 | AB16: 25 | AC16: =IF(ISERROR(IF('Wainwright Summary'!$E$7-C16>AB16,0,(AB16-('Wainwright Summary'!$E$7-C16))/AB16)*G16)," ",(IF('Wainwright Summary'!$E$7-C16>AB16,0,(AB16-('Wainwright Summary'!$E$7-C16))/AB16)*G16)) -> 5000 | AD16: =VLOOKUP(C16,'Inflation-OLD'!$A$6:$B$126,2)/VLOOKUP('Wainwright Summary'!$E$6,'Inflation-OLD'!$A$6:$B$126,2) -> 0.65831676 | AE16: =IF(ISERROR(AA16*AD16), " ",AA16*AD16 ) -> 17856.842 | AF16: =IF(ISERROR((AC16/G16)*AE16)," ",(AC16/G16)*AE16) -> 3571.3684 | AG16: =IF(ISERROR(C16+AB16)," ",(C16+AB16)) -> 2013 | AJ16: =AB16 -> 25 | AN16: In Initial R&R. hp unknown | AR16: 25000 | AS16: =$AS$9 -> 1 | AT16: =AR16*AS16 -> 25000
B18: Building 3559 Well #2 - 55.8-ft depth, 12-in dia. | C18: 1988 | D18: 1 | E18: ea | F18: 7000 | G18: =IF(ISERROR(F18*D18)," ",F18*D18) -> 7000 | H18: 0 | I18: 0 | J18: 0 | K18: 0 | L18: 0 | M18: =G18*H18 -> 0 | N18: =(G18+M18)*I18 -> 0 | O18: =(G18+M18+N18)*J18 -> 0 | P18: =(G18+M18+N18+O18)*K18 -> 0 | Q18: =(G18+M18+N18+O18+P18)*L18 -> 0 | R18: =G18+SUM(M18:Q18) -> 7000 | T18: =T$10 -> 0.05 | U18: 0.03 | V18: =V$10 -> 0.1 | W18: =R18*S18 -> 0 | X18: =R18*T18 -> 350 | Y18: =R18*U18 -> 210 | Z18: =(W18+X18)*V18 -> 35 | AA18: =R18+SUM(W18:Z18) -> 7595 | AB18: 50 | AC18: =IF(ISERROR(IF('Wainwright Summary'!$E$7-C18>AB18,0,(AB18-('Wainwright Summary'!$E$7-C18))/AB18)*G18)," ",(IF('Wainwright Summary'!$E$7-C18>AB18,0,(AB18-('Wainwright Summary'!$E$7-C18))/AB18)*G18)) -> 4200 | AD18: =VLOOKUP(C18,'Inflation-OLD'!$A$6:$B$126,2)/VLOOKUP('Wainwright Summary'!$E$6,'Inflation-OLD'!$A$6:$B$126,2) -> 0.65831676 | AE18: =IF(ISERROR(AA18*AD18), " ",AA18*AD18 ) -> 4999.9158 | AF18: =IF(ISERROR((AC18/G18)*AE18)," ",(AC18/G18)*AE18) -> 2999.9495 | AG18: 2060 | AJ18: =AB18 -> 50 | AK18: =ROUND(0.5*AA18,-2) -> 3800 | AL18: 2038 | AM18: 1 | AN18: Unknown if building, telemetry, controls, etc. | AR18: 15000 | AS18: =$AS$9 -> 1 | AT18: =AR18*AS18 -> 15000
B19: Building 3559 Well #2 Pump & Motor - 2200-gpm VFD | C19: 1988 | D19: 1 | E19: ea | F19: =AT19 -> 25000 | G19: =IF(ISERROR(F19*D19)," ",F19*D19) -> 25000 | H19: 0 | I19: 0 | J19: 0 | K19: 0 | L19: 0 | M19: =G19*H19 -> 0 | N19: =(G19+M19)*I19 -> 0 | O19: =(G19+M19+N19)*J19 -> 0 | P19: =(G19+M19+N19+O19)*K19 -> 0 | Q19: =(G19+M19+N19+O19+P19)*L19 -> 0 | R19: =G19+SUM(M19:Q19) -> 25000 | T19: =T$10 -> 0.05 | U19: 0.03 | V19: =V$10 -> 0.1 | W19: =R19*S19 -> 0 | X19: =R19*T19 -> 1250 | Y19: =R19*U19 -> 750 | Z19: =(W19+X19)*V19 -> 125 | AA19: =R19+SUM(W19:Z19) -> 27125 | AB19: 25 | AC19: =IF(ISERROR(IF('Wainwright Summary'!$E$7-C19>AB19,0,(AB19-('Wainwright Summary'!$E$7-C19))/AB19)*G19)," ",(IF('Wainwright Summary'!$E$7-C19>AB19,0,(AB19-('Wainwright Summary'!$E$7-C19))/AB19)*G19)) -> 5000 | AD19: =VLOOKUP(C19,'Inflation-OLD'!$A$6:$B$126,2)/VLOOKUP('Wainwright Summary'!$E$6,'Inflation-OLD'!$A$6:$B$126,2) -> 0.65831676 | AE19: =IF(ISERROR(AA19*AD19), " ",AA19*AD19 ) -> 17856.842 | AF19: =IF(ISERROR((AC19/G19)*AE19)," ",(AC19/G19)*AE19) -> 3571.3684 | AG19: =IF(ISERROR(C19+AB19)," ",(C19+AB19)) -> 2013 | AJ19: =AB19 -> 25 | AN19: In Initial R&R. hp unknown | AR19: 25000 | AS19: =$AS$9 -> 1 | AT19: =AR19*AS19 -> 25000
B21: Building 3563 | C21: 1953 | D21: 1 | E21: ea | F21: =AT21 -> 60000 | G21: =IF(ISERROR(F21*D21)," ",F21*D21) -> 60000 | M21: =G21*H21 -> 0 | N21: =(G21+M21)*I21 -> 0 | O21: =(G21+M21+N21)*J21 -> 0 | P21: =(G21+M21+N21+O21)*K21 -> 0 | Q21: =(G21+M21+N21+O21+P21)*L21 -> 0 | R21: =G21+SUM(M21:Q21) -> 60000 | T21: =T$10 -> 0.05 | U21: 0.03 | V21: =V$10 -> 0.1 | W21: =R21*S21 -> 0 | X21: =R21*T21 -> 3000 | Y21: =R21*U21 -> 1800 | Z21: =(W21+X21)*V21 -> 300 | AA21: =R21+SUM(W21:Z21) -> 65100 | AB21: 75 | AC21: =IF(ISERROR(IF('Wainwright Summary'!$E$7-C21>AB21,0,(AB21-('Wainwright Summary'!$E$7-C21))/AB21)*G21)," ",(IF('Wainwright Summary'!$E$7-C21>AB21,0,(AB21-('Wainwright Summary'!$E$7-C21))/AB21)*G21)) -> 16000 | AD21: =VLOOKUP(C21,'Inflation-OLD'!$A$6:$B$126,2)/VLOOKUP('Wainwright Summary'!$E$6,'Inflation-OLD'!$A$6:$B$126,2) -> 0.15956454 | AE21: =IF(ISERROR(AA21*AD21), " ",AA21*AD21 ) -> 10387.652 | AF21: =IF(ISERROR((AC21/G21)*AE21)," ",(AC21/G21)*AE21) -> 2770.0404 | AG21: 2060 | AJ21: =AB21 -> 75 | AK21: 10000 | AL21: 2028 | AM21: 1 | AN21: One of 2 back-up primary water supply wells. | AR21: 60000 | AS21: =$AS$9 -> 1 | AT21: =AR21*AS21 -> 60000
B22: Building 3563 Well - 109-ft depth, 12-in dia. | C22: 1953 | D22: 1 | E22: ea | F22: =AT22 -> 15000 | G22: =IF(ISERROR(F22*D22)," ",F22*D22) -> 15000 | H22: 0 | I22: 0 | J22: 0 | K22: 0 | L22: 0 | M22: =G22*H22 -> 0 | N22: =(G22+M22)*I22 -> 0 | O22: =(G22+M22+N22)*J22 -> 0 | P22: =(G22+M22+N22+O22)*K22 -> 0 | Q22: =(G22+M22+N22+O22+P22)*L22 -> 0 | R22: =G22+SUM(M22:Q22) -> 15000 | T22: =T$10 -> 0.05 | U22: 0.03 | V22: =V$10 -> 0.1 | W22: =R22*S22 -> 0 | X22: =R22*T22 -> 750 | Y22: =R22*U22 -> 450 | Z22: =(W22+X22)*V22 -> 75 | AA22: =R22+SUM(W22:Z22) -> 16275 | AB22: 50 | AC22: =IF(ISERROR(IF('Wainwright Summary'!$E$7-C22>AB22,0,(AB22-('Wainwright Summary'!$E$7-C22))/AB22)*G22)," ",(IF('Wainwright Summary'!$E$7-C22>AB22,0,(AB22-('Wainwright Summary'!$E$7-C22))/AB22)*G22)) -> 0 | AD22: =VLOOKUP(C22,'Inflation-OLD'!$A$6:$B$126,2)/VLOOKUP('Wainwright Summary'!$E$6,'Inflation-OLD'!$A$6:$B$126,2) -> 0.15956454 | AE22: =IF(ISERROR(AA22*AD22), " ",AA22*AD22 ) -> 2596.9129 | AF22: =IF(ISERROR((AC22/G22)*AE22)," ",(AC22/G22)*AE22) -> 0 | AG22: 2060 | AJ22: =AB22 -> 50 | AK22: =ROUND(0.5*AA22,-2) -> 8100 | AL22: 2009 | AM22: 1 | AN22: In Initial R&R. Unknown if building, telemetry, controls, etc. | AR22: 15000 | AS22: =$AS$9 -> 1 | AT22: =AR22*AS22 -> 15000
B23: Building 3563 Well Pump & Motor - 1000-gpm | C23: 1953 | D23: 1 | E23: ea | F23: =AT23 -> 15000 | G23: =IF(ISERROR(F23*D23)," ",F23*D23) -> 15000 | H23: 0 | I23: 0 | J23: 0 | K23: 0 | L23: 0 | M23: =G23*H23 -> 0 | N23: =(G23+M23)*I23 -> 0 | O23: =(G23+M23+N23)*J23 -> 0 | P23: =(G23+M23+N23+O23)*K23 -> 0 | Q23: =(G23+M23+N23+O23+P23)*L23 -> 0 | R23: =G23+SUM(M23:Q23) -> 15000 | T23: =T$10 -> 0.05 | U23: 0.03 | V23: =V$10 -> 0.1 | W23: =R23*S23 -> 0 | X23: =R23*T23 -> 750 | Y23: =R23*U23 -> 450 | Z23: =(W23+X23)*V23 -> 75 | AA23: =R23+SUM(W23:Z23) -> 16275 | AB23: 25 | AC23: =IF(ISERROR(IF('Wainwright Summary'!$E$7-C23>AB23,0,(AB23-('Wainwright Summary'!$E$7-C23))/AB23)*G23)," ",(IF('Wainwright Summary'!$E$7-C23>AB23,0,(AB23-('Wainwright Summary'!$E$7-C23))/AB23)*G23)) -> 0 | AD23: =VLOOKUP(C23,'Inflation-OLD'!$A$6:$B$126,2)/VLOOKUP('Wainwright Summary'!$E$6,'Inflation-OLD'!$A$6:$B$126,2) -> 0.15956454 | AE23: =IF(ISERROR(AA23*AD23), " ",AA23*AD23 ) -> 2596.9129 | AF23: =IF(ISERROR((AC23/G23)*AE23)," ",(AC23/G23)*AE23) -> 0 | AG23: 2009 | AJ23: =AB23 -> 25 | AN23: In Initial R&R. hp unknown | AR23: 15000 | AS23: =$AS$9 -> 1 | AT23: =AR23*AS23 -> 15000
B24: Building 3563 Emergency Generator - 220 hp | C24: 1995 | D24: 1 | E24: ea | F24: =AT24 -> 55000 | G24: =IF(ISERROR(F24*D24)," ",F24*D24) -> 55000 | H24: 0 | I24: 0 | J24: 0 | K24: 0 | L24: 0 | M24: =G24*H24 -> 0 | N24: =(G24+M24)*I24 -> 0 | O24: =(G24+M24+N24)*J24 -> 0 | P24: =(G24+M24+N24+O24)*K24 -> 0 | Q24: =(G24+M24+N24+O24+P24)*L24 -> 0 | R24: =G24+SUM(M24:Q24) -> 55000 | T24: =T$10 -> 0.05 | U24: 0.03 | V24: =V$10 -> 0.1 | W24: =R24*S24 -> 0 | X24: =R24*T24 -> 2750 | Y24: =R24*U24 -> 1650 | Z24: =(W24+X24)*V24 -> 275 | AA24: =R24+SUM(W24:Z24) -> 59675 | AB24: 35 | AC24: =IF(ISERROR(IF('Wainwright Summary'!$E$7-C24>AB24,0,(AB24-('Wainwright Summary'!$E$7-C24))/AB24)*G24)," ",(IF('Wainwright Summary'!$E$7-C24>AB24,0,(AB24-('Wainwright Summary'!$E$7-C24))/AB24)*G24)) -> 34571.429 | AD24: =VLOOKUP(C24,'Inflation-OLD'!$A$6:$B$126,2)/VLOOKUP('Wainwright Summary'!$E$6,'Inflation-OLD'!$A$6:$B$126,2) -> 0.80653668 | AE24: =IF(ISERROR(AA24*AD24), " ",AA24*AD24 ) -> 48130.077 | AF24: =IF(ISERROR((AC24/G24)*AE24)," ",(AC24/G24)*AE24) -> 30253.191 | AG24: =IF(ISERROR(C24+AB24)," ",(C24+AB24)) -> 2030 | AJ24: =AB24 -> 35 | AR24: 55000 | AS24: =$AS$9 -> 1 | AT24: =AR24*AS24 -> 55000
B26: Building 3565 | C26: 1970 | D26: 1 | E26: ea | F26: =AT26 -> 60000 | G26: =IF(ISERROR(F26*D26)," ",F26*D26) -> 60000 | H26: 0 | I26: 0 | J26: 0 | K26: 0 | L26: 0 | M26: =G26*H26 -> 0 | N26: =(G26+M26)*I26 -> 0 | O26: =(G26+M26+N26)*J26 -> 0 | P26: =(G26+M26+N26+O26)*K26 -> 0 | Q26: =(G26+M26+N26+O26+P26)*L26 -> 0 | R26: =G26+SUM(M26:Q26) -> 60000 | T26: =T$10 -> 0.05 | U26: 0.03 | V26: =V$10 -> 0.1 | W26: =R26*S26 -> 0 | X26: =R26*T26 -> 3000 | Y26: =R26*U26 -> 1800 | Z26: =(W26+X26)*V26 -> 300 | AA26: =R26+SUM(W26:Z26) -> 65100 | AB26: 75 | AC26: =IF(ISERROR(IF('Wainwright Summary'!$E$7-C26>AB26,0,(AB26-('Wainwright Summary'!$E$7-C26))/AB26)*G26)," ",(IF('Wainwright Summary'!$E$7-C26>AB26,0,(AB26-('Wainwright Summary'!$E$7-C26))/AB26)*G26)) -> 29600 | AD26: =VLOOKUP(C26,'Inflation-OLD'!$A$6:$B$126,2)/VLOOKUP('Wainwright Summary'!$E$6,'Inflation-OLD'!$A$6:$B$126,2) -> 0.2359352 | AE26: =IF(ISERROR(AA26*AD26), " ",AA26*AD26 ) -> 15359.382 | AF26: =IF(ISERROR((AC26/G26)*AE26)," ",(AC26/G26)*AE26) -> 7577.295 | AG26: 2060 | AJ26: =AB26 -> 75 | AK26: 10000 | AL26: 2045 | AM26: 1 | AN26: One of 2 back-up primary water supply wells. | AR26: 60000 | AS26: =$AS$9 -> 1 | AT26: =AR26*AS26 -> 60000
B27: Building 3565 Well - 200-ft depth, 16-in dia. | C27: 1970 | D27: 1 | E27: ea | F27: 40000 | G27: =IF(ISERROR(F27*D27)," ",F27*D27) -> 40000 | H27: 0 | I27: 0 | J27: 0 | K27: 0 | L27: 0 | M27: =G27*H27 -> 0 | N27: =(G27+M27)*I27 -> 0 | O27: =(G27+M27+N27)*J27 -> 0 | P27: =(G27+M27+N27+O27)*K27 -> 0 | Q27: =(G27+M27+N27+O27+P27)*L27 -> 0 | R27: =G27+SUM(M27:Q27) -> 40000 | T27: =T$10 -> 0.05 | U27: 0.03 | V27: =V$10 -> 0.1 | W27: =R27*S27 -> 0 | X27: =R27*T27 -> 2000 | Y27: =R27*U27 -> 1200 | Z27: =(W27+X27)*V27 -> 200 | AA27: =R27+SUM(W27:Z27) -> 43400 | AB27: 50 | AC27: =IF(ISERROR(IF('Wainwright Summary'!$E$7-C27>AB27,0,(AB27-('Wainwright Summary'!$E$7-C27))/AB27)*G27)," ",(IF('Wainwright Summary'!$E$7-C27>AB27,0,(AB27-('Wainwright Summary'!$E$7-C27))/AB27)*G27)) -> 9600 | AD27: =VLOOKUP(C27,'Inflation-OLD'!$A$6:$B$126,2)/VLOOKUP('Wainwright Summary'!$E$6,'Inflation-OLD'!$A$6:$B$126,2) -> 0.2359352 | AE27: =IF(ISERROR(AA27*AD27), " ",AA27*AD27 ) -> 10239.588 | AF27: =IF(ISERROR((AC27/G27)*AE27)," ",(AC27/G27)*AE27) -> 2457.5011 | AG27: 2060 | AJ27: =AB27 -> 50 | AK27: =ROUND(0.5*AA27,-2) -> 21700 | AL27: 2020 | AM27: 1 | AN27: Unknown if building, telemetry, controls, etc. | AR27: 20000 | AS27: =$AS$9 -> 1 | AT27: =AR27*AS27 -> 20000
B28: Building 3565 Well Pump & Motor - 1000-gpm | C28: 1970 | D28: 1 | E28: ea | F28: =AT28 -> 15000 | G28: =IF(ISERROR(F28*D28)," ",F28*D28) -> 15000 | H28: 0 | I28: 0 | J28: 0 | K28: 0 | L28: 0 | M28: =G28*H28 -> 0 | N28: =(G28+M28)*I28 -> 0 | O28: =(G28+M28+N28)*J28 -> 0 | P28: =(G28+M28+N28+O28)*K28 -> 0 | Q28: =(G28+M28+N28+O28+P28)*L28 -> 0 | R28: =G28+SUM(M28:Q28) -> 15000 | T28: =T$10 -> 0.05 | U28: 0.03 | V28: =V$10 -> 0.1 | W28: =R28*S28 -> 0 | X28: =R28*T28 -> 750 | Y28: =R28*U28 -> 450 | Z28: =(W28+X28)*V28 -> 75 | AA28: =R28+SUM(W28:Z28) -> 16275 | AB28: 25 | AC28: =IF(ISERROR(IF('Wainwright Summary'!$E$7-C28>AB28,0,(AB28-('Wainwright Summary'!$E$7-C28))/AB28)*G28)," ",(IF('Wainwright Summary'!$E$7-C28>AB28,0,(AB28-('Wainwright Summary'!$E$7-C28))/AB28)*G28)) -> 0 | AD28: =VLOOKUP(C28,'Inflation-OLD'!$A$6:$B$126,2)/VLOOKUP('Wainwright Summary'!$E$6,'Inflation-OLD'!$A$6:$B$126,2) -> 0.2359352 | AE28: =IF(ISERROR(AA28*AD28), " ",AA28*AD28 ) -> 3839.8454 | AF28: =IF(ISERROR((AC28/G28)*AE28)," ",(AC28/G28)*AE28) -> 0 | AG28: 2009 | AJ28: =AB28 -> 25 | AN28: In Initial R&R. hp unknown | AR28: 15000 | AS28: =$AS$9 -> 1 | AT28: =AR28*AS28 -> 15000
B29: Building 3565 Emergency Generator - 25 kW | C29: 1989 | D29: 1 | E29: ea | F29: =AT29 -> 40000 | G29: =IF(ISERROR(F29*D29)," ",F29*D29) -> 40000 | H29: 0 | I29: 0 | J29: 0 | K29: 0 | L29: 0 | M29: =G29*H29 -> 0 | N29: =(G29+M29)*I29 -> 0 | O29: =(G29+M29+N29)*J29 -> 0 | P29: =(G29+M29+N29+O29)*K29 -> 0 | Q29: =(G29+M29+N29+O29+P29)*L29 -> 0 | R29: =G29+SUM(M29:Q29) -> 40000 | T29: =T$10 -> 0.05 | U29: 0.03 | V29: =V$10 -> 0.1 | W29: =R29*S29 -> 0 | X29: =R29*T29 -> 2000 | Y29: =R29*U29 -> 1200 | Z29: =(W29+X29)*V29 -> 200 | AA29: =R29+SUM(W29:Z29) -> 43400 | AB29: 35 | AC29: =IF(ISERROR(IF('Wainwright Summary'!$E$7-C29>AB29,0,(AB29-('Wainwright Summary'!$E$7-C29))/AB29)*G29)," ",(IF('Wainwright Summary'!$E$7-C29>AB29,0,(AB29-('Wainwright Summary'!$E$7-C29))/AB29)*G29)) -> 18285.714 | AD29: =VLOOKUP(C29,'Inflation-OLD'!$A$6:$B$126,2)/VLOOKUP('Wainwright Summary'!$E$6,'Inflation-OLD'!$A$6:$B$126,2) -> 0.68380105 | AE29: =IF(ISERROR(AA29*AD29), " ",AA29*AD29 ) -> 29676.966 | AF29: =IF(ISERROR((AC29/G29)*AE29)," ",(AC29/G29)*AE29) -> 13566.613 | AG29: =IF(ISERROR(C29+AB29)," ",(C29+AB29)) -> 2024 | AJ29: =AB29 -> 35 | AR29: 40000 | AS29: =$AS$9 -> 1 | AT29: =AR29*AS29 -> 40000
B31: Fire Protection Wells | G31: =IF(ISERROR(F31*D31)," ",F31*D31) -> 0 | M31: =G31*H31 -> 0 | N31: =(G31+M31)*I31 -> 0 | O31: =(G31+M31+N31)*J31 -> 0 | P31: =(G31+M31+N31+O31)*K31 -> 0 | Q31: =(G31+M31+N31+O31+P31)*L31 -> 0 | R31: =G31+SUM(M31:Q31) -> 0 | T31: =T$10 -> 0.05 | U31: 0.03 | V31: =V$10 -> 0.1 | W31: =R31*S31 -> 0 | X31: =R31*T31 -> 0 | Y31: =R31*U31 -> 0 | Z31: =(W31+X31)*V31 -> 0 | AA31: =R31+SUM(W31:Z31) -> 0
B32: Building 1011 | C32: 1949 | D32: 1 | E32: ea | F32: =AT32 -> 60000 | G32: =IF(ISERROR(F32*D32)," ",F32*D32) -> 60000 | H32: 0 | I32: 0 | J32: 0 | K32: 0 | L32: 0 | M32: =G32*H32 -> 0 | N32: =(G32+M32)*I32 -> 0 | O32: =(G32+M32+N32)*J32 -> 0 | P32: =(G32+M32+N32+O32)*K32 -> 0 | Q32: =(G32+M32+N32+O32+P32)*L32 -> 0 | R32: =G32+SUM(M32:Q32) -> 60000 | T32: =T$10 -> 0.05 | U32: 0.03 | V32: =V$10 -> 0.1 | W32: =R32*S32 -> 0 | X32: =R32*T32 -> 3000 | Y32: =R32*U32 -> 1800 | Z32: =(W32+X32)*V32 -> 300 | AA32: =R32+SUM(W32:Z32) -> 65100 | AB32: 75 | AC32: =IF(ISERROR(IF('Wainwright Summary'!$E$7-C32>AB32,0,(AB32-('Wainwright Summary'!$E$7-C32))/AB32)*G32)," ",(IF('Wainwright Summary'!$E$7-C32>AB32,0,(AB32-('Wainwright Summary'!$E$7-C32))/AB32)*G32)) -> 12800 | AD32: =VLOOKUP(C32,'Inflation-OLD'!$A$6:$B$126,2)/VLOOKUP('Wainwright Summary'!$E$6,'Inflation-OLD'!$A$6:$B$126,2) -> 0.14517825 | AE32: =IF(ISERROR(AA32*AD32), " ",AA32*AD32 ) -> 9451.1039 | AF32: =IF(ISERROR((AC32/G32)*AE32)," ",(AC32/G32)*AE32) -> 2016.2355 | AG32: 2060 | AJ32: =AB32 -> 75 | AK32: 10000 | AL32: 2024 | AM32: 1 | AN32: In Initial R&R. | AR32: 60000 | AS32: =$AS$9 -> 1 | AT32: =AR32*AS32 -> 60000
B33: Building 1011 Well - 60-ft depth, 8-in dia. | C33: 1949 | D33: 1 | E33: ea | F33: =AT33 -> 6000 | G33: =IF(ISERROR(F33*D33)," ",F33*D33) -> 6000 | H33: 0 | I33: 0 | J33: 0 | K33: 0 | L33: 0 | M33: =G33*H33 -> 0 | N33: =(G33+M33)*I33 -> 0 | O33: =(G33+M33+N33)*J33 -> 0 | P33: =(G33+M33+N33+O33)*K33 -> 0 | Q33: =(G33+M33+N33+O33+P33)*L33 -> 0 | R33: =G33+SUM(M33:Q33) -> 6000 | T33: =T$10 -> 0.05 | U33: 0.03 | V33: =V$10 -> 0.1 | W33: =R33*S33 -> 0 | X33: =R33*T33 -> 300 | Y33: =R33*U33 -> 180 | Z33: =(W33+X33)*V33 -> 30 | AA33: =R33+SUM(W33:Z33) -> 6510 | AB33: 50 | AC33: =IF(ISERROR(IF('Wainwright Summary'!$E$7-C33>AB33,0,(AB33-('Wainwright Summary'!$E$7-C33))/AB33)*G33)," ",(IF('Wainwright Summary'!$E$7-C33>AB33,0,(AB33-('Wainwright Summary'!$E$7-C33))/AB33)*G33)) -> 0 | AD33: =VLOOKUP(C33,'Inflation-OLD'!$A$6:$B$126,2)/VLOOKUP('Wainwright Summary'!$E$6,'Inflation-OLD'!$A$6:$B$126,2) -> 0.14517825 | AE33: =IF(ISERROR(AA33*AD33), " ",AA33*AD33 ) -> 945.11039 | AF33: =IF(ISERROR((AC33/G33)*AE33)," ",(AC33/G33)*AE33) -> 0 | AG33: 2060 | AJ33: =AB33 -> 50 | AK33: =ROUND(0.5*AA33,-2) -> 3300 | AL33: 2010 | AM33: 1 | AN33: Initial R&R. Unknown if building, telemetry, controls, etc. | AR33: 6000 | AS33: =$AS$9 -> 1 | AT33: =AR33*AS33 -> 6000
B34: Building 1011 Well Pump & Motor - 750-gpm | C34: 1949 | D34: 1 | E34: ea | F34: =AT34 -> 15000 | G34: =IF(ISERROR(F34*D34)," ",F34*D34) -> 15000 | H34: 0 | I34: 0 | J34: 0 | K34: 0 | L34: 0 | M34: =G34*H34 -> 0 | N34: =(G34+M34)*I34 -> 0 | O34: =(G34+M34+N34)*J34 -> 0 | P34: =(G34+M34+N34+O34)*K34 -> 0 | Q34: =(G34+M34+N34+O34+P34)*L34 -> 0 | R34: =G34+SUM(M34:Q34) -> 15000 | T34: =T$10 -> 0.05 | U34: 0.03 | V34: =V$10 -> 0.1 | W34: =R34*S34 -> 0 | X34: =R34*T34 -> 750 | Y34: =R34*U34 -> 450 | Z34: =(W34+X34)*V34 -> 75 | AA34: =R34+SUM(W34:Z34) -> 16275 | AB34: 25 | AC34: =IF(ISERROR(IF('Wainwright Summary'!$E$7-C34>AB34,0,(AB34-('Wainwright Summary'!$E$7-C34))/AB34)*G34)," ",(IF('Wainwright Summary'!$E$7-C34>AB34,0,(AB34-('Wainwright Summary'!$E$7-C34))/AB34)*G34)) -> 0 | AD34: =VLOOKUP(C34,'Inflation-OLD'!$A$6:$B$126,2)/VLOOKUP('Wainwright Summary'!$E$6,'Inflation-OLD'!$A$6:$B$126,2) -> 0.14517825 | AE34: =IF(ISERROR(AA34*AD34), " ",AA34*AD34 ) -> 2362.776 | AF34: =IF(ISERROR((AC34/G34)*AE34)," ",(AC34/G34)*AE34) -> 0 | AG34: 2010 | AJ34: =AB34 -> 25 | AN34: In Initial R&R. hp unknown | AR34: 15000 | AS34: =$AS$9 -> 1 | AT34: =AR34*AS34 -> 15000
B36: Building 1032 | C36: 1950 | D36: 1 | E36: ea | F36: =AT36 -> 60000 | G36: =IF(ISERROR(F36*D36)," ",F36*D36) -> 60000 | H36: 0 | I36: 0 | J36: 0 | K36: 0 | L36: 0 | M36: =G36*H36 -> 0 | N36: =(G36+M36)*I36 -> 0 | O36: =(G36+M36+N36)*J36 -> 0 | P36: =(G36+M36+N36+O36)*K36 -> 0 | Q36: =(G36+M36+N36+O36+P36)*L36 -> 0 | R36: =G36+SUM(M36:Q36) -> 60000 | T36: =T$10 -> 0.05 | U36: 0.03 | V36: =V$10 -> 0.1 | W36: =R36*S36 -> 0 | X36: =R36*T36 -> 3000 | Y36: =R36*U36 -> 1800 | Z36: =(W36+X36)*V36 -> 300 | AA36: =R36+SUM(W36:Z36) -> 65100 | AB36: 75 | AC36: =IF(ISERROR(IF('Wainwright Summary'!$E$7-C36>AB36,0,(AB36-('Wainwright Summary'!$E$7-C36))/AB36)*G36)," ",(IF('Wainwright Summary'!$E$7-C36>AB36,0,(AB36-('Wainwright Summary'!$E$7-C36))/AB36)*G36)) -> 13600 | AD36: =VLOOKUP(C36,'Inflation-OLD'!$A$6:$B$126,2)/VLOOKUP('Wainwright Summary'!$E$6,'Inflation-OLD'!$A$6:$B$126,2) -> 0.14287644 | AE36: =IF(ISERROR(AA36*AD36), " ",AA36*AD36 ) -> 9301.2563 | AF36: =IF(ISERROR((AC36/G36)*AE36)," ",(AC36/G36)*AE36) -> 2108.2848 | AG36: 2060 | AJ36: =AB36 -> 75 | AK36: 10000 | AL36: 2025 | AM36: 1 | AN36: In Initial R&R. | AR36: 60000 | AS36: =$AS$9 -> 1 | AT36: =AR36*AS36 -> 60000
B37: Building 1032 Well - 58-ft depth, 12-in dia. | C37: 1950 | D37: 1 | E37: ea | F37: 8000 | G37: =IF(ISERROR(F37*D37)," ",F37*D37) -> 8000 | H37: 0 | I37: 0 | J37: 0 | K37: 0 | L37: 0 | M37: =G37*H37 -> 0 | N37: =(G37+M37)*I37 -> 0 | O37: =(G37+M37+N37)*J37 -> 0 | P37: =(G37+M37+N37+O37)*K37 -> 0 | Q37: =(G37+M37+N37+O37+P37)*L37 -> 0 | R37: =G37+SUM(M37:Q37) -> 8000 | T37: =T$10 -> 0.05 | U37: 0.03 | V37: =V$10 -> 0.1 | W37: =R37*S37 -> 0 | X37: =R37*T37 -> 400 | Y37: =R37*U37 -> 240 | Z37: =(W37+X37)*V37 -> 40 | AA37: =R37+SUM(W37:Z37) -> 8680 | AB37: 50 | AC37: =IF(ISERROR(IF('Wainwright Summary'!$E$7-C37>AB37,0,(AB37-('Wainwright Summary'!$E$7-C37))/AB37)*G37)," ",(IF('Wainwright Summary'!$E$7-C37>AB37,0,(AB37-('Wainwright Summary'!$E$7-C37))/AB37)*G37)) -> 0 | AD37: =VLOOKUP(C37,'Inflation-OLD'!$A$6:$B$126,2)/VLOOKUP('Wainwright Summary'!$E$6,'Inflation-OLD'!$A$6:$B$126,2) -> 0.14287644 | AE37: =IF(ISERROR(AA37*AD37), " ",AA37*AD37 ) -> 1240.1675 | AF37: =IF(ISERROR((AC37/G37)*AE37)," ",(AC37/G37)*AE37) -> 0 | AG37: 2060 | AJ37: =AB37 -> 50 | AK37: =ROUND(0.5*AA37,-2) -> 4300 | AL37: 2011 | AM37: 1 | AN37: In Initial R&R.Unknown if building, telemetry, controls, etc. | AR37: 15000 | AS37: =$AS$9 -> 1 | AT37: =AR37*AS37 -> 15000
B38: Building 1032 Well Pump & Motor - 750-gpm | C38: 1985 | D38: 1 | E38: ea | F38: =AT38 -> 15000 | G38: =IF(ISERROR(F38*D38)," ",F38*D38) -> 15000 | H38: 0 | I38: 0 | J38: 0 | K38: 0 | L38: 0 | M38: =G38*H38 -> 0 | N38: =(G38+M38)*I38 -> 0 | O38: =(G38+M38+N38)*J38 -> 0 | P38: =(G38+M38+N38+O38)*K38 -> 0 | Q38: =(G38+M38+N38+O38+P38)*L38 -> 0 | R38: =G38+SUM(M38:Q38) -> 15000 | T38: =T$10 -> 0.05 | U38: 0.03 | V38: =V$10 -> 0.1 | W38: =R38*S38 -> 0 | X38: =R38*T38 -> 750 | Y38: =R38*U38 -> 450 | Z38: =(W38+X38)*V38 -> 75 | AA38: =R38+SUM(W38:Z38) -> 16275 | AB38: 25 | AC38: =IF(ISERROR(IF('Wainwright Summary'!$E$7-C38>AB38,0,(AB38-('Wainwright Summary'!$E$7-C38))/AB38)*G38)," ",(IF('Wainwright Summary'!$E$7-C38>AB38,0,(AB38-('Wainwright Summary'!$E$7-C38))/AB38)*G38)) -> 1200 | AD38: =VLOOKUP(C38,'Inflation-OLD'!$A$6:$B$126,2)/VLOOKUP('Wainwright Summary'!$E$6,'Inflation-OLD'!$A$6:$B$126,2) -> 0.60685494 | AE38: =IF(ISERROR(AA38*AD38), " ",AA38*AD38 ) -> 9876.5641 | AF38: =IF(ISERROR((AC38/G38)*AE38)," ",(AC38/G38)*AE38) -> 790.12513 | AG38: 2011 | AJ38: =AB38 -> 25 | AN38: In Initial R&R. hp unknown | AR38: 15000 | AS38: =$AS$9 -> 1 | AT38: =AR38*AS38 -> 15000
B39: Building 1032 Well Emergency Generator - 250 kW | C39: 1993 | D39: 1 | E39: ea | F39: =AT39 -> 60000 | G39: =IF(ISERROR(F39*D39)," ",F39*D39) -> 60000 | H39: 0 | I39: 0 | J39: 0 | K39: 0 | L39: 0 | M39: =G39*H39 -> 0 | N39: =(G39+M39)*I39 -> 0 | O39: =(G39+M39+N39)*J39 -> 0 | P39: =(G39+M39+N39+O39)*K39 -> 0 | Q39: =(G39+M39+N39+O39+P39)*L39 -> 0 | R39: =G39+SUM(M39:Q39) -> 60000 | T39: =T$10 -> 0.05 | U39: 0.03 | V39: =V$10 -> 0.1 | W39: =R39*S39 -> 0 | X39: =R39*T39 -> 3000 | Y39: =R39*U39 -> 1800 | Z39: =(W39+X39)*V39 -> 300 | AA39: =R39+SUM(W39:Z39) -> 65100 | AB39: 35 | AC39: =IF(ISERROR(IF('Wainwright Summary'!$E$7-C39>AB39,0,(AB39-('Wainwright Summary'!$E$7-C39))/AB39)*G39)," ",(IF('Wainwright Summary'!$E$7-C39>AB39,0,(AB39-('Wainwright Summary'!$E$7-C39))/AB39)*G39)) -> 34285.714 | AD39: =VLOOKUP(C39,'Inflation-OLD'!$A$6:$B$126,2)/VLOOKUP('Wainwright Summary'!$E$6,'Inflation-OLD'!$A$6:$B$126,2) -> 0.77209179 | AE39: =IF(ISERROR(AA39*AD39), " ",AA39*AD39 ) -> 50263.175 | AF39: =IF(ISERROR((AC39/G39)*AE39)," ",(AC39/G39)*AE39) -> 28721.815 | AG39: =IF(ISERROR(C39+AB39)," ",(C39+AB39)) -> 2028 | AJ39: =AB39 -> 35 | AR39: 60000 | AS39: =$AS$9 -> 1 | AT39: =AR39*AS39 -> 60000
B40: Install Sand Trap on 1032 Well - WCU4 | C40: 1950 | D40: 1 | E40: ea | F40: =AT40 -> 35000 | G40: =IF(ISERROR(F40*D40)," ",F40*D40) -> 35000 | H40: 0 | I40: 0 | J40: 0 | K40: 0 | L40: 0 | M40: =G40*H40 -> 0 | N40: =(G40+M40)*I40 -> 0 | O40: =(G40+M40+N40)*J40 -> 0 | P40: =(G40+M40+N40+O40)*K40 -> 0 | Q40: =(G40+M40+N40+O40+P40)*L40 -> 0 | R40: =G40+SUM(M40:Q40) -> 35000 | T40: =T$10 -> 0.05 | U40: 0.03 | V40: =V$10 -> 0.1 | W40: =R40*S40 -> 0 | X40: =R40*T40 -> 1750 | Y40: =R40*U40 -> 1050 | Z40: =(W40+X40)*V40 -> 175 | AA40: =R40+SUM(W40:Z40) -> 37975 | AB40: 25 | AC40: =IF(ISERROR(IF('Wainwright Summary'!$E$7-C40>AB40,0,(AB40-('Wainwright Summary'!$E$7-C40))/AB40)*G40)," ",(IF('Wainwright Summary'!$E$7-C40>AB40,0,(AB40-('Wainwright Summary'!$E$7-C40))/AB40)*G40)) -> 0 | AD40: =VLOOKUP(C40,'Inflation-OLD'!$A$6:$B$126,2)/VLOOKUP('Wainwright Summary'!$E$6,'Inflation-OLD'!$A$6:$B$126,2) -> 0.14287644 | AE40: =IF(ISERROR(AA40*AD40), " ",AA40*AD40 ) -> 5425.7328 | AF40: =IF(ISERROR((AC40/G40)*AE40)," ",(AC40/G40)*AE40) -> 0 | AG40: 2009 | AJ40: =AB40 -> 25 | AR40: 35000 | AS40: =$AS$9 -> 1 | AT40: =AR40*AS40 -> 35000
B42: Building 3003 | C42: 1945 | D42: 1 | E42: ea | F42: =AT42 -> 60000 | G42: =IF(ISERROR(F42*D42)," ",F42*D42) -> 60000 | H42: 0 | I42: 0 | J42: 0 | K42: 0 | L42: 0 | M42: =G42*H42 -> 0 | N42: =(G42+M42)*I42 -> 0 | O42: =(G42+M42+N42)*J42 -> 0 | P42: =(G42+M42+N42+O42)*K42 -> 0 | Q42: =(G42+M42+N42+O42+P42)*L42 -> 0 | R42: =G42+SUM(M42:Q42) -> 60000 | T42: =T$10 -> 0.05 | U42: 0.03 | V42: =V$10 -> 0.1 | W42: =R42*S42 -> 0 | X42: =R42*T42 -> 3000 | Y42: =R42*U42 -> 1800 | Z42: =(W42+X42)*V42 -> 300 | AA42: =R42+SUM(W42:Z42) -> 65100 | AB42: 75 | AC42: =IF(ISERROR(IF('Wainwright Summary'!$E$7-C42>AB42,0,(AB42-('Wainwright Summary'!$E$7-C42))/AB42)*G42)," ",(IF('Wainwright Summary'!$E$7-C42>AB42,0,(AB42-('Wainwright Summary'!$E$7-C42))/AB42)*G42)) -> 9600 | AD42: =VLOOKUP(C42,'Inflation-OLD'!$A$6:$B$126,2)/VLOOKUP('Wainwright Summary'!$E$6,'Inflation-OLD'!$A$6:$B$126,2) -> 0.10752726 | AE42: =IF(ISERROR(AA42*AD42), " ",AA42*AD42 ) -> 7000.0249 | AF42: =IF(ISERROR((AC42/G42)*AE42)," ",(AC42/G42)*AE42) -> 1120.004 | AG42: 2060 | AJ42: =AB42 -> 75 | AK42: 10000 | AL42: 2020 | AM42: 1 | AN42: In Initial R&R. | AR42: 60000 | AS42: =$AS$9 -> 1 | AT42: =AR42*AS42 -> 60000
B43: Building 3003 Well - 160-ft depth, 8-in dia. | C43: 1945 | D43: 1 | E43: ea | F43: 9000 | G43: =IF(ISERROR(F43*D43)," ",F43*D43) -> 9000 | H43: 0 | I43: 0 | J43: 0 | K43: 0 | L43: 0 | M43: =G43*H43 -> 0 | N43: =(G43+M43)*I43 -> 0 | O43: =(G43+M43+N43)*J43 -> 0 | P43: =(G43+M43+N43+O43)*K43 -> 0 | Q43: =(G43+M43+N43+O43+P43)*L43 -> 0 | R43: =G43+SUM(M43:Q43) -> 9000 | T43: =T$10 -> 0.05 | U43: 0.03 | V43: =V$10 -> 0.1 | W43: =R43*S43 -> 0 | X43: =R43*T43 -> 450 | Y43: =R43*U43 -> 270 | Z43: =(W43+X43)*V43 -> 45 | AA43: =R43+SUM(W43:Z43) -> 9765 | AB43: 50 | AC43: =IF(ISERROR(IF('Wainwright Summary'!$E$7-C43>AB43,0,(AB43-('Wainwright Summary'!$E$7-C43))/AB43)*G43)," ",(IF('Wainwright Summary'!$E$7-C43>AB43,0,(AB43-('Wainwright Summary'!$E$7-C43))/AB43)*G43)) -> 0 | AD43: =VLOOKUP(C43,'Inflation-OLD'!$A$6:$B$126,2)/VLOOKUP('Wainwright Summary'!$E$6,'Inflation-OLD'!$A$6:$B$126,2) -> 0.10752726 | AE43: =IF(ISERROR(AA43*AD43), " ",AA43*AD43 ) -> 1050.0037 | AF43: =IF(ISERROR((AC43/G43)*AE43)," ",(AC43/G43)*AE43) -> 0 | AG43: 2060 | AJ43: =AB43 -> 50 | AK43: =ROUND(0.5*AA43,-2) -> 4900 | AL43: 2012 | AM43: 1 | AN43: Initial R&R. Unknown if building, telemetry, controls, etc. | AR43: 6000 | AS43: =$AS$9 -> 1 | AT43: =AR43*AS43 -> 6000
B44: Building 3003 Well Pump & Motor - 600-gpm | C44: 1945 | D44: 1 | E44: ea | F44: =AT44 -> 15000 | G44: =IF(ISERROR(F44*D44)," ",F44*D44) -> 15000 | H44: 0 | I44: 0 | J44: 0 | K44: 0 | L44: 0 | M44: =G44*H44 -> 0 | N44: =(G44+M44)*I44 -> 0 | O44: =(G44+M44+N44)*J44 -> 0 | P44: =(G44+M44+N44+O44)*K44 -> 0 | Q44: =(G44+M44+N44+O44+P44)*L44 -> 0 | R44: =G44+SUM(M44:Q44) -> 15000 | T44: =T$10 -> 0.05 | U44: 0.03 | V44: =V$10 -> 0.1 | W44: =R44*S44 -> 0 | X44: =R44*T44 -> 750 | Y44: =R44*U44 -> 450 | Z44: =(W44+X44)*V44 -> 75 | AA44: =R44+SUM(W44:Z44) -> 16275 | AB44: 25 | AC44: =IF(ISERROR(IF('Wainwright Summary'!$E$7-C44>AB44,0,(AB44-('Wainwright Summary'!$E$7-C44))/AB44)*G44)," ",(IF('Wainwright Summary'!$E$7-C44>AB44,0,(AB44-('Wainwright Summary'!$E$7-C44))/AB44)*G44)) -> 0 | AD44: =VLOOKUP(C44,'Inflation-OLD'!$A$6:$B$126,2)/VLOOKUP('Wainwright Summary'!$E$6,'Inflation-OLD'!$A$6:$B$126,2) -> 0.10752726 | AE44: =IF(ISERROR(AA44*AD44), " ",AA44*AD44 ) -> 1750.0062 | AF44: =IF(ISERROR((AC44/G44)*AE44)," ",(AC44/G44)*AE44) -> 0 | AG44: 2012 | AJ44: =AB44 -> 25 | AN44: In Initial R&R. hp unknown | AR44: 15000 | AS44: =$AS$9 -> 1 | AT44: =AR44*AS44 -> 15000
B46: Building 3405 | C46: 1954 | D46: 1 | E46: ea | F46: =AT46 -> 60000 | G46: =IF(ISERROR(F46*D46)," ",F46*D46) -> 60000 | H46: 0 | I46: 0 | J46: 0 | K46: 0 | L46: 0 | M46: =G46*H46 -> 0 | N46: =(G46+M46)*I46 -> 0 | O46: =(G46+M46+N46)*J46 -> 0 | P46: =(G46+M46+N46+O46)*K46 -> 0 | Q46: =(G46+M46+N46+O46+P46)*L46 -> 0 | R46: =G46+SUM(M46:Q46) -> 60000 | T46: =T$10 -> 0.05 | U46: 0.03 | V46: =V$10 -> 0.1 | W46: =R46*S46 -> 0 | X46: =R46*T46 -> 3000 | Y46: =R46*U46 -> 1800 | Z46: =(W46+X46)*V46 -> 300 | AA46: =R46+SUM(W46:Z46) -> 65100 | AB46: 75 | AC46: =IF(ISERROR(IF('Wainwright Summary'!$E$7-C46>AB46,0,(AB46-('Wainwright Summary'!$E$7-C46))/AB46)*G46)," ",(IF('Wainwright Summary'!$E$7-C46>AB46,0,(AB46-('Wainwright Summary'!$E$7-C46))/AB46)*G46)) -> 16800 | AD46: =VLOOKUP(C46,'Inflation-OLD'!$A$6:$B$126,2)/VLOOKUP('Wainwright Summary'!$E$6,'Inflation-OLD'!$A$6:$B$126,2) -> 0.16120869 | AE46: =IF(ISERROR(AA46*AD46), " ",AA46*AD46 ) -> 10494.686 | AF46: =IF(ISERROR((AC46/G46)*AE46)," ",(AC46/G46)*AE46) -> 2938.512 | AG46: 2060 | AJ46: =AB46 -> 75 | AK46: 10000 | AL46: 2029 | AM46: 1 | AR46: 60000 | AS46: =$AS$9 -> 1 | AT46: =AR46*AS46 -> 60000
B47: Building 3405 Well - 118-ft depth, 12-in dia. | C47: 1954 | D47: 1 | E47: ea | F47: =AT47 -> 15000 | G47: =IF(ISERROR(F47*D47)," ",F47*D47) -> 15000 | H47: 0 | I47: 0 | J47: 0 | K47: 0 | L47: 0 | M47: =G47*H47 -> 0 | N47: =(G47+M47)*I47 -> 0 | O47: =(G47+M47+N47)*J47 -> 0 | P47: =(G47+M47+N47+O47)*K47 -> 0 | Q47: =(G47+M47+N47+O47+P47)*L47 -> 0 | R47: =G47+SUM(M47:Q47) -> 15000 | T47: =T$10 -> 0.05 | U47: 0.03 | V47: =V$10 -> 0.1 | W47: =R47*S47 -> 0 | X47: =R47*T47 -> 750 | Y47: =R47*U47 -> 450 | Z47: =(W47+X47)*V47 -> 75 | AA47: =R47+SUM(W47:Z47) -> 16275 | AB47: 50 | AC47: =IF(ISERROR(IF('Wainwright Summary'!$E$7-C47>AB47,0,(AB47-('Wainwright Summary'!$E$7-C47))/AB47)*G47)," ",(IF('Wainwright Summary'!$E$7-C47>AB47,0,(AB47-('Wainwright Summary'!$E$7-C47))/AB47)*G47)) -> 0 | AD47: =VLOOKUP(C47,'Inflation-OLD'!$A$6:$B$126,2)/VLOOKUP('Wainwright Summary'!$E$6,'Inflation-OLD'!$A$6:$B$126,2) -> 0.16120869 | AE47: =IF(ISERROR(AA47*AD47), " ",AA47*AD47 ) -> 2623.6714 | AF47: =IF(ISERROR((AC47/G47)*AE47)," ",(AC47/G47)*AE47) -> 0 | AG47: 2060 | AJ47: =AB47 -> 50 | AK47: =ROUND(0.5*AA47,-2) -> 8100 | AL47: 2013 | AM47: 1 | AN47: Unknown if building, telemetry, controls, etc. | AR47: 15000 | AS47: =$AS$9 -> 1 | AT47: =AR47*AS47 -> 15000
B48: Building 3405 Well Pump & Motor - 1000-gpm | C48: 1954 | D48: 1 | E48: ea | F48: =AT48 -> 15000 | G48: =IF(ISERROR(F48*D48)," ",F48*D48) -> 15000 | H48: 0 | I48: 0 | J48: 0 | K48: 0 | L48: 0 | M48: =G48*H48 -> 0 | N48: =(G48+M48)*I48 -> 0 | O48: =(G48+M48+N48)*J48 -> 0 | P48: =(G48+M48+N48+O48)*K48 -> 0 | Q48: =(G48+M48+N48+O48+P48)*L48 -> 0 | R48: =G48+SUM(M48:Q48) -> 15000 | T48: =T$10 -> 0.05 | U48: 0.03 | V48: =V$10 -> 0.1 | W48: =R48*S48 -> 0 | X48: =R48*T48 -> 750 | Y48: =R48*U48 -> 450 | Z48: =(W48+X48)*V48 -> 75 | AA48: =R48+SUM(W48:Z48) -> 16275 | AB48: 25 | AC48: =IF(ISERROR(IF('Wainwright Summary'!$E$7-C48>AB48,0,(AB48-('Wainwright Summary'!$E$7-C48))/AB48)*G48)," ",(IF('Wainwright Summary'!$E$7-C48>AB48,0,(AB48-('Wainwright Summary'!$E$7-C48))/AB48)*G48)) -> 0 | AD48: =VLOOKUP(C48,'Inflation-OLD'!$A$6:$B$126,2)/VLOOKUP('Wainwright Summary'!$E$6,'Inflation-OLD'!$A$6:$B$126,2) -> 0.16120869 | AE48: =IF(ISERROR(AA48*AD48), " ",AA48*AD48 ) -> 2623.6714 | AF48: =IF(ISERROR((AC48/G48)*AE48)," ",(AC48/G48)*AE48) -> 0 | AG48: 2013 | AJ48: =AB48 -> 25 | AN48: hp unknown | AR48: 15000 | AS48: =$AS$9 -> 1 | AT48: =AR48*AS48 -> 15000
B49: Building 3405 Well Emergency Generator - 220 hp | C49: 1995 | D49: 1 | E49: ea | F49: =AT49 -> 55000 | G49: =IF(ISERROR(F49*D49)," ",F49*D49) -> 55000 | H49: 0 | I49: 0 | J49: 0 | K49: 0 | L49: 0 | M49: =G49*H49 -> 0 | N49: =(G49+M49)*I49 -> 0 | O49: =(G49+M49+N49)*J49 -> 0 | P49: =(G49+M49+N49+O49)*K49 -> 0 | Q49: =(G49+M49+N49+O49+P49)*L49 -> 0 | R49: =G49+SUM(M49:Q49) -> 55000 | T49: =T$10 -> 0.05 | U49: 0.03 | V49: =V$10 -> 0.1 | W49: =R49*S49 -> 0 | X49: =R49*T49 -> 2750 | Y49: =R49*U49 -> 1650 | Z49: =(W49+X49)*V49 -> 275 | AA49: =R49+SUM(W49:Z49) -> 59675 | AB49: 35 | AC49: =IF(ISERROR(IF('Wainwright Summary'!$E$7-C49>AB49,0,(AB49-('Wainwright Summary'!$E$7-C49))/AB49)*G49)," ",(IF('Wainwright Summary'!$E$7-C49>AB49,0,(AB49-('Wainwright Summary'!$E$7-C49))/AB49)*G49)) -> 34571.429 | AD49: =VLOOKUP(C49,'Inflation-OLD'!$A$6:$B$126,2)/VLOOKUP('Wainwright Summary'!$E$6,'Inflation-OLD'!$A$6:$B$126,2) -> 0.80653668 | AE49: =IF(ISERROR(AA49*AD49), " ",AA49*AD49 ) -> 48130.077 | AF49: =IF(ISERROR((AC49/G49)*AE49)," ",(AC49/G49)*AE49) -> 30253.191 | AG49: =IF(ISERROR(C49+AB49)," ",(C49+AB49)) -> 2030 | AJ49: =AB49 -> 35 | AR49: 55000 | AS49: =$AS$9 -> 1 | AT49: =AR49*AS49 -> 55000
B51: Building 4023 | C51: 1950 | D51: 1 | E51: ea | F51: =AT51 -> 60000 | G51: =IF(ISERROR(F51*D51)," ",F51*D51) -> 60000 | H51: 0 | I51: 0 | J51: 0 | K51: 0 | L51: 0 | M51: =G51*H51 -> 0 | N51: =(G51+M51)*I51 -> 0 | O51: =(G51+M51+N51)*J51 -> 0 | P51: =(G51+M51+N51+O51)*K51 -> 0 | Q51: =(G51+M51+N51+O51+P51)*L51 -> 0 | R51: =G51+SUM(M51:Q51) -> 60000 | T51: =T$10 -> 0.05 | U51: 0.03 | V51: =V$10 -> 0.1 | W51: =R51*S51 -> 0 | X51: =R51*T51 -> 3000 | Y51: =R51*U51 -> 1800 | Z51: =(W51+X51)*V51 -> 300 | AA51: =R51+SUM(W51:Z51) -> 65100 | AB51: 75 | AC51: =IF(ISERROR(IF('Wainwright Summary'!$E$7-C51>AB51,0,(AB51-('Wainwright Summary'!$E$7-C51))/AB51)*G51)," ",(IF('Wainwright Summary'!$E$7-C51>AB51,0,(AB51-('Wainwright Summary'!$E$7-C51))/AB51)*G51)) -> 13600 | AD51: =VLOOKUP(C51,'Inflation-OLD'!$A$6:$B$126,2)/VLOOKUP('Wainwright Summary'!$E$6,'Inflation-OLD'!$A$6:$B$126,2) -> 0.14287644 | AE51: =IF(ISERROR(AA51*AD51), " ",AA51*AD51 ) -> 9301.2563 | AF51: =IF(ISERROR((AC51/G51)*AE51)," ",(AC51/G51)*AE51) -> 2108.2848 | AG51: 2060 | AJ51: =AB51 -> 75 | AK51: 10000 | AL51: 2025 | AM51: 1 | AR51: 60000 | AS51: =$AS$9 -> 1 | AT51: =AR51*AS51 -> 60000
B52: Building 4023 Well - Unknown depth, 12-in dia. | C52: 1950 | D52: 1 | E52: ea | F52: =AT52 -> 15000 | G52: =IF(ISERROR(F52*D52)," ",F52*D52) -> 15000 | H52: 0 | I52: 0 | J52: 0 | K52: 0 | L52: 0 | M52: =G52*H52 -> 0 | N52: =(G52+M52)*I52 -> 0 | O52: =(G52+M52+N52)*J52 -> 0 | P52: =(G52+M52+N52+O52)*K52 -> 0 | Q52: =(G52+M52+N52+O52+P52)*L52 -> 0 | R52: =G52+SUM(M52:Q52) -> 15000 | T52: =T$10 -> 0.05 | U52: 0.03 | V52: =V$10 -> 0.1 | W52: =R52*S52 -> 0 | X52: =R52*T52 -> 750 | Y52: =R52*U52 -> 450 | Z52: =(W52+X52)*V52 -> 75 | AA52: =R52+SUM(W52:Z52) -> 16275 | AB52: 50 | AC52: =IF(ISERROR(IF('Wainwright Summary'!$E$7-C52>AB52,0,(AB52-('Wainwright Summary'!$E$7-C52))/AB52)*G52)," ",(IF('Wainwright Summary'!$E$7-C52>AB52,0,(AB52-('Wainwright Summary'!$E$7-C52))/AB52)*G52)) -> 0 | AD52: =VLOOKUP(C52,'Inflation-OLD'!$A$6:$B$126,2)/VLOOKUP('Wainwright Summary'!$E$6,'Inflation-OLD'!$A$6:$B$126,2) -> 0.14287644 | AE52: =IF(ISERROR(AA52*AD52), " ",AA52*AD52 ) -> 2325.3141 | AF52: =IF(ISERROR((AC52/G52)*AE52)," ",(AC52/G52)*AE52) -> 0 | AG52: 2060 | AJ52: =AB52 -> 50 | AK52: =ROUND(0.5*AA52,-2) -> 8100 | AL52: 2014 | AM52: 1 | AN52: Unknown if building, telemetry, controls, etc. | AR52: 15000 | AS52: =$AS$9 -> 1 | AT52: =AR52*AS52 -> 15000
B53: Drill NEW 4023 well - WCU3 | D53: 1 | E53: ea | F53: =AT53 -> 30000 | G53: =IF(ISERROR(F53*D53)," ",F53*D53) -> 30000 | H53: 0 | I53: 0 | J53: 0 | K53: 0 | L53: 0 | M53: =G53*H53 -> 0 | N53: =(G53+M53)*I53 -> 0 | O53: =(G53+M53+N53)*J53 -> 0 | P53: =(G53+M53+N53+O53)*K53 -> 0 | Q53: =(G53+M53+N53+O53+P53)*L53 -> 0 | R53: =G53+SUM(M53:Q53) -> 30000 | T53: =T$10 -> 0.05 | U53: 0.03 | V53: =V$10 -> 0.1 | W53: =R53*S53 -> 0 | X53: =R53*T53 -> 1500 | Y53: =R53*U53 -> 900 | Z53: =(W53+X53)*V53 -> 150 | AA53: =R53+SUM(W53:Z53) -> 32550 | AB53: 50 | AC53: =IF(ISERROR(IF('Wainwright Summary'!$E$7-C53>AB53,0,(AB53-('Wainwright Summary'!$E$7-C53))/AB53)*G53)," ",(IF('Wainwright Summary'!$E$7-C53>AB53,0,(AB53-('Wainwright Summary'!$E$7-C53))/AB53)*G53)) -> 0 | AE53: =IF(ISERROR(D53*F53*AD53), " ",D53*F53*AD53 ) -> 0 | AF53: =IF(ISERROR((AC53/G53)*AE53)," ",(AC53/G53)*AE53) -> 0 | AG53: 2008 | AJ53: =AB53 -> 50 | AR53: 30000 | AS53: =$AS$9 -> 1 | AT53: =AR53*AS53 -> 30000
B54: Building 4023 Well Pump & Motor - 750-gpm | C54: 1950 | D54: 1 | E54: ea | F54: =AT54 -> 15000 | G54: =IF(ISERROR(F54*D54)," ",F54*D54) -> 15000 | H54: 0 | I54: 0 | J54: 0 | K54: 0 | L54: 0 | M54: =G54*H54 -> 0 | N54: =(G54+M54)*I54 -> 0 | O54: =(G54+M54+N54)*J54 -> 0 | P54: =(G54+M54+N54+O54)*K54 -> 0 | Q54: =(G54+M54+N54+O54+P54)*L54 -> 0 | R54: =G54+SUM(M54:Q54) -> 15000 | T54: =T$10 -> 0.05 | U54: 0.03 | V54: =V$10 -> 0.1 | W54: =R54*S54 -> 0 | X54: =R54*T54 -> 750 | Y54: =R54*U54 -> 450 | Z54: =(W54+X54)*V54 -> 75 | AA54: =R54+SUM(W54:Z54) -> 16275 | AB54: 25 | AC54: =IF(ISERROR(IF('Wainwright Summary'!$E$7-C54>AB54,0,(AB54-('Wainwright Summary'!$E$7-C54))/AB54)*G54)," ",(IF('Wainwright Summary'!$E$7-C54>AB54,0,(AB54-('Wainwright Summary'!$E$7-C54))/AB54)*G54)) -> 0 | AD54: =VLOOKUP(C54,'Inflation-OLD'!$A$6:$B$126,2)/VLOOKUP('Wainwright Summary'!$E$6,'Inflation-OLD'!$A$6:$B$126,2) -> 0.14287644 | AE54: =IF(ISERROR(AA54*AD54), " ",AA54*AD54 ) -> 2325.3141 | AF54: =IF(ISERROR((AC54/G54)*AE54)," ",(AC54/G54)*AE54) -> 0 | AG54: 2014 | AJ54: =AB54 -> 25 | AN54: hp unknown | AR54: 15000 | AS54: =$AS$9 -> 1 | AT54: =AR54*AS54 -> 15000
B55: Building 4023 Well Emergency Generator - 220 hp | C55: 1995 | D55: 1 | E55: ea | F55: =AT55 -> 55000 | G55: =IF(ISERROR(F55*D55)," ",F55*D55) -> 55000 | H55: 0 | I55: 0 | J55: 0 | K55: 0 | L55: 0 | M55: =G55*H55 -> 0 | N55: =(G55+M55)*I55 -> 0 | O55: =(G55+M55+N55)*J55 -> 0 | P55: =(G55+M55+N55+O55)*K55 -> 0 | Q55: =(G55+M55+N55+O55+P55)*L55 -> 0 | R55: =G55+SUM(M55:Q55) -> 55000 | T55: =T$10 -> 0.05 | U55: 0.03 | V55: =V$10 -> 0.1 | W55: =R55*S55 -> 0 | X55: =R55*T55 -> 2750 | Y55: =R55*U55 -> 1650 | Z55: =(W55+X55)*V55 -> 275 | AA55: =R55+SUM(W55:Z55) -> 59675 | AB55: 35 | AC55: =IF(ISERROR(IF('Wainwright Summary'!$E$7-C55>AB55,0,(AB55-('Wainwright Summary'!$E$7-C55))/AB55)*G55)," ",(IF('Wainwright Summary'!$E$7-C55>AB55,0,(AB55-('Wainwright Summary'!$E$7-C55))/AB55)*G55)) -> 34571.429 | AD55: =VLOOKUP(C55,'Inflation-OLD'!$A$6:$B$126,2)/VLOOKUP('Wainwright Summary'!$E$6,'Inflation-OLD'!$A$6:$B$126,2) -> 0.80653668 | AE55: =IF(ISERROR(AA55*AD55), " ",AA55*AD55 ) -> 48130.077 | AF55: =IF(ISERROR((AC55/G55)*AE55)," ",(AC55/G55)*AE55) -> 30253.191 | AG55: =IF(ISERROR(C55+AB55)," ",(C55+AB55)) -> 2030 | AJ55: =AB55 -> 35 | AR55: 55000 | AS55: =$AS$9 -> 1 | AT55: =AR55*AS55 -> 55000
B57: Fire Protection Wells
B58: Building 1170 - snow maker | C58: 1949 | D58: 1 | E58: ea | F58: =AT58 -> 60000 | G58: =IF(ISERROR(F58*D58)," ",F58*D58) -> 60000 | H58: 0 | I58: 0 | J58: 0 | K58: 0 | L58: 0 | M58: =G58*H58 -> 0 | N58: =(G58+M58)*I58 -> 0 | O58: =(G58+M58+N58)*J58 -> 0 | P58: =(G58+M58+N58+O58)*K58 -> 0 | Q58: =(G58+M58+N58+O58+P58)*L58 -> 0 | R58: =G58+SUM(M58:Q58) -> 60000 | T58: =T$10 -> 0.05 | U58: 0.03 | V58: =V$10 -> 0.1 | W58: =R58*S58 -> 0 | X58: =R58*T58 -> 3000 | Y58: =R58*U58 -> 1800 | Z58: =(W58+X58)*V58 -> 300 | AA58: =R58+SUM(W58:Z58) -> 65100 | AB58: 75 | AC58: =IF(ISERROR(IF('Wainwright Summary'!$E$7-C58>AB58,0,(AB58-('Wainwright Summary'!$E$7-C58))/AB58)*G58)," ",(IF('Wainwright Summary'!$E$7-C58>AB58,0,(AB58-('Wainwright Summary'!$E$7-C58))/AB58)*G58)) -> 12800 | AD58: =VLOOKUP(C58,'Inflation-OLD'!$A$6:$B$126,2)/VLOOKUP('Wainwright Summary'!$E$6,'Inflation-OLD'!$A$6:$B$126,2) -> 0.14517825 | AE58: =IF(ISERROR(AA58*AD58), " ",AA58*AD58 ) -> 9451.1039 | AF58: =IF(ISERROR((AC58/G58)*AE58)," ",(AC58/G58)*AE58) -> 2016.2355 | AG58: 2060 | AJ58: =AB58 -> 75 | AK58: 10000 | AL58: 2024 | AM58: 1 | AR58: 60000 | AS58: =$AS$9 -> 1 | AT58: =AR58*AS58 -> 60000
